Workbook

Sheet Resumen
A1: PRESUPUESTO MENSUAL — DUBAI | D1: 0.24
A3: INGRESOS
A4: Salary 1 | B4: AED | C4: 25000
A5: Salary 2 | B5: AED | C5: 5000
A6: Adicional | B6: AED | C6: 1800
A7: TOTAL INGRESOS | C7: =SUM(C4:C6) -> 31800
A9: PREVISION GASTOS FIJOS
A10: Concepto | B10: AED | C10: EUR
A11: Alquiler Piso | B11: 8000 | C11: =B11*$D$1 -> 1920
A12: Compra Mensual | B12: 2800 | C12: =B12*$D$1 -> 672
A13: Coche (préstamo/pago) | B13: 2150 | C13: =B13*$D$1 -> 516
A14: DEWA (electricidad) | B14: 1200 | C14: =B14*$D$1 -> 288
A15: Gasolina y Salik | B15: 1000 | C15: =B15*$D$1 -> 240
A16: Seguro Bea | B16: 750 | C16: =B16*$D$1 -> 180
A17: Multas | B17: 500 | C17: =B17*$D$1 -> 120
A18: Nanny/Maid | B18: 0 | C18: =B18*$D$1 -> 0
A19: Móviles | B19: 320 | C19: =B19*$D$1 -> 76.8
A20: Internet | B20: 400 | C20: =B20*$D$1 -> 96
A21: Seguro Coche | B21: 300 | C21: =B21*$D$1 -> 72
A22: Visado Bea | B22: 200 | C22: =B22*$D$1 -> 48
... A25: Car Wash | B25: 100 | C25: =B25*$D$1 -> 24
A26: TOTAL GASTOS FIJOS | B26: =SUM(B11:B25) -> 18020 | C26: =SUM(C11:C25) -> 4324.8
A28: DISTRIBUCIÓN DEL INGRESO
A29: Total Ingresos | B29: =C7 -> 31800 | C29: =B29*$D$1 -> 7632
A30: (-) Gastos Fijos | B30: =B26 -> 18020 | C30: =C26 -> 4324.8
A31: (-) Ahorros | B31: =Ahorros!C14 -> 10800 | C31: =B31*$D$1 -> 2592
A32: = Disponible para Gastar | B32: =B29-B30-B31 -> 2980 | C32: =C29-C30-C31 -> 715.2
A34: RESUMEN ANUAL — GASTOS VARIABLES
A35: Mes | B35: Presupuesto | C35: Gastado | D35: Restante
A36: Enero | B36: =Resumen!$B$32 -> 2980 | C36: =Enero!C32 -> 0 | D36: =B36-C36 -> 2980
A37: Febrero | B37: =Resumen!$B$32 -> 2980 | C37: =Febrero!C32 -> 0 | D37: =B37-C37 -> 2980
A38: Marzo | B38: =Resumen!$B$32 -> 2980 | C38: =Marzo!C32 -> 0 | D38: =B38-C38 -> 2980
A39: Abril | B39: =Resumen!$B$32 -> 2980 | C39: =Abril!C32 -> 23465.167 | D39: =B39-C39 -> -20485.167
A40: Mayo | B40: =Resumen!$B$32 -> 2980 | C40: =Mayo!C32 -> 78371.572 | D40: =B40-C40 -> -75391.572
A41: Junio | B41: =Resumen!$B$32 -> 2980 | C41: =Junio!C32 -> 25618.3 | D41: =B41-C41 -> -22638.3
A42: Julio | B42: =Resumen!$B$32 -> 2980 | C42: =Julio!C32 -> 17112.102 | D42: =B42-C42 -> -14132.102
A43: Agosto | B43: =Resumen!$B$32 -> 2980 | C43: =Agosto!C32 -> 0 | D43: =B43-C43 -> 2980
A44: Septiembre | B44: =Resumen!$B$32 -> 2980 | C44: =Septiembre!C32 -> 0 | D44: =B44-C44 -> 2980
A45: Octubre | B45: =Resumen!$B$32 -> 2980 | C45: =Octubre!C32 -> 0 | D45: =B45-C45 -> 2980
A46: Noviembre | B46: =Resumen!$B$32 -> 2980 | C46: =Noviembre!C32 -> 0 | D46: =B46-C46 -> 2980
A47: Diciembre | B47: =Resumen!$B$32 -> 2980 | C47: =Diciembre!C32 -> 0 | D47: =B47-C47 -> 2980
A48: TOTAL ANUAL | B48: =SUM(B36:B47) -> 35760 | C48: =SUM(C36:C47) -> 144567.14 | D48: =B48-C48 -> -108807.14

Sheet Ahorros
A1: AHORROS E INVERSIONES
A3: CUENTAS DE AHORRO
A4: Cuenta | B4: Objetivo | C4: Contribución | D4: Saldo Inicial | E4: Saldo Final | F4: Saldo Final €
A5: Cuenta Corriente | B5: 0 | C5: 3000 | D5: 0 | E5: =C5+D5 -> 3000 | F5: =E5*Resumen!$D$1 -> 720
A6: Cuenta Inversiones | B6: 0 | C6: 6000 | D6: 0 | E6: =C6+D6 -> 6000 | F6: =E6*Resumen!$D$1 -> 1440
A7: Otros 1 | B7: 0 | C7: 0 | D7: 0 | E7: =C7+D7 -> 0 | F7: =E7*Resumen!$D$1 -> 0
A8: Otros 2 | B8: 0 | C8: 0 | D8: 0 | E8: =C8+D8 -> 0 | F8: =E8*Resumen!$D$1 -> 0
A9: Otros 3 | B9: 0 | C9: 0 | D9: 0 | E9: =C9+D9 -> 0 | F9: =E9*Resumen!$D$1 -> 0
A10: FONDOS DE EMERGENCIA
A11: Emergencias varias | B11: 0 | C11: 400 | D11: 0 | E11: =C11+D11 -> 400 | F11: =E11*Resumen!$D$1 -> 96
A12: Emergencia Médica | B12: 0 | C12: 1000 | D12: 0 | E12: =C12+D12 -> 1000 | F12: =E12*Resumen!$D$1 -> 240
A13: Emergencia Coche | B13: 0 | C13: 400 | D13: 0 | E13: =C13+D13 -> 400 | F13: =E13*Resumen!$D$1 -> 96
A14: TOTAL AHORRO | C14: =SUM(C5:C9)+SUM(C11:C13) -> 10800 | D14: =SUM(D5:D9)+SUM(D11:D13) -> 0 | E14: =SUM(E5:E9)+SUM(E11:E13) -> 10800 | F14: =E14*Resumen!$D$1 -> 2592
A16: PROVISIONES (Sinking Funds)
A17: Concepto | B17: Objetivo | C17: Contribución | D17: Saldo Inicial | E17: Saldo Final | F17: Saldo Final €
A18: Medicinas y gastos médicos | B18: 0 | C18: 0 | D18: 0 | E18: =C18+D18 -> 0 | F18: =E18*Resumen!$D$1 -> 0
A19: TOTAL PROVISIONES | C19: =SUM(C18:C18) -> 0 | D19: =SUM(D18:D18) -> 0 | E19: =SUM(E18:E18) -> 0 | F19: =E19*Resumen!$D$1 -> 0

Sheet Enero
A1: INGRESOS MENSUALES
A2: Concepto | C2: Total AED | D2: Total EUR
A3: Salario Santi | C3: =Resumen!$C$4 -> 25000 | D3: =C3*Resumen!$D$1 -> 6000
A4: Salario Bea | C4: =D4/Resumen!$D$1 -> 5000 | D4: =Resumen!$C$5*Resumen!$D$1 -> 1200
A5: Ingresos extra | C5: =D5/Resumen!$D$1 -> 1800 | D5: =Resumen!$C$6*Resumen!$D$1 -> 432
A6: TOTAL INGRESOS | C6: =SUM(C3:C5) -> 31800 | D6: =SUM(D3:D5) -> 7632
A7: BALANCE (Ingreso - Gasto) | C7: =C6-C32 -> 31800 | D7: =D6-D32 -> 7632
A9: GASTOS MENSUALES
A11: RESUMEN POR CATEGORÍA
A12: Categoría | B12: Nº Gastos | C12: Total AED | D12: Total EUR
A13: Restaurantes | B13: =COUNTIF(B37:B56,A13)+COUNTIF(G37:G56,A13)+COUNTIF(L37:L56,A13)+COUNTIF(Q37:Q56,A13)+COUNTIF(V37:V56,A13) -> 0 | C13: =SUMIF(B37:B56,A13,C37:C56)+SUMIF(G37:G56,A13,H37:H56)+SUMIF(L37:L56,A13,M37:M56)+SUMIF(Q37:Q56,A13,R37:R56)+SUMIF(V37:V56,A13,W37:W56)+(SUMIF(B37:B56,A13,D37:D56)+SUMIF(G37:G56,A13,I37:I56)+SUMIF(L37:L56,A13,N37:N56)+SUMIF(Q37:Q56,A13,S37:S56)+SUMIF(V37:V56,A13,X37:X56))/Resumen!$D$1 -> 0 | D13: =C13*Resumen!$D$1 -> 0
A14: Ocio | B14: =COUNTIF(B37:B56,A14)+COUNTIF(G37:G56,A14)+COUNTIF(L37:L56,A14)+COUNTIF(Q37:Q56,A14)+COUNTIF(V37:V56,A14) -> 0 | C14: =SUMIF(B37:B56,A14,C37:C56)+SUMIF(G37:G56,A14,H37:H56)+SUMIF(L37:L56,A14,M37:M56)+SUMIF(Q37:Q56,A14,R37:R56)+SUMIF(V37:V56,A14,W37:W56)+(SUMIF(B37:B56,A14,D37:D56)+SUMIF(G37:G56,A14,I37:I56)+SUMIF(L37:L56,A14,N37:N56)+SUMIF(Q37:Q56,A14,S37:S56)+SUMIF(V37:V56,A14,X37:X56))/Resumen!$D$1 -> 0 | D14: =C14*Resumen!$D$1 -> 0
A15: Compras | B15: 0 | C15: 0 | D15: =C15*Resumen!$D$1 -> 0
A16: Salud | B16: =COUNTIF(B37:B56,A16)+COUNTIF(G37:G56,A16)+COUNTIF(L37:L56,A16)+COUNTIF(Q37:Q56,A16)+COUNTIF(V37:V56,A16) -> 0 | C16: =SUMIF(B37:B56,A16,C37:C56)+SUMIF(G37:G56,A16,H37:H56)+SUMIF(L37:L56,A16,M37:M56)+SUMIF(Q37:Q56,A16,R37:R56)+SUMIF(V37:V56,A16,W37:W56)+(SUMIF(B37:B56,A16,D37:D56)+SUMIF(G37:G56,A16,I37:I56)+SUMIF(L37:L56,A16,N37:N56)+SUMIF(Q37:Q56,A16,S37:S56)+SUMIF(V37:V56,A16,X37:X56))/Resumen!$D$1 -> 0 | D16: =C16*Resumen!$D$1 -> 0
A17: Viajes | B17: =COUNTIF(B37:B56,A17)+COUNTIF(G37:G56,A17)+COUNTIF(L37:L56,A17)+COUNTIF(Q37:Q56,A17)+COUNTIF(V37:V56,A17) -> 0 | C17: =SUMIF(B37:B56,A17,C37:C56)+SUMIF(G37:G56,A17,H37:H56)+SUMIF(L37:L56,A17,M37:M56)+SUMIF(Q37:Q56,A17,R37:R56)+SUMIF(V37:V56,A17,W37:W56)+(SUMIF(B37:B56,A17,D37:D56)+SUMIF(G37:G56,A17,I37:I56)+SUMIF(L37:L56,A17,N37:N56)+SUMIF(Q37:Q56,A17,S37:S56)+SUMIF(V37:V56,A17,X37:X56))/Resumen!$D$1 -> 0 | D17: =C17*Resumen!$D$1 -> 0
A18: Santi | B18: =COUNTIF(B37:B56,A18)+COUNTIF(G37:G56,A18)+COUNTIF(L37:L56,A18)+COUNTIF(Q37:Q56,A18)+COUNTIF(V37:V56,A18) -> 0 | C18: =SUMIF(B37:B56,A18,C37:C56)+SUMIF(G37:G56,A18,H37:H56)+SUMIF(L37:L56,A18,M37:M56)+SUMIF(Q37:Q56,A18,R37:R56)+SUMIF(V37:V56,A18,W37:W56)+(SUMIF(B37:B56,A18,D37:D56)+SUMIF(G37:G56,A18,I37:I56)+SUMIF(L37:L56,A18,N37:N56)+SUMIF(Q37:Q56,A18,S37:S56)+SUMIF(V37:V56,A18,X37:X56))/Resumen!$D$1 -> 0 | D18: =C18*Resumen!$D$1 -> 0
A19: Bea | B19: =COUNTIF(B37:B56,A19)+COUNTIF(G37:G56,A19)+COUNTIF(L37:L56,A19)+COUNTIF(Q37:Q56,A19)+COUNTIF(V37:V56,A19) -> 0 | C19: =SUMIF(B37:B56,A19,C37:C56)+SUMIF(G37:G56,A19,H37:H56)+SUMIF(L37:L56,A19,M37:M56)+SUMIF(Q37:Q56,A19,R37:R56)+SUMIF(V37:V56,A19,W37:W56)+(SUMIF(B37:B56,A19,D37:D56)+SUMIF(G37:G56,A19,I37:I56)+SUMIF(L37:L56,A19,N37:N56)+SUMIF(Q37:Q56,A19,S37:S56)+SUMIF(V37:V56,A19,X37:X56))/Resumen!$D$1 -> 0 | D19: =C19*Resumen!$D$1 -> 0
A20: Personal | B20: =COUNTIF(B37:B56,A20)+COUNTIF(G37:G56,A20)+COUNTIF(L37:L56,A20)+COUNTIF(Q37:Q56,A20)+COUNTIF(V37:V56,A20) -> 0 | C20: =SUMIF(B37:B56,A20,C37:C56)+SUMIF(G37:G56,A20,H37:H56)+SUMIF(L37:L56,A20,M37:M56)+SUMIF(Q37:Q56,A20,R37:R56)+SUMIF(V37:V56,A20,W37:W56)+(SUMIF(B37:B56,A20,D37:D56)+SUMIF(G37:G56,A20,I37:I56)+SUMIF(L37:L56,A20,N37:N56)+SUMIF(Q37:Q56,A20,S37:S56)+SUMIF(V37:V56,A20,X37:X56))/Resumen!$D$1 -> 0 | D20: =C20*Resumen!$D$1 -> 0
A21: Transporte | B21: =COUNTIF(B37:B56,A21)+COUNTIF(G37:G56,A21)+COUNTIF(L37:L56,A21)+COUNTIF(Q37:Q56,A21)+COUNTIF(V37:V56,A21) -> 0 | C21: =SUMIF(B37:B56,A21,C37:C56)+SUMIF(G37:G56,A21,H37:H56)+SUMIF(L37:L56,A21,M37:M56)+SUMIF(Q37:Q56,A21,R37:R56)+SUMIF(V37:V56,A21,W37:W56)+(SUMIF(B37:B56,A21,D37:D56)+SUMIF(G37:G56,A21,I37:I56)+SUMIF(L37:L56,A21,N37:N56)+SUMIF(Q37:Q56,A21,S37:S56)+SUMIF(V37:V56,A21,X37:X56))/Resumen!$D$1 -> 0 | D21: =C21*Resumen!$D$1 -> 0
A22: Regalos | B22: =COUNTIF(B37:B56,A22)+COUNTIF(G37:G56,A22)+COUNTIF(L37:L56,A22)+COUNTIF(Q37:Q56,A22)+COUNTIF(V37:V56,A22) -> 0 | C22: =SUMIF(B37:B56,A22,C37:C56)+SUMIF(G37:G56,A22,H37:H56)+SUMIF(L37:L56,A22,M37:M56)+SUMIF(Q37:Q56,A22,R37:R56)+SUMIF(V37:V56,A22,W37:W56)+(SUMIF(B37:B56,A22,D37:D56)+SUMIF(G37:G56,A22,I37:I56)+SUMIF(L37:L56,A22,N37:N56)+SUMIF(Q37:Q56,A22,S37:S56)+SUMIF(V37:V56,A22,X37:X56))/Resumen!$D$1 -> 0 | D22: =C22*Resumen!$D$1 -> 0
A23: Alquiler piso | B23: =COUNTIF(B37:B56,A23)+COUNTIF(G37:G56,A23)+COUNTIF(L37:L56,A23)+COUNTIF(Q37:Q56,A23)+COUNTIF(V37:V56,A23) -> 0 | C23: =SUMIF(B37:B56,A23,C37:C56)+SUMIF(G37:G56,A23,H37:H56)+SUMIF(L37:L56,A23,M37:M56)+SUMIF(Q37:Q56,A23,R37:R56)+SUMIF(V37:V56,A23,W37:W56)+(SUMIF(B37:B56,A23,D37:D56)+SUMIF(G37:G56,A23,I37:I56)+SUMIF(L37:L56,A23,N37:N56)+SUMIF(Q37:Q56,A23,S37:S56)+SUMIF(V37:V56,A23,X37:X56))/Resumen!$D$1 -> 0 | D23: =C23*Resumen!$D$1 -> 0
A24: Mudanza | B24: =COUNTIF(B37:B56,A24)+COUNTIF(G37:G56,A24)+COUNTIF(L37:L56,A24)+COUNTIF(Q37:Q56,A24)+COUNTIF(V37:V56,A24) -> 0 | C24: =SUMIF(B37:B56,A24,C37:C56)+SUMIF(G37:G56,A24,H37:H56)+SUMIF(L37:L56,A24,M37:M56)+SUMIF(Q37:Q56,A24,R37:R56)+SUMIF(V37:V56,A24,W37:W56)+(SUMIF(B37:B56,A24,D37:D56)+SUMIF(G37:G56,A24,I37:I56)+SUMIF(L37:L56,A24,N37:N56)+SUMIF(Q37:Q56,A24,S37:S56)+SUMIF(V37:V56,A24,X37:X56))/Resumen!$D$1 -> 0 | D24: =C24*Resumen!$D$1 -> 0
A25: Tasas | B25: =COUNTIF(B37:B56,A25)+COUNTIF(G37:G56,A25)+COUNTIF(L37:L56,A25)+COUNTIF(Q37:Q56,A25)+COUNTIF(V37:V56,A25) -> 0 | C25: =SUMIF(B37:B56,A25,C37:C56)+SUMIF(G37:G56,A25,H37:H56)+SUMIF(L37:L56,A25,M37:M56)+SUMIF(Q37:Q56,A25,R37:R56)+SUMIF(V37:V56,A25,W37:W56)+(SUMIF(B37:B56,A25,D37:D56)+SUMIF(G37:G56,A25,I37:I56)+SUMIF(L37:L56,A25,N37:N56)+SUMIF(Q37:Q56,A25,S37:S56)+SUMIF(V37:V56,A25,X37:X56))/Resumen!$D$1 -> 0 | D25: =C25*Resumen!$D$1 -> 0
A26: Suministros piso | B26: =COUNTIF(B37:B56,A26)+COUNTIF(G37:G56,A26)+COUNTIF(L37:L56,A26)+COUNTIF(Q37:Q56,A26)+COUNTIF(V37:V56,A26) -> 0 | C26: =SUMIF(B37:B56,A26,C37:C56)+SUMIF(G37:G56,A26,H37:H56)+SUMIF(L37:L56,A26,M37:M56)+SUMIF(Q37:Q56,A26,R37:R56)+SUMIF(V37:V56,A26,W37:W56)+(SUMIF(B37:B56,A26,D37:D56)+SUMIF(G37:G56,A26,I37:I56)+SUMIF(L37:L56,A26,N37:N56)+SUMIF(Q37:Q56,A26,S37:S56)+SUMIF(V37:V56,A26,X37:X56))/Resumen!$D$1 -> 0 | D26: =C26*Resumen!$D$1 -> 0
A27: Otros | B27: =COUNTIF(B37:B56,A27)+COUNTIF(G37:G56,A27)+COUNTIF(L37:L56,A27)+COUNTIF(Q37:Q56,A27)+COUNTIF(V37:V56,A27) -> 0 | C27: =SUMIF(B37:B56,A27,C37:C56)+SUMIF(G37:G56,A27,H37:H56)+SUMIF(L37:L56,A27,M37:M56)+SUMIF(Q37:Q56,A27,R37:R56)+SUMIF(V37:V56,A27,W37:W56)+(SUMIF(B37:B56,A27,D37:D56)+SUMIF(G37:G56,A27,I37:I56)+SUMIF(L37:L56,A27,N37:N56)+SUMIF(Q37:Q56,A27,S37:S56)+SUMIF(V37:V56,A27,X37:X56))/Resumen!$D$1 -> 0 | D27: =C27*Resumen!$D$1 -> 0
A28: Hogar | B28: =COUNTIF(B37:B56,A28)+COUNTIF(G37:G56,A28)+COUNTIF(L37:L56,A28)+COUNTIF(Q37:Q56,A28)+COUNTIF(V37:V56,A28) -> 0 | C28: =SUMIF(B37:B56,A28,C37:C56)+SUMIF(G37:G56,A28,H37:H56)+SUMIF(L37:L56,A28,M37:M56)+SUMIF(Q37:Q56,A28,R37:R56)+SUMIF(V37:V56,A28,W37:W56)+(SUMIF(B37:B56,A28,D37:D56)+SUMIF(G37:G56,A28,I37:I56)+SUMIF(L37:L56,A28,N37:N56)+SUMIF(Q37:Q56,A28,S37:S56)+SUMIF(V37:V56,A28,X37:X56))/Resumen!$D$1 -> 0 | D28: =C28*Resumen!$D$1 -> 0
A29: Delivery | B29: =COUNTIF(B37:B56,A29)+COUNTIF(G37:G56,A29)+COUNTIF(L37:L56,A29)+COUNTIF(Q37:Q56,A29)+COUNTIF(V37:V56,A29) -> 0 | C29: =SUMIF(B37:B56,A29,C37:C56)+SUMIF(G37:G56,A29,H37:H56)+SUMIF(L37:L56,A29,M37:M56)+SUMIF(Q37:Q56,A29,R37:R56)+SUMIF(V37:V56,A29,W37:W56)+(SUMIF(B37:B56,A29,D37:D56)+SUMIF(G37:G56,A29,I37:I56)+SUMIF(L37:L56,A29,N37:N56)+SUMIF(Q37:Q56,A29,S37:S56)+SUMIF(V37:V56,A29,X37:X56))/Resumen!$D$1 -> 0 | D29: =C29*Resumen!$D$1 -> 0
A30: Supermercado | B30: =COUNTIF(B37:B56,A30)+COUNTIF(G37:G56,A30)+COUNTIF(L37:L56,A30)+COUNTIF(Q37:Q56,A30)+COUNTIF(V37:V56,A30) -> 0 | C30: =SUMIF(B37:B56,A30,C37:C56)+SUMIF(G37:G56,A30,H37:H56)+SUMIF(L37:L56,A30,M37:M56)+SUMIF(Q37:Q56,A30,R37:R56)+SUMIF(V37:V56,A30,W37:W56)+(SUMIF(B37:B56,A30,D37:D56)+SUMIF(G37:G56,A30,I37:I56)+SUMIF(L37:L56,A30,N37:N56)+SUMIF(Q37:Q56,A30,S37:S56)+SUMIF(V37:V56,A30,X37:X56))/Resumen!$D$1 -> 0 | D30: =C30*Resumen!$D$1 -> 0
A31: Suscripciones | B31: =COUNTIF(B37:B56,A31)+COUNTIF(G37:G56,A31)+COUNTIF(L37:L56,A31)+COUNTIF(Q37:Q56,A31)+COUNTIF(V37:V56,A31) -> 0 | C31: =SUMIF(B37:B56,A31,C37:C56)+SUMIF(G37:G56,A31,H37:H56)+SUMIF(L37:L56,A31,M37:M56)+SUMIF(Q37:Q56,A31,R37:R56)+SUMIF(V37:V56,A31,W37:W56)+(SUMIF(B37:B56,A31,D37:D56)+SUMIF(G37:G56,A31,I37:I56)+SUMIF(L37:L56,A31,N37:N56)+SUMIF(Q37:Q56,A31,S37:S56)+SUMIF(V37:V56,A31,X37:X56))/Resumen!$D$1 -> 0 | D31: =C31*Resumen!$D$1 -> 0
A32: TOTAL MES | B32: =SUM(B13:B31) -> 0 | C32: =SUM(C13:C31) -> 0 | D32: =SUM(D13:D31) -> 0
A34: REGISTRO SEMANAL
A35: SEMANA 1 | F35: SEMANA 2 | K35: SEMANA 3 | P35: SEMANA 4 | U35: SEMANA 5
A36: Concepto | B36: Categ. | C36: AED | D36: EUR | E36: Fecha | F36: Concepto | G36: Categ. | H36: AED | I36: EUR | J36: Fecha | K36: Concepto | L36: Categ. | M36: AED | N36: EUR | O36: Fecha | P36: Concepto | Q36: Categ. | R36: AED | S36: EUR | T36: Fecha | U36: Concepto | V36: Categ. | W36: AED | X36: EUR
A37: Sofa y mesa café | B37: Compras | C37: 821.61
A57: TOTAL | C57: =SUM(C37:C56)+SUM(D37:D56)/Resumen!$D$1 -> 821.61 | D57: =SUM(D37:D56)+SUM(C37:C56)*Resumen!$D$1 -> 197.1864 | H57: =SUM(H37:H56)+SUM(I37:I56)/Resumen!$D$1 -> 0 | I57: =SUM(I37:I56)+SUM(H37:H56)*Resumen!$D$1 -> 0 | M57: =SUM(M37:M56)+SUM(N37:N56)/Resumen!$D$1 -> 0 | N57: =SUM(N37:N56)+SUM(M37:M56)*Resumen!$D$1 -> 0 | R57: =SUM(R37:R56)+SUM(S37:S56)/Resumen!$D$1 -> 0 | S57: =SUM(S37:S56)+SUM(R37:R56)*Resumen!$D$1 -> 0 | W57: =SUM(W37:W56)+SUM(X37:X56)/Resumen!$D$1 -> 0 | X57: =SUM(X37:X56)+SUM(W37:W56)*Resumen!$D$1 -> 0
A58: RESTANTE | C58: =Resumen!$B$32-C57 -> 2158.39 | D58: =Resumen!$C$32-D57 -> 518.0136 | H58: =C58-H57 -> 2158.39 | I58: =D58-I57 -> 518.0136 | M58: =H58-M57 -> 2158.39 | N58: =I58-N57 -> 518.0136 | R58: =M58-R57 -> 2158.39 | S58: =N58-S57 -> 518.0136 | W58: =R58-W57 -> 2158.39 | X58: =S58-X57 -> 518.0136

Sheet Febrero
A1: INGRESOS MENSUALES
A2: Concepto | C2: Total AED | D2: Total EUR
A3: Salario Santi | C3: =Resumen!$C$4 -> 25000 | D3: =C3*Resumen!$D$1 -> 6000
A4: Salario Bea | C4: =D4/Resumen!$D$1 -> 5000 | D4: =Resumen!$C$5*Resumen!$D$1 -> 1200
A5: Ingresos extra | C5: =D5/Resumen!$D$1 -> 1800 | D5: =Resumen!$C$6*Resumen!$D$1 -> 432
A6: TOTAL INGRESOS | C6: =SUM(C3:C5) -> 31800 | D6: =SUM(D3:D5) -> 7632
A7: BALANCE (Ingreso - Gasto) | C7: =C6-C32 -> 31800 | D7: =D6-D32 -> 7632
A9: GASTOS MENSUALES
A11: RESUMEN POR CATEGORÍA
A12: Categoría | B12: Nº Gastos | C12: Total AED | D12: Total EUR
A13: Restaurantes | B13: =COUNTIF(B37:B56,A13)+COUNTIF(G37:G56,A13)+COUNTIF(L37:L56,A13)+COUNTIF(Q37:Q56,A13)+COUNTIF(V37:V56,A13) -> 0 | C13: =SUMIF(B37:B56,A13,C37:C56)+SUMIF(G37:G56,A13,H37:H56)+SUMIF(L37:L56,A13,M37:M56)+SUMIF(Q37:Q56,A13,R37:R56)+SUMIF(V37:V56,A13,W37:W56)+(SUMIF(B37:B56,A13,D37:D56)+SUMIF(G37:G56,A13,I37:I56)+SUMIF(L37:L56,A13,N37:N56)+SUMIF(Q37:Q56,A13,S37:S56)+SUMIF(V37:V56,A13,X37:X56))/Resumen!$D$1 -> 0 | D13: =C13*Resumen!$D$1 -> 0
A14: Ocio | B14: =COUNTIF(B37:B56,A14)+COUNTIF(G37:G56,A14)+COUNTIF(L37:L56,A14)+COUNTIF(Q37:Q56,A14)+COUNTIF(V37:V56,A14) -> 0 | C14: =SUMIF(B37:B56,A14,C37:C56)+SUMIF(G37:G56,A14,H37:H56)+SUMIF(L37:L56,A14,M37:M56)+SUMIF(Q37:Q56,A14,R37:R56)+SUMIF(V37:V56,A14,W37:W56)+(SUMIF(B37:B56,A14,D37:D56)+SUMIF(G37:G56,A14,I37:I56)+SUMIF(L37:L56,A14,N37:N56)+SUMIF(Q37:Q56,A14,S37:S56)+SUMIF(V37:V56,A14,X37:X56))/Resumen!$D$1 -> 0 | D14: =C14*Resumen!$D$1 -> 0
A15: Compras | B15: =COUNTIF(B37:B56,A15)+COUNTIF(G37:G56,A15)+COUNTIF(L37:L56,A15)+COUNTIF(Q37:Q56,A15)+COUNTIF(V37:V56,A15) -> 0 | C15: =SUMIF(B37:B56,A15,C37:C56)+SUMIF(G37:G56,A15,H37:H56)+SUMIF(L37:L56,A15,M37:M56)+SUMIF(Q37:Q56,A15,R37:R56)+SUMIF(V37:V56,A15,W37:W56)+(SUMIF(B37:B56,A15,D37:D56)+SUMIF(G37:G56,A15,I37:I56)+SUMIF(L37:L56,A15,N37:N56)+SUMIF(Q37:Q56,A15,S37:S56)+SUMIF(V37:V56,A15,X37:X56))/Resumen!$D$1 -> 0 | D15: =C15*Resumen!$D$1 -> 0
A16: Salud | B16: =COUNTIF(B37:B56,A16)+COUNTIF(G37:G56,A16)+COUNTIF(L37:L56,A16)+COUNTIF(Q37:Q56,A16)+COUNTIF(V37:V56,A16) -> 0 | C16: =SUMIF(B37:B56,A16,C37:C56)+SUMIF(G37:G56,A16,H37:H56)+SUMIF(L37:L56,A16,M37:M56)+SUMIF(Q37:Q56,A16,R37:R56)+SUMIF(V37:V56,A16,W37:W56)+(SUMIF(B37:B56,A16,D37:D56)+SUMIF(G37:G56,A16,I37:I56)+SUMIF(L37:L56,A16,N37:N56)+SUMIF(Q37:Q56,A16,S37:S56)+SUMIF(V37:V56,A16,X37:X56))/Resumen!$D$1 -> 0 | D16: =C16*Resumen!$D$1 -> 0
A17: Viajes | B17: =COUNTIF(B37:B56,A17)+COUNTIF(G37:G56,A17)+COUNTIF(L37:L56,A17)+COUNTIF(Q37:Q56,A17)+COUNTIF(V37:V56,A17) -> 0 | C17: =SUMIF(B37:B56,A17,C37:C56)+SUMIF(G37:G56,A17,H37:H56)+SUMIF(L37:L56,A17,M37:M56)+SUMIF(Q37:Q56,A17,R37:R56)+SUMIF(V37:V56,A17,W37:W56)+(SUMIF(B37:B56,A17,D37:D56)+SUMIF(G37:G56,A17,I37:I56)+SUMIF(L37:L56,A17,N37:N56)+SUMIF(Q37:Q56,A17,S37:S56)+SUMIF(V37:V56,A17,X37:X56))/Resumen!$D$1 -> 0 | D17: =C17*Resumen!$D$1 -> 0
A18: Santi | B18: =COUNTIF(B37:B56,A18)+COUNTIF(G37:G56,A18)+COUNTIF(L37:L56,A18)+COUNTIF(Q37:Q56,A18)+COUNTIF(V37:V56,A18) -> 0 | C18: =SUMIF(B37:B56,A18,C37:C56)+SUMIF(G37:G56,A18,H37:H56)+SUMIF(L37:L56,A18,M37:M56)+SUMIF(Q37:Q56,A18,R37:R56)+SUMIF(V37:V56,A18,W37:W56)+(SUMIF(B37:B56,A18,D37:D56)+SUMIF(G37:G56,A18,I37:I56)+SUMIF(L37:L56,A18,N37:N56)+SUMIF(Q37:Q56,A18,S37:S56)+SUMIF(V37:V56,A18,X37:X56))/Resumen!$D$1 -> 0 | D18: =C18*Resumen!$D$1 -> 0
A19: Bea | B19: =COUNTIF(B37:B56,A19)+COUNTIF(G37:G56,A19)+COUNTIF(L37:L56,A19)+COUNTIF(Q37:Q56,A19)+COUNTIF(V37:V56,A19) -> 0 | C19: =SUMIF(B37:B56,A19,C37:C56)+SUMIF(G37:G56,A19,H37:H56)+SUMIF(L37:L56,A19,M37:M56)+SUMIF(Q37:Q56,A19,R37:R56)+SUMIF(V37:V56,A19,W37:W56)+(SUMIF(B37:B56,A19,D37:D56)+SUMIF(G37:G56,A19,I37:I56)+SUMIF(L37:L56,A19,N37:N56)+SUMIF(Q37:Q56,A19,S37:S56)+SUMIF(V37:V56,A19,X37:X56))/Resumen!$D$1 -> 0 | D19: =C19*Resumen!$D$1 -> 0
A20: Personal | B20: =COUNTIF(B37:B56,A20)+COUNTIF(G37:G56,A20)+COUNTIF(L37:L56,A20)+COUNTIF(Q37:Q56,A20)+COUNTIF(V37:V56,A20) -> 0 | C20: =SUMIF(B37:B56,A20,C37:C56)+SUMIF(G37:G56,A20,H37:H56)+SUMIF(L37:L56,A20,M37:M56)+SUMIF(Q37:Q56,A20,R37:R56)+SUMIF(V37:V56,A20,W37:W56)+(SUMIF(B37:B56,A20,D37:D56)+SUMIF(G37:G56,A20,I37:I56)+SUMIF(L37:L56,A20,N37:N56)+SUMIF(Q37:Q56,A20,S37:S56)+SUMIF(V37:V56,A20,X37:X56))/Resumen!$D$1 -> 0 | D20: =C20*Resumen!$D$1 -> 0
A21: Transporte | B21: =COUNTIF(B37:B56,A21)+COUNTIF(G37:G56,A21)+COUNTIF(L37:L56,A21)+COUNTIF(Q37:Q56,A21)+COUNTIF(V37:V56,A21) -> 0 | C21: =SUMIF(B37:B56,A21,C37:C56)+SUMIF(G37:G56,A21,H37:H56)+SUMIF(L37:L56,A21,M37:M56)+SUMIF(Q37:Q56,A21,R37:R56)+SUMIF(V37:V56,A21,W37:W56)+(SUMIF(B37:B56,A21,D37:D56)+SUMIF(G37:G56,A21,I37:I56)+SUMIF(L37:L56,A21,N37:N56)+SUMIF(Q37:Q56,A21,S37:S56)+SUMIF(V37:V56,A21,X37:X56))/Resumen!$D$1 -> 0 | D21: =C21*Resumen!$D$1 -> 0
A22: Regalos | B22: =COUNTIF(B37:B56,A22)+COUNTIF(G37:G56,A22)+COUNTIF(L37:L56,A22)+COUNTIF(Q37:Q56,A22)+COUNTIF(V37:V56,A22) -> 0 | C22: =SUMIF(B37:B56,A22,C37:C56)+SUMIF(G37:G56,A22,H37:H56)+SUMIF(L37:L56,A22,M37:M56)+SUMIF(Q37:Q56,A22,R37:R56)+SUMIF(V37:V56,A22,W37:W56)+(SUMIF(B37:B56,A22,D37:D56)+SUMIF(G37:G56,A22,I37:I56)+SUMIF(L37:L56,A22,N37:N56)+SUMIF(Q37:Q56,A22,S37:S56)+SUMIF(V37:V56,A22,X37:X56))/Resumen!$D$1 -> 0 | D22: =C22*Resumen!$D$1 -> 0
A23: Alquiler piso | B23: =COUNTIF(B37:B56,A23)+COUNTIF(G37:G56,A23)+COUNTIF(L37:L56,A23)+COUNTIF(Q37:Q56,A23)+COUNTIF(V37:V56,A23) -> 0 | C23: =SUMIF(B37:B56,A23,C37:C56)+SUMIF(G37:G56,A23,H37:H56)+SUMIF(L37:L56,A23,M37:M56)+SUMIF(Q37:Q56,A23,R37:R56)+SUMIF(V37:V56,A23,W37:W56)+(SUMIF(B37:B56,A23,D37:D56)+SUMIF(G37:G56,A23,I37:I56)+SUMIF(L37:L56,A23,N37:N56)+SUMIF(Q37:Q56,A23,S37:S56)+SUMIF(V37:V56,A23,X37:X56))/Resumen!$D$1 -> 0 | D23: =C23*Resumen!$D$1 -> 0
A24: Mudanza | B24: =COUNTIF(B37:B56,A24)+COUNTIF(G37:G56,A24)+COUNTIF(L37:L56,A24)+COUNTIF(Q37:Q56,A24)+COUNTIF(V37:V56,A24) -> 0 | C24: =SUMIF(B37:B56,A24,C37:C56)+SUMIF(G37:G56,A24,H37:H56)+SUMIF(L37:L56,A24,M37:M56)+SUMIF(Q37:Q56,A24,R37:R56)+SUMIF(V37:V56,A24,W37:W56)+(SUMIF(B37:B56,A24,D37:D56)+SUMIF(G37:G56,A24,I37:I56)+SUMIF(L37:L56,A24,N37:N56)+SUMIF(Q37:Q56,A24,S37:S56)+SUMIF(V37:V56,A24,X37:X56))/Resumen!$D$1 -> 0 | D24: =C24*Resumen!$D$1 -> 0
A25: Tasas | B25: =COUNTIF(B37:B56,A25)+COUNTIF(G37:G56,A25)+COUNTIF(L37:L56,A25)+COUNTIF(Q37:Q56,A25)+COUNTIF(V37:V56,A25) -> 0 | C25: =SUMIF(B37:B56,A25,C37:C56)+SUMIF(G37:G56,A25,H37:H56)+SUMIF(L37:L56,A25,M37:M56)+SUMIF(Q37:Q56,A25,R37:R56)+SUMIF(V37:V56,A25,W37:W56)+(SUMIF(B37:B56,A25,D37:D56)+SUMIF(G37:G56,A25,I37:I56)+SUMIF(L37:L56,A25,N37:N56)+SUMIF(Q37:Q56,A25,S37:S56)+SUMIF(V37:V56,A25,X37:X56))/Resumen!$D$1 -> 0 | D25: =C25*Resumen!$D$1 -> 0
A26: Suministros piso | B26: =COUNTIF(B37:B56,A26)+COUNTIF(G37:G56,A26)+COUNTIF(L37:L56,A26)+COUNTIF(Q37:Q56,A26)+COUNTIF(V37:V56,A26) -> 0 | C26: =SUMIF(B37:B56,A26,C37:C56)+SUMIF(G37:G56,A26,H37:H56)+SUMIF(L37:L56,A26,M37:M56)+SUMIF(Q37:Q56,A26,R37:R56)+SUMIF(V37:V56,A26,W37:W56)+(SUMIF(B37:B56,A26,D37:D56)+SUMIF(G37:G56,A26,I37:I56)+SUMIF(L37:L56,A26,N37:N56)+SUMIF(Q37:Q56,A26,S37:S56)+SUMIF(V37:V56,A26,X37:X56))/Resumen!$D$1 -> 0 | D26: =C26*Resumen!$D$1 -> 0
A27: Otros | B27: =COUNTIF(B37:B56,A27)+COUNTIF(G37:G56,A27)+COUNTIF(L37:L56,A27)+COUNTIF(Q37:Q56,A27)+COUNTIF(V37:V56,A27) -> 0 | C27: =SUMIF(B37:B56,A27,C37:C56)+SUMIF(G37:G56,A27,H37:H56)+SUMIF(L37:L56,A27,M37:M56)+SUMIF(Q37:Q56,A27,R37:R56)+SUMIF(V37:V56,A27,W37:W56)+(SUMIF(B37:B56,A27,D37:D56)+SUMIF(G37:G56,A27,I37:I56)+SUMIF(L37:L56,A27,N37:N56)+SUMIF(Q37:Q56,A27,S37:S56)+SUMIF(V37:V56,A27,X37:X56))/Resumen!$D$1 -> 0 | D27: =C27*Resumen!$D$1 -> 0
A28: Hogar | B28: =COUNTIF(B37:B56,A28)+COUNTIF(G37:G56,A28)+COUNTIF(L37:L56,A28)+COUNTIF(Q37:Q56,A28)+COUNTIF(V37:V56,A28) -> 0 | C28: =SUMIF(B37:B56,A28,C37:C56)+SUMIF(G37:G56,A28,H37:H56)+SUMIF(L37:L56,A28,M37:M56)+SUMIF(Q37:Q56,A28,R37:R56)+SUMIF(V37:V56,A28,W37:W56)+(SUMIF(B37:B56,A28,D37:D56)+SUMIF(G37:G56,A28,I37:I56)+SUMIF(L37:L56,A28,N37:N56)+SUMIF(Q37:Q56,A28,S37:S56)+SUMIF(V37:V56,A28,X37:X56))/Resumen!$D$1 -> 0 | D28: =C28*Resumen!$D$1 -> 0
A29: Delivery | B29: =COUNTIF(B37:B56,A29)+COUNTIF(G37:G56,A29)+COUNTIF(L37:L56,A29)+COUNTIF(Q37:Q56,A29)+COUNTIF(V37:V56,A29) -> 0 | C29: =SUMIF(B37:B56,A29,C37:C56)+SUMIF(G37:G56,A29,H37:H56)+SUMIF(L37:L56,A29,M37:M56)+SUMIF(Q37:Q56,A29,R37:R56)+SUMIF(V37:V56,A29,W37:W56)+(SUMIF(B37:B56,A29,D37:D56)+SUMIF(G37:G56,A29,I37:I56)+SUMIF(L37:L56,A29,N37:N56)+SUMIF(Q37:Q56,A29,S37:S56)+SUMIF(V37:V56,A29,X37:X56))/Resumen!$D$1 -> 0 | D29: =C29*Resumen!$D$1 -> 0
A30: Supermercado | B30: =COUNTIF(B37:B56,A30)+COUNTIF(G37:G56,A30)+COUNTIF(L37:L56,A30)+COUNTIF(Q37:Q56,A30)+COUNTIF(V37:V56,A30) -> 0 | C30: =SUMIF(B37:B56,A30,C37:C56)+SUMIF(G37:G56,A30,H37:H56)+SUMIF(L37:L56,A30,M37:M56)+SUMIF(Q37:Q56,A30,R37:R56)+SUMIF(V37:V56,A30,W37:W56)+(SUMIF(B37:B56,A30,D37:D56)+SUMIF(G37:G56,A30,I37:I56)+SUMIF(L37:L56,A30,N37:N56)+SUMIF(Q37:Q56,A30,S37:S56)+SUMIF(V37:V56,A30,X37:X56))/Resumen!$D$1 -> 0 | D30: =C30*Resumen!$D$1 -> 0
A31: Suscripciones | B31: =COUNTIF(B37:B56,A31)+COUNTIF(G37:G56,A31)+COUNTIF(L37:L56,A31)+COUNTIF(Q37:Q56,A31)+COUNTIF(V37:V56,A31) -> 0 | C31: =SUMIF(B37:B56,A31,C37:C56)+SUMIF(G37:G56,A31,H37:H56)+SUMIF(L37:L56,A31,M37:M56)+SUMIF(Q37:Q56,A31,R37:R56)+SUMIF(V37:V56,A31,W37:W56)+(SUMIF(B37:B56,A31,D37:D56)+SUMIF(G37:G56,A31,I37:I56)+SUMIF(L37:L56,A31,N37:N56)+SUMIF(Q37:Q56,A31,S37:S56)+SUMIF(V37:V56,A31,X37:X56))/Resumen!$D$1 -> 0 | D31: =C31*Resumen!$D$1 -> 0
A32: TOTAL MES | B32: =SUM(B13:B31) -> 0 | C32: =SUM(C13:C31) -> 0 | D32: =SUM(D13:D31) -> 0
A34: REGISTRO SEMANAL
A35: SEMANA 1 | F35: SEMANA 2 | K35: SEMANA 3 | P35: SEMANA 4 | U35: SEMANA 5
A36: Concepto | B36: Categ. | C36: AED | D36: EUR | E36: Fecha | F36: Concepto | G36: Categ. | H36: AED | I36: EUR | J36: Fecha | K36: Concepto | L36: Categ. | M36: AED | N36: EUR | O36: Fecha | P36: Concepto | Q36: Categ. | R36: AED | S36: EUR | T36: Fecha | U36: Concepto | V36: Categ. | W36: AED | X36: EUR
A57: TOTAL | C57: =SUM(C37:C56)+SUM(D37:D56)/Resumen!$D$1 -> 0 | D57: =SUM(D37:D56)+SUM(C37:C56)*Resumen!$D$1 -> 0 | H57: =SUM(H37:H56)+SUM(I37:I56)/Resumen!$D$1 -> 0 | I57: =SUM(I37:I56)+SUM(H37:H56)*Resumen!$D$1 -> 0 | M57: =SUM(M37:M56)+SUM(N37:N56)/Resumen!$D$1 -> 0 | N57: =SUM(N37:N56)+SUM(M37:M56)*Resumen!$D$1 -> 0 | R57: =SUM(R37:R56)+SUM(S37:S56)/Resumen!$D$1 -> 0 | S57: =SUM(S37:S56)+SUM(R37:R56)*Resumen!$D$1 -> 0 | W57: =SUM(W37:W56)+SUM(X37:X56)/Resumen!$D$1 -> 0 | X57: =SUM(X37:X56)+SUM(W37:W56)*Resumen!$D$1 -> 0
A58: RESTANTE | C58: =Resumen!$B$32-C57 -> 2980 | D58: =Resumen!$C$32-D57 -> 715.2 | H58: =C58-H57 -> 2980 | I58: =D58-I57 -> 715.2 | M58: =H58-M57 -> 2980 | N58: =I58-N57 -> 715.2 | R58: =M58-R57 -> 2980 | S58: =N58-S57 -> 715.2 | W58: =R58-W57 -> 2980 | X58: =S58-X57 -> 715.2

Sheet Marzo
A1: INGRESOS MENSUALES
A2: Concepto | C2: Total AED | D2: Total EUR
A3: Salario Santi | C3: =Resumen!$C$4 -> 25000 | D3: =C3*Resumen!$D$1 -> 6000
A4: Salario Bea | C4: =D4/Resumen!$D$1 -> 5000 | D4: =Resumen!$C$5*Resumen!$D$1 -> 1200
A5: Ingresos extra | C5: =D5/Resumen!$D$1 -> 1800 | D5: =Resumen!$C$6*Resumen!$D$1 -> 432
A6: TOTAL INGRESOS | C6: =SUM(C3:C5) -> 31800 | D6: =SUM(D3:D5) -> 7632
A7: BALANCE (Ingreso - Gasto) | C7: =C6-C32 -> 31800 | D7: =D6-D32 -> 7632
A9: GASTOS MENSUALES
A11: RESUMEN POR CATEGORÍA
A12: Categoría | B12: Nº Gastos | C12: Total AED | D12: Total EUR
A13: Restaurantes | B13: =COUNTIF(B37:B56,A13)+COUNTIF(G37:G56,A13)+COUNTIF(L37:L56,A13)+COUNTIF(Q37:Q56,A13)+COUNTIF(V37:V56,A13) -> 0 | C13: =SUMIF(B37:B56,A13,C37:C56)+SUMIF(G37:G56,A13,H37:H56)+SUMIF(L37:L56,A13,M37:M56)+SUMIF(Q37:Q56,A13,R37:R56)+SUMIF(V37:V56,A13,W37:W56)+(SUMIF(B37:B56,A13,D37:D56)+SUMIF(G37:G56,A13,I37:I56)+SUMIF(L37:L56,A13,N37:N56)+SUMIF(Q37:Q56,A13,S37:S56)+SUMIF(V37:V56,A13,X37:X56))/Resumen!$D$1 -> 0 | D13: =C13*Resumen!$D$1 -> 0
A14: Ocio | B14: =COUNTIF(B37:B56,A14)+COUNTIF(G37:G56,A14)+COUNTIF(L37:L56,A14)+COUNTIF(Q37:Q56,A14)+COUNTIF(V37:V56,A14) -> 0 | C14: =SUMIF(B37:B56,A14,C37:C56)+SUMIF(G37:G56,A14,H37:H56)+SUMIF(L37:L56,A14,M37:M56)+SUMIF(Q37:Q56,A14,R37:R56)+SUMIF(V37:V56,A14,W37:W56)+(SUMIF(B37:B56,A14,D37:D56)+SUMIF(G37:G56,A14,I37:I56)+SUMIF(L37:L56,A14,N37:N56)+SUMIF(Q37:Q56,A14,S37:S56)+SUMIF(V37:V56,A14,X37:X56))/Resumen!$D$1 -> 0 | D14: =C14*Resumen!$D$1 -> 0
A15: Compras | B15: =COUNTIF(B37:B56,A15)+COUNTIF(G37:G56,A15)+COUNTIF(L37:L56,A15)+COUNTIF(Q37:Q56,A15)+COUNTIF(V37:V56,A15) -> 0 | C15: =SUMIF(B37:B56,A15,C37:C56)+SUMIF(G37:G56,A15,H37:H56)+SUMIF(L37:L56,A15,M37:M56)+SUMIF(Q37:Q56,A15,R37:R56)+SUMIF(V37:V56,A15,W37:W56)+(SUMIF(B37:B56,A15,D37:D56)+SUMIF(G37:G56,A15,I37:I56)+SUMIF(L37:L56,A15,N37:N56)+SUMIF(Q37:Q56,A15,S37:S56)+SUMIF(V37:V56,A15,X37:X56))/Resumen!$D$1 -> 0 | D15: =C15*Resumen!$D$1 -> 0
A16: Salud | B16: =COUNTIF(B37:B56,A16)+COUNTIF(G37:G56,A16)+COUNTIF(L37:L56,A16)+COUNTIF(Q37:Q56,A16)+COUNTIF(V37:V56,A16) -> 0 | C16: =SUMIF(B37:B56,A16,C37:C56)+SUMIF(G37:G56,A16,H37:H56)+SUMIF(L37:L56,A16,M37:M56)+SUMIF(Q37:Q56,A16,R37:R56)+SUMIF(V37:V56,A16,W37:W56)+(SUMIF(B37:B56,A16,D37:D56)+SUMIF(G37:G56,A16,I37:I56)+SUMIF(L37:L56,A16,N37:N56)+SUMIF(Q37:Q56,A16,S37:S56)+SUMIF(V37:V56,A16,X37:X56))/Resumen!$D$1 -> 0 | D16: =C16*Resumen!$D$1 -> 0
A17: Viajes | B17: =COUNTIF(B37:B56,A17)+COUNTIF(G37:G56,A17)+COUNTIF(L37:L56,A17)+COUNTIF(Q37:Q56,A17)+COUNTIF(V37:V56,A17) -> 0 | C17: =SUMIF(B37:B56,A17,C37:C56)+SUMIF(G37:G56,A17,H37:H56)+SUMIF(L37:L56,A17,M37:M56)+SUMIF(Q37:Q56,A17,R37:R56)+SUMIF(V37:V56,A17,W37:W56)+(SUMIF(B37:B56,A17,D37:D56)+SUMIF(G37:G56,A17,I37:I56)+SUMIF(L37:L56,A17,N37:N56)+SUMIF(Q37:Q56,A17,S37:S56)+SUMIF(V37:V56,A17,X37:X56))/Resumen!$D$1 -> 0 | D17: =C17*Resumen!$D$1 -> 0
A18: Santi | B18: =COUNTIF(B37:B56,A18)+COUNTIF(G37:G56,A18)+COUNTIF(L37:L56,A18)+COUNTIF(Q37:Q56,A18)+COUNTIF(V37:V56,A18) -> 0 | C18: =SUMIF(B37:B56,A18,C37:C56)+SUMIF(G37:G56,A18,H37:H56)+SUMIF(L37:L56,A18,M37:M56)+SUMIF(Q37:Q56,A18,R37:R56)+SUMIF(V37:V56,A18,W37:W56)+(SUMIF(B37:B56,A18,D37:D56)+SUMIF(G37:G56,A18,I37:I56)+SUMIF(L37:L56,A18,N37:N56)+SUMIF(Q37:Q56,A18,S37:S56)+SUMIF(V37:V56,A18,X37:X56))/Resumen!$D$1 -> 0 | D18: =C18*Resumen!$D$1 -> 0
A19: Bea | B19: =COUNTIF(B37:B56,A19)+COUNTIF(G37:G56,A19)+COUNTIF(L37:L56,A19)+COUNTIF(Q37:Q56,A19)+COUNTIF(V37:V56,A19) -> 0 | C19: =SUMIF(B37:B56,A19,C37:C56)+SUMIF(G37:G56,A19,H37:H56)+SUMIF(L37:L56,A19,M37:M56)+SUMIF(Q37:Q56,A19,R37:R56)+SUMIF(V37:V56,A19,W37:W56)+(SUMIF(B37:B56,A19,D37:D56)+SUMIF(G37:G56,A19,I37:I56)+SUMIF(L37:L56,A19,N37:N56)+SUMIF(Q37:Q56,A19,S37:S56)+SUMIF(V37:V56,A19,X37:X56))/Resumen!$D$1 -> 0 | D19: =C19*Resumen!$D$1 -> 0
A20: Personal | B20: =COUNTIF(B37:B56,A20)+COUNTIF(G37:G56,A20)+COUNTIF(L37:L56,A20)+COUNTIF(Q37:Q56,A20)+COUNTIF(V37:V56,A20) -> 0 | C20: =SUMIF(B37:B56,A20,C37:C56)+SUMIF(G37:G56,A20,H37:H56)+SUMIF(L37:L56,A20,M37:M56)+SUMIF(Q37:Q56,A20,R37:R56)+SUMIF(V37:V56,A20,W37:W56)+(SUMIF(B37:B56,A20,D37:D56)+SUMIF(G37:G56,A20,I37:I56)+SUMIF(L37:L56,A20,N37:N56)+SUMIF(Q37:Q56,A20,S37:S56)+SUMIF(V37:V56,A20,X37:X56))/Resumen!$D$1 -> 0 | D20: =C20*Resumen!$D$1 -> 0
A21: Transporte | B21: =COUNTIF(B37:B56,A21)+COUNTIF(G37:G56,A21)+COUNTIF(L37:L56,A21)+COUNTIF(Q37:Q56,A21)+COUNTIF(V37:V56,A21) -> 0 | C21: =SUMIF(B37:B56,A21,C37:C56)+SUMIF(G37:G56,A21,H37:H56)+SUMIF(L37:L56,A21,M37:M56)+SUMIF(Q37:Q56,A21,R37:R56)+SUMIF(V37:V56,A21,W37:W56)+(SUMIF(B37:B56,A21,D37:D56)+SUMIF(G37:G56,A21,I37:I56)+SUMIF(L37:L56,A21,N37:N56)+SUMIF(Q37:Q56,A21,S37:S56)+SUMIF(V37:V56,A21,X37:X56))/Resumen!$D$1 -> 0 | D21: =C21*Resumen!$D$1 -> 0
A22: Regalos | B22: =COUNTIF(B37:B56,A22)+COUNTIF(G37:G56,A22)+COUNTIF(L37:L56,A22)+COUNTIF(Q37:Q56,A22)+COUNTIF(V37:V56,A22) -> 0 | C22: =SUMIF(B37:B56,A22,C37:C56)+SUMIF(G37:G56,A22,H37:H56)+SUMIF(L37:L56,A22,M37:M56)+SUMIF(Q37:Q56,A22,R37:R56)+SUMIF(V37:V56,A22,W37:W56)+(SUMIF(B37:B56,A22,D37:D56)+SUMIF(G37:G56,A22,I37:I56)+SUMIF(L37:L56,A22,N37:N56)+SUMIF(Q37:Q56,A22,S37:S56)+SUMIF(V37:V56,A22,X37:X56))/Resumen!$D$1 -> 0 | D22: =C22*Resumen!$D$1 -> 0
A23: Alquiler piso | B23: =COUNTIF(B37:B56,A23)+COUNTIF(G37:G56,A23)+COUNTIF(L37:L56,A23)+COUNTIF(Q37:Q56,A23)+COUNTIF(V37:V56,A23) -> 0 | C23: =SUMIF(B37:B56,A23,C37:C56)+SUMIF(G37:G56,A23,H37:H56)+SUMIF(L37:L56,A23,M37:M56)+SUMIF(Q37:Q56,A23,R37:R56)+SUMIF(V37:V56,A23,W37:W56)+(SUMIF(B37:B56,A23,D37:D56)+SUMIF(G37:G56,A23,I37:I56)+SUMIF(L37:L56,A23,N37:N56)+SUMIF(Q37:Q56,A23,S37:S56)+SUMIF(V37:V56,A23,X37:X56))/Resumen!$D$1 -> 0 | D23: =C23*Resumen!$D$1 -> 0
A24: Mudanza | B24: =COUNTIF(B37:B56,A24)+COUNTIF(G37:G56,A24)+COUNTIF(L37:L56,A24)+COUNTIF(Q37:Q56,A24)+COUNTIF(V37:V56,A24) -> 0 | C24: =SUMIF(B37:B56,A24,C37:C56)+SUMIF(G37:G56,A24,H37:H56)+SUMIF(L37:L56,A24,M37:M56)+SUMIF(Q37:Q56,A24,R37:R56)+SUMIF(V37:V56,A24,W37:W56)+(SUMIF(B37:B56,A24,D37:D56)+SUMIF(G37:G56,A24,I37:I56)+SUMIF(L37:L56,A24,N37:N56)+SUMIF(Q37:Q56,A24,S37:S56)+SUMIF(V37:V56,A24,X37:X56))/Resumen!$D$1 -> 0 | D24: =C24*Resumen!$D$1 -> 0
A25: Tasas | B25: =COUNTIF(B37:B56,A25)+COUNTIF(G37:G56,A25)+COUNTIF(L37:L56,A25)+COUNTIF(Q37:Q56,A25)+COUNTIF(V37:V56,A25) -> 0 | C25: =SUMIF(B37:B56,A25,C37:C56)+SUMIF(G37:G56,A25,H37:H56)+SUMIF(L37:L56,A25,M37:M56)+SUMIF(Q37:Q56,A25,R37:R56)+SUMIF(V37:V56,A25,W37:W56)+(SUMIF(B37:B56,A25,D37:D56)+SUMIF(G37:G56,A25,I37:I56)+SUMIF(L37:L56,A25,N37:N56)+SUMIF(Q37:Q56,A25,S37:S56)+SUMIF(V37:V56,A25,X37:X56))/Resumen!$D$1 -> 0 | D25: =C25*Resumen!$D$1 -> 0
A26: Suministros piso | B26: =COUNTIF(B37:B56,A26)+COUNTIF(G37:G56,A26)+COUNTIF(L37:L56,A26)+COUNTIF(Q37:Q56,A26)+COUNTIF(V37:V56,A26) -> 0 | C26: =SUMIF(B37:B56,A26,C37:C56)+SUMIF(G37:G56,A26,H37:H56)+SUMIF(L37:L56,A26,M37:M56)+SUMIF(Q37:Q56,A26,R37:R56)+SUMIF(V37:V56,A26,W37:W56)+(SUMIF(B37:B56,A26,D37:D56)+SUMIF(G37:G56,A26,I37:I56)+SUMIF(L37:L56,A26,N37:N56)+SUMIF(Q37:Q56,A26,S37:S56)+SUMIF(V37:V56,A26,X37:X56))/Resumen!$D$1 -> 0 | D26: =C26*Resumen!$D$1 -> 0
A27: Otros | B27: =COUNTIF(B37:B56,A27)+COUNTIF(G37:G56,A27)+COUNTIF(L37:L56,A27)+COUNTIF(Q37:Q56,A27)+COUNTIF(V37:V56,A27) -> 0 | C27: =SUMIF(B37:B56,A27,C37:C56)+SUMIF(G37:G56,A27,H37:H56)+SUMIF(L37:L56,A27,M37:M56)+SUMIF(Q37:Q56,A27,R37:R56)+SUMIF(V37:V56,A27,W37:W56)+(SUMIF(B37:B56,A27,D37:D56)+SUMIF(G37:G56,A27,I37:I56)+SUMIF(L37:L56,A27,N37:N56)+SUMIF(Q37:Q56,A27,S37:S56)+SUMIF(V37:V56,A27,X37:X56))/Resumen!$D$1 -> 0 | D27: =C27*Resumen!$D$1 -> 0
A28: Hogar | B28: =COUNTIF(B37:B56,A28)+COUNTIF(G37:G56,A28)+COUNTIF(L37:L56,A28)+COUNTIF(Q37:Q56,A28)+COUNTIF(V37:V56,A28) -> 0 | C28: =SUMIF(B37:B56,A28,C37:C56)+SUMIF(G37:G56,A28,H37:H56)+SUMIF(L37:L56,A28,M37:M56)+SUMIF(Q37:Q56,A28,R37:R56)+SUMIF(V37:V56,A28,W37:W56)+(SUMIF(B37:B56,A28,D37:D56)+SUMIF(G37:G56,A28,I37:I56)+SUMIF(L37:L56,A28,N37:N56)+SUMIF(Q37:Q56,A28,S37:S56)+SUMIF(V37:V56,A28,X37:X56))/Resumen!$D$1 -> 0 | D28: =C28*Resumen!$D$1 -> 0
A29: Delivery | B29: =COUNTIF(B37:B56,A29)+COUNTIF(G37:G56,A29)+COUNTIF(L37:L56,A29)+COUNTIF(Q37:Q56,A29)+COUNTIF(V37:V56,A29) -> 0 | C29: =SUMIF(B37:B56,A29,C37:C56)+SUMIF(G37:G56,A29,H37:H56)+SUMIF(L37:L56,A29,M37:M56)+SUMIF(Q37:Q56,A29,R37:R56)+SUMIF(V37:V56,A29,W37:W56)+(SUMIF(B37:B56,A29,D37:D56)+SUMIF(G37:G56,A29,I37:I56)+SUMIF(L37:L56,A29,N37:N56)+SUMIF(Q37:Q56,A29,S37:S56)+SUMIF(V37:V56,A29,X37:X56))/Resumen!$D$1 -> 0 | D29: =C29*Resumen!$D$1 -> 0
A30: Supermercado | B30: =COUNTIF(B37:B56,A30)+COUNTIF(G37:G56,A30)+COUNTIF(L37:L56,A30)+COUNTIF(Q37:Q56,A30)+COUNTIF(V37:V56,A30) -> 0 | C30: =SUMIF(B37:B56,A30,C37:C56)+SUMIF(G37:G56,A30,H37:H56)+SUMIF(L37:L56,A30,M37:M56)+SUMIF(Q37:Q56,A30,R37:R56)+SUMIF(V37:V56,A30,W37:W56)+(SUMIF(B37:B56,A30,D37:D56)+SUMIF(G37:G56,A30,I37:I56)+SUMIF(L37:L56,A30,N37:N56)+SUMIF(Q37:Q56,A30,S37:S56)+SUMIF(V37:V56,A30,X37:X56))/Resumen!$D$1 -> 0 | D30: =C30*Resumen!$D$1 -> 0
A31: Suscripciones | B31: =COUNTIF(B37:B56,A31)+COUNTIF(G37:G56,A31)+COUNTIF(L37:L56,A31)+COUNTIF(Q37:Q56,A31)+COUNTIF(V37:V56,A31) -> 0 | C31: =SUMIF(B37:B56,A31,C37:C56)+SUMIF(G37:G56,A31,H37:H56)+SUMIF(L37:L56,A31,M37:M56)+SUMIF(Q37:Q56,A31,R37:R56)+SUMIF(V37:V56,A31,W37:W56)+(SUMIF(B37:B56,A31,D37:D56)+SUMIF(G37:G56,A31,I37:I56)+SUMIF(L37:L56,A31,N37:N56)+SUMIF(Q37:Q56,A31,S37:S56)+SUMIF(V37:V56,A31,X37:X56))/Resumen!$D$1 -> 0 | D31: =C31*Resumen!$D$1 -> 0
A32: TOTAL MES | B32: =SUM(B13:B31) -> 0 | C32: =SUM(C13:C31) -> 0 | D32: =SUM(D13:D31) -> 0
A34: REGISTRO SEMANAL
A35: SEMANA 1 | F35: SEMANA 2 | K35: SEMANA 3 | P35: SEMANA 4 | U35: SEMANA 5
A36: Concepto | B36: Categ. | C36: AED | D36: EUR | E36: Fecha | F36: Concepto | G36: Categ. | H36: AED | I36: EUR | J36: Fecha | K36: Concepto | L36: Categ. | M36: AED | N36: EUR | O36: Fecha | P36: Concepto | Q36: Categ. | R36: AED | S36: EUR | T36: Fecha | U36: Concepto | V36: Categ. | W36: AED | X36: EUR
A57: TOTAL | C57: =SUM(C37:C56)+SUM(D37:D56)/Resumen!$D$1 -> 0 | D57: =SUM(D37:D56)+SUM(C37:C56)*Resumen!$D$1 -> 0 | H57: =SUM(H37:H56)+SUM(I37:I56)/Resumen!$D$1 -> 0 | I57: =SUM(I37:I56)+SUM(H37:H56)*Resumen!$D$1 -> 0 | M57: =SUM(M37:M56)+SUM(N37:N56)/Resumen!$D$1 -> 0 | N57: =SUM(N37:N56)+SUM(M37:M56)*Resumen!$D$1 -> 0 | R57: =SUM(R37:R56)+SUM(S37:S56)/Resumen!$D$1 -> 0 | S57: =SUM(S37:S56)+SUM(R37:R56)*Resumen!$D$1 -> 0 | W57: =SUM(W37:W56)+SUM(X37:X56)/Resumen!$D$1 -> 0 | X57: =SUM(X37:X56)+SUM(W37:W56)*Resumen!$D$1 -> 0
A58: RESTANTE | C58: =Resumen!$B$32-C57 -> 2980 | D58: =Resumen!$C$32-D57 -> 715.2 | H58: =C58-H57 -> 2980 | I58: =D58-I57 -> 715.2 | M58: =H58-M57 -> 2980 | N58: =I58-N57 -> 715.2 | R58: =M58-R57 -> 2980 | S58: =N58-S57 -> 715.2 | W58: =R58-W57 -> 2980 | X58: =S58-X57 -> 715.2

Sheet Abril
A1: INGRESOS MENSUALES
A2: Concepto | C2: Total AED | D2: Total EUR
A3: Salario Santi | C3: =Resumen!$C$4 -> 25000 | D3: =C3*Resumen!$D$1 -> 6000
A4: Salario Bea | C4: =D4/Resumen!$D$1 -> 5000 | D4: =Resumen!$C$5*Resumen!$D$1 -> 1200
A5: Ingresos extra | C5: =D5/Resumen!$D$1 -> 1800 | D5: =Resumen!$C$6*Resumen!$D$1 -> 432
A6: TOTAL INGRESOS | C6: =SUM(C3:C5) -> 31800 | D6: =SUM(D3:D5) -> 7632
A7: BALANCE (Ingreso - Gasto) | C7: =C6-C32 -> 8334.8333 | D7: =D6-D32 -> 2000.36
A9: GASTOS MENSUALES
A11: RESUMEN POR CATEGORÍA
A12: Categoría | B12: Nº Gastos | C12: Total AED | D12: Total EUR
A13: Restaurantes | B13: =COUNTIF(B37:B56,A13)+COUNTIF(G37:G56,A13)+COUNTIF(L37:L56,A13)+COUNTIF(Q37:Q56,A13)+COUNTIF(V37:V56,A13) -> 22 | C13: =SUMIF(B37:B56,A13,C37:C56)+SUMIF(G37:G56,A13,H37:H56)+SUMIF(L37:L56,A13,M37:M56)+SUMIF(Q37:Q56,A13,R37:R56)+SUMIF(V37:V56,A13,W37:W56)+(SUMIF(B37:B56,A13,D37:D56)+SUMIF(G37:G56,A13,I37:I56)+SUMIF(L37:L56,A13,N37:N56)+SUMIF(Q37:Q56,A13,S37:S56)+SUMIF(V37:V56,A13,X37:X56))/Resumen!$D$1 -> 3252.625 | D13: =C13*Resumen!$D$1 -> 780.63
A14: Ocio | B14: =COUNTIF(B37:B56,A14)+COUNTIF(G37:G56,A14)+COUNTIF(L37:L56,A14)+COUNTIF(Q37:Q56,A14)+COUNTIF(V37:V56,A14) -> 5 | C14: =SUMIF(B37:B56,A14,C37:C56)+SUMIF(G37:G56,A14,H37:H56)+SUMIF(L37:L56,A14,M37:M56)+SUMIF(Q37:Q56,A14,R37:R56)+SUMIF(V37:V56,A14,W37:W56)+(SUMIF(B37:B56,A14,D37:D56)+SUMIF(G37:G56,A14,I37:I56)+SUMIF(L37:L56,A14,N37:N56)+SUMIF(Q37:Q56,A14,S37:S56)+SUMIF(V37:V56,A14,X37:X56))/Resumen!$D$1 -> 547.04167 | D14: =C14*Resumen!$D$1 -> 131.29
A15: Compras | B15: =COUNTIF(B37:B56,A15)+COUNTIF(G37:G56,A15)+COUNTIF(L37:L56,A15)+COUNTIF(Q37:Q56,A15)+COUNTIF(V37:V56,A15) -> 6 | C15: =SUMIF(B37:B56,A15,C37:C56)+SUMIF(G37:G56,A15,H37:H56)+SUMIF(L37:L56,A15,M37:M56)+SUMIF(Q37:Q56,A15,R37:R56)+SUMIF(V37:V56,A15,W37:W56)+(SUMIF(B37:B56,A15,D37:D56)+SUMIF(G37:G56,A15,I37:I56)+SUMIF(L37:L56,A15,N37:N56)+SUMIF(Q37:Q56,A15,S37:S56)+SUMIF(V37:V56,A15,X37:X56))/Resumen!$D$1 -> 1355.6667 | D15: =C15*Resumen!$D$1 -> 325.36
A16: Salud | B16: =COUNTIF(B37:B56,A16)+COUNTIF(G37:G56,A16)+COUNTIF(L37:L56,A16)+COUNTIF(Q37:Q56,A16)+COUNTIF(V37:V56,A16) -> 3 | C16: =SUMIF(B37:B56,A16,C37:C56)+SUMIF(G37:G56,A16,H37:H56)+SUMIF(L37:L56,A16,M37:M56)+SUMIF(Q37:Q56,A16,R37:R56)+SUMIF(V37:V56,A16,W37:W56)+(SUMIF(B37:B56,A16,D37:D56)+SUMIF(G37:G56,A16,I37:I56)+SUMIF(L37:L56,A16,N37:N56)+SUMIF(Q37:Q56,A16,S37:S56)+SUMIF(V37:V56,A16,X37:X56))/Resumen!$D$1 -> 2096.875 | D16: =C16*Resumen!$D$1 -> 503.25
A17: Viajes | B17: =COUNTIF(B37:B56,A17)+COUNTIF(G37:G56,A17)+COUNTIF(L37:L56,A17)+COUNTIF(Q37:Q56,A17)+COUNTIF(V37:V56,A17) -> 0 | C17: =SUMIF(B37:B56,A17,C37:C56)+SUMIF(G37:G56,A17,H37:H56)+SUMIF(L37:L56,A17,M37:M56)+SUMIF(Q37:Q56,A17,R37:R56)+SUMIF(V37:V56,A17,W37:W56)+(SUMIF(B37:B56,A17,D37:D56)+SUMIF(G37:G56,A17,I37:I56)+SUMIF(L37:L56,A17,N37:N56)+SUMIF(Q37:Q56,A17,S37:S56)+SUMIF(V37:V56,A17,X37:X56))/Resumen!$D$1 -> 0 | D17: =C17*Resumen!$D$1 -> 0
A18: Santi | B18: =COUNTIF(B37:B56,A18)+COUNTIF(G37:G56,A18)+COUNTIF(L37:L56,A18)+COUNTIF(Q37:Q56,A18)+COUNTIF(V37:V56,A18) -> 0 | C18: =SUMIF(B37:B56,A18,C37:C56)+SUMIF(G37:G56,A18,H37:H56)+SUMIF(L37:L56,A18,M37:M56)+SUMIF(Q37:Q56,A18,R37:R56)+SUMIF(V37:V56,A18,W37:W56)+(SUMIF(B37:B56,A18,D37:D56)+SUMIF(G37:G56,A18,I37:I56)+SUMIF(L37:L56,A18,N37:N56)+SUMIF(Q37:Q56,A18,S37:S56)+SUMIF(V37:V56,A18,X37:X56))/Resumen!$D$1 -> 0 | D18: =C18*Resumen!$D$1 -> 0
A19: Bea | B19: =COUNTIF(B37:B56,A19)+COUNTIF(G37:G56,A19)+COUNTIF(L37:L56,A19)+COUNTIF(Q37:Q56,A19)+COUNTIF(V37:V56,A19) -> 1 | C19: =SUMIF(B37:B56,A19,C37:C56)+SUMIF(G37:G56,A19,H37:H56)+SUMIF(L37:L56,A19,M37:M56)+SUMIF(Q37:Q56,A19,R37:R56)+SUMIF(V37:V56,A19,W37:W56)+(SUMIF(B37:B56,A19,D37:D56)+SUMIF(G37:G56,A19,I37:I56)+SUMIF(L37:L56,A19,N37:N56)+SUMIF(Q37:Q56,A19,S37:S56)+SUMIF(V37:V56,A19,X37:X56))/Resumen!$D$1 -> 2272.3333 | D19: =C19*Resumen!$D$1 -> 545.36
A20: Personal | B20: =COUNTIF(B37:B56,A20)+COUNTIF(G37:G56,A20)+COUNTIF(L37:L56,A20)+COUNTIF(Q37:Q56,A20)+COUNTIF(V37:V56,A20) -> 0 | C20: =SUMIF(B37:B56,A20,C37:C56)+SUMIF(G37:G56,A20,H37:H56)+SUMIF(L37:L56,A20,M37:M56)+SUMIF(Q37:Q56,A20,R37:R56)+SUMIF(V37:V56,A20,W37:W56)+(SUMIF(B37:B56,A20,D37:D56)+SUMIF(G37:G56,A20,I37:I56)+SUMIF(L37:L56,A20,N37:N56)+SUMIF(Q37:Q56,A20,S37:S56)+SUMIF(V37:V56,A20,X37:X56))/Resumen!$D$1 -> 0 | D20: =C20*Resumen!$D$1 -> 0
A21: Transporte | B21: =COUNTIF(B37:B56,A21)+COUNTIF(G37:G56,A21)+COUNTIF(L37:L56,A21)+COUNTIF(Q37:Q56,A21)+COUNTIF(V37:V56,A21) -> 7 | C21: =SUMIF(B37:B56,A21,C37:C56)+SUMIF(G37:G56,A21,H37:H56)+SUMIF(L37:L56,A21,M37:M56)+SUMIF(Q37:Q56,A21,R37:R56)+SUMIF(V37:V56,A21,W37:W56)+(SUMIF(B37:B56,A21,D37:D56)+SUMIF(G37:G56,A21,I37:I56)+SUMIF(L37:L56,A21,N37:N56)+SUMIF(Q37:Q56,A21,S37:S56)+SUMIF(V37:V56,A21,X37:X56))/Resumen!$D$1 -> 4430.7083 | D21: =C21*Resumen!$D$1 -> 1063.37
A22: Regalos | B22: =COUNTIF(B37:B56,A22)+COUNTIF(G37:G56,A22)+COUNTIF(L37:L56,A22)+COUNTIF(Q37:Q56,A22)+COUNTIF(V37:V56,A22) -> 0 | C22: =SUMIF(B37:B56,A22,C37:C56)+SUMIF(G37:G56,A22,H37:H56)+SUMIF(L37:L56,A22,M37:M56)+SUMIF(Q37:Q56,A22,R37:R56)+SUMIF(V37:V56,A22,W37:W56)+(SUMIF(B37:B56,A22,D37:D56)+SUMIF(G37:G56,A22,I37:I56)+SUMIF(L37:L56,A22,N37:N56)+SUMIF(Q37:Q56,A22,S37:S56)+SUMIF(V37:V56,A22,X37:X56))/Resumen!$D$1 -> 0 | D22: =C22*Resumen!$D$1 -> 0
A23: Alquiler piso | B23: =COUNTIF(B37:B56,A23)+COUNTIF(G37:G56,A23)+COUNTIF(L37:L56,A23)+COUNTIF(Q37:Q56,A23)+COUNTIF(V37:V56,A23) -> 0 | C23: =SUMIF(B37:B56,A23,C37:C56)+SUMIF(G37:G56,A23,H37:H56)+SUMIF(L37:L56,A23,M37:M56)+SUMIF(Q37:Q56,A23,R37:R56)+SUMIF(V37:V56,A23,W37:W56)+(SUMIF(B37:B56,A23,D37:D56)+SUMIF(G37:G56,A23,I37:I56)+SUMIF(L37:L56,A23,N37:N56)+SUMIF(Q37:Q56,A23,S37:S56)+SUMIF(V37:V56,A23,X37:X56))/Resumen!$D$1 -> 0 | D23: =C23*Resumen!$D$1 -> 0
A24: Mudanza | B24: =COUNTIF(B37:B56,A24)+COUNTIF(G37:G56,A24)+COUNTIF(L37:L56,A24)+COUNTIF(Q37:Q56,A24)+COUNTIF(V37:V56,A24) -> 0 | C24: =SUMIF(B37:B56,A24,C37:C56)+SUMIF(G37:G56,A24,H37:H56)+SUMIF(L37:L56,A24,M37:M56)+SUMIF(Q37:Q56,A24,R37:R56)+SUMIF(V37:V56,A24,W37:W56)+(SUMIF(B37:B56,A24,D37:D56)+SUMIF(G37:G56,A24,I37:I56)+SUMIF(L37:L56,A24,N37:N56)+SUMIF(Q37:Q56,A24,S37:S56)+SUMIF(V37:V56,A24,X37:X56))/Resumen!$D$1 -> 0 | D24: =C24*Resumen!$D$1 -> 0
A25: Tasas | B25: =COUNTIF(B37:B56,A25)+COUNTIF(G37:G56,A25)+COUNTIF(L37:L56,A25)+COUNTIF(Q37:Q56,A25)+COUNTIF(V37:V56,A25) -> 0 | C25: =SUMIF(B37:B56,A25,C37:C56)+SUMIF(G37:G56,A25,H37:H56)+SUMIF(L37:L56,A25,M37:M56)+SUMIF(Q37:Q56,A25,R37:R56)+SUMIF(V37:V56,A25,W37:W56)+(SUMIF(B37:B56,A25,D37:D56)+SUMIF(G37:G56,A25,I37:I56)+SUMIF(L37:L56,A25,N37:N56)+SUMIF(Q37:Q56,A25,S37:S56)+SUMIF(V37:V56,A25,X37:X56))/Resumen!$D$1 -> 0 | D25: =C25*Resumen!$D$1 -> 0
A26: Suministros piso | B26: =COUNTIF(B37:B56,A26)+COUNTIF(G37:G56,A26)+COUNTIF(L37:L56,A26)+COUNTIF(Q37:Q56,A26)+COUNTIF(V37:V56,A26) -> 0 | C26: =SUMIF(B37:B56,A26,C37:C56)+SUMIF(G37:G56,A26,H37:H56)+SUMIF(L37:L56,A26,M37:M56)+SUMIF(Q37:Q56,A26,R37:R56)+SUMIF(V37:V56,A26,W37:W56)+(SUMIF(B37:B56,A26,D37:D56)+SUMIF(G37:G56,A26,I37:I56)+SUMIF(L37:L56,A26,N37:N56)+SUMIF(Q37:Q56,A26,S37:S56)+SUMIF(V37:V56,A26,X37:X56))/Resumen!$D$1 -> 0 | D26: =C26*Resumen!$D$1 -> 0
A27: Otros | B27: =COUNTIF(B37:B56,A27)+COUNTIF(G37:G56,A27)+COUNTIF(L37:L56,A27)+COUNTIF(Q37:Q56,A27)+COUNTIF(V37:V56,A27) -> 7 | C27: =SUMIF(B37:B56,A27,C37:C56)+SUMIF(G37:G56,A27,H37:H56)+SUMIF(L37:L56,A27,M37:M56)+SUMIF(Q37:Q56,A27,R37:R56)+SUMIF(V37:V56,A27,W37:W56)+(SUMIF(B37:B56,A27,D37:D56)+SUMIF(G37:G56,A27,I37:I56)+SUMIF(L37:L56,A27,N37:N56)+SUMIF(Q37:Q56,A27,S37:S56)+SUMIF(V37:V56,A27,X37:X56))/Resumen!$D$1 -> 939.5 | D27: =C27*Resumen!$D$1 -> 225.48
A28: Hogar | B28: =COUNTIF(B37:B56,A28)+COUNTIF(G37:G56,A28)+COUNTIF(L37:L56,A28)+COUNTIF(Q37:Q56,A28)+COUNTIF(V37:V56,A28) -> 1 | C28: =SUMIF(B37:B56,A28,C37:C56)+SUMIF(G37:G56,A28,H37:H56)+SUMIF(L37:L56,A28,M37:M56)+SUMIF(Q37:Q56,A28,R37:R56)+SUMIF(V37:V56,A28,W37:W56)+(SUMIF(B37:B56,A28,D37:D56)+SUMIF(G37:G56,A28,I37:I56)+SUMIF(L37:L56,A28,N37:N56)+SUMIF(Q37:Q56,A28,S37:S56)+SUMIF(V37:V56,A28,X37:X56))/Resumen!$D$1 -> 6614.8333 | D28: =C28*Resumen!$D$1 -> 1587.56
A29: Delivery | B29: =COUNTIF(B37:B56,A29)+COUNTIF(G37:G56,A29)+COUNTIF(L37:L56,A29)+COUNTIF(Q37:Q56,A29)+COUNTIF(V37:V56,A29) -> 10 | C29: =SUMIF(B37:B56,A29,C37:C56)+SUMIF(G37:G56,A29,H37:H56)+SUMIF(L37:L56,A29,M37:M56)+SUMIF(Q37:Q56,A29,R37:R56)+SUMIF(V37:V56,A29,W37:W56)+(SUMIF(B37:B56,A29,D37:D56)+SUMIF(G37:G56,A29,I37:I56)+SUMIF(L37:L56,A29,N37:N56)+SUMIF(Q37:Q56,A29,S37:S56)+SUMIF(V37:V56,A29,X37:X56))/Resumen!$D$1 -> 849.08333 | D29: =C29*Resumen!$D$1 -> 203.78
A30: Supermercado | B30: =COUNTIF(B37:B56,A30)+COUNTIF(G37:G56,A30)+COUNTIF(L37:L56,A30)+COUNTIF(Q37:Q56,A30)+COUNTIF(V37:V56,A30) -> 9 | C30: =SUMIF(B37:B56,A30,C37:C56)+SUMIF(G37:G56,A30,H37:H56)+SUMIF(L37:L56,A30,M37:M56)+SUMIF(Q37:Q56,A30,R37:R56)+SUMIF(V37:V56,A30,W37:W56)+(SUMIF(B37:B56,A30,D37:D56)+SUMIF(G37:G56,A30,I37:I56)+SUMIF(L37:L56,A30,N37:N56)+SUMIF(Q37:Q56,A30,S37:S56)+SUMIF(V37:V56,A30,X37:X56))/Resumen!$D$1 -> 639.875 | D30: =C30*Resumen!$D$1 -> 153.57
A31: Suscripciones | B31: =COUNTIF(B37:B56,A31)+COUNTIF(G37:G56,A31)+COUNTIF(L37:L56,A31)+COUNTIF(Q37:Q56,A31)+COUNTIF(V37:V56,A31) -> 2 | C31: =SUMIF(B37:B56,A31,C37:C56)+SUMIF(G37:G56,A31,H37:H56)+SUMIF(L37:L56,A31,M37:M56)+SUMIF(Q37:Q56,A31,R37:R56)+SUMIF(V37:V56,A31,W37:W56)+(SUMIF(B37:B56,A31,D37:D56)+SUMIF(G37:G56,A31,I37:I56)+SUMIF(L37:L56,A31,N37:N56)+SUMIF(Q37:Q56,A31,S37:S56)+SUMIF(V37:V56,A31,X37:X56))/Resumen!$D$1 -> 466.625 | D31: =C31*Resumen!$D$1 -> 111.99
A32: TOTAL MES | B32: =SUM(B13:B31) -> 73 | C32: =SUM(C13:C31) -> 23465.167 | D32: =SUM(D13:D31) -> 5631.64
A34: REGISTRO SEMANAL
A35: SEMANA 1 | F35: SEMANA 2 | K35: SEMANA 3 | P35: SEMANA 4 | U35: SEMANA 5
A36: Concepto | B36: Categ. | C36: AED | D36: EUR | E36: Fecha | F36: Concepto | G36: Categ. | H36: AED | I36: EUR | J36: Fecha | K36: Concepto | L36: Categ. | M36: AED | N36: EUR | O36: Fecha | P36: Concepto | Q36: Categ. | R36: AED | S36: EUR | T36: Fecha | U36: Concepto | V36: Categ. | W36: AED | X36: EUR
A37: Starbucks | B37: Restaurantes | D37: 7.55 | F37: Careem | G37: Delivery | I37: 18.7 | K37: Emarat 6565 | L37: Otros | N37: 36.1 | P37: Lime | Q37: Transporte | S37: 16.04 | U37: UAE Tenis fed | V37: Ocio | W37: 15
A38: Zara | B38: Compras | D38: 57.33 | F38: Careem | G38: Delivery | I38: 16.72 | K38: Sobremesa | L38: Restaurantes | N38: 100.5 | P38: Careem | Q38: Delivery | S38: 34.15 | U38: UAE Tenis fed | V38: Ocio | W38: 262.5
A39: Shabab Stores | B39: Compras | D39: 44.26 | F39: Hubba caffee | G39: Restaurantes | I39: 3.19 | K39: 12 carts rest | L39: Restaurantes | N39: 8.42 | P39: Noq zajel courier | Q39: Delivery | S39: 24.55 | U39: Salik optical | V39: Otros
A40: New Shangai | B40: Restaurantes | D40: 36.1 | F40: Hexa café | G40: Restaurantes | I40: 5.94 | K40: Arabian tea house | L40: Restaurantes | N40: 110.42 | P40: Careem | Q40: Delivery | S40: 12.71 | U40: fertiitas | V40: Salud | X40: 151.25
A41: Booking apartment | B41: Hogar | D41: 1587.56 | F41: Boulevard plaza bsc | G41: Restaurantes | I41: 11.81 | K41: Claude Subscription | L41: Suscripciones | N41: 90 | P41: Lime | Q41: Transporte | S41: 17.34 | U41: du jumbo | V41: Bea | X41: 545.36
A42: Asemas | B42: Otros | D42: 74.52 | F42: Careem | G42: Delivery | I42: 15.89 | K42: Google gemini | L42: Suscripciones | N42: 21.99 | P42: Tim Hortons | Q42: Restaurantes | S42: 8.4
A43: Boulevard plaza bsc | B43: Restaurantes | D43: 11.81 | F43: Generali España | G43: Otros | I43: 54.67 | K43: Far east seafood | L43: Restaurantes | N43: 56.77 | P43: Lime | Q43: Transporte | S43: 10.55
A44: Careem | B44: Delivery | D44: 23.62 | F44: Art 14 tower park | G44: Transporte | I44: 7.28 | K44: Oud ad sandal | L44: Compras | N44: 15.25 | P44: Kumor rest | Q44: Restaurantes | S44: 105.6
A45: Rotana star | B45: Transporte | C45: 2000 | F45: Apointa | G45: Ocio | I45: 24.04 | K45: Qasr al reef | L45: Compras | N45: 23.46 | P45: Valtrasns trans | Q45: Transporte | S45: 5.83
A46: Heymondo | B46: Salud | D46: 152 | F46: Boulevard plaza bsc | G46: Restaurantes | I46: 8.74 | K46: Careem | L46: Delivery | N46: 14.33 | P46: Playtomic | Q46: Ocio | S46: 20.62
A47: Heymondo Bea | B47: Salud | D47: 200 | F47: Mvp lab concept | G47: Restaurantes | I47: 14.43 | K47: Careem | L47: Delivery | N47: 20.88 | P47: Padel sport academy | Q47: Ocio | S47: 20.03
A48: GMG Consumer | B48: Supermercado | D48: 37.1 | F48: Gmg Consumeer | G48: Supermercado | I48: 5.27 | K48: Gmg Consumeer | L48: Supermercado | N48: 21.83 | P48: Digitalñ Dubai | Q48: Otros | S48: 3.3
A49: GMG Consumer | B49: Supermercado | D49: 19.92 | F49: Envio dinero | G49: Otros | I49: 55 | K49: fmart | L49: Supermercado | N49: 4.87 | P49: Salt | Q49: Restaurantes | S49: 36.05
A50: nicki beach | B50: Restaurantes | D50: 47.76 | F50: bsc boulevard | G50: Restaurantes | I50: 12.18 | P50: Starbucks | Q50: Restaurantes | S50: 10.6
A51: Rotana star rent | B51: Transporte | D51: 526.33 | F51: yue baby rest | G51: Restaurantes | I51: 11.69 | P51: Digital dubai | Q51: Otros | S51: 1.89
F52: hippo box | G52: Supermercado | I52: 23.43 | P52: Gmg Consumeer | Q52: Supermercado | S52: 22.66
F53: mall dubai | G53: Compras | I53: 157.02 | P53: Gelateria romana | Q53: Restaurantes | S53: 8.01
F54: Gmg Consumeer | G54: Supermercado | I54: 17.67 | P54: H&M | Q54: Compras | S54: 28.04
F55: kings speciality | G55: Restaurantes | I55: 160.38 | P55: Careem | Q55: Delivery | S55: 22.23
F56: bsc boulevard | G56: Restaurantes | I56: 4.28 | P56: Al maya super | Q56: Supermercado | S56: 0.82
F57: dubai mall | G57: Compras | I57: 10.9 | P57: Careem | Q57: Delivery | S57: 22.8
F58: carrefour moe | G58: Supermercado | I58: 316.33 | P58: Careem | Q58: Delivery | S58: 5.58
P59: Lime | Q59: Transporte | S59: 14.11
P60: Oriental palace | Q60: Restaurante | S60: 77.87
P61: Careem | Q61: Delivery | S61: 17.23
P62: Hillhouse braserie | Q62: Restaurante | S62: 16.68
P63: Careem | Q63: Delivery | S63: 19
P64: Careem | Q64: Delivery | S64: 32.71
P65: Careem | Q65: Delivery | S65: 7.97
P66: Crareem | Q66: Delivery | S66: 16.49
A68: TOTAL | C68: =SUM(C37:C67)+SUM(D37:D67)/Resumen!$D$1 -> 13774.417 | D68: =SUM(D37:D67)+SUM(C37:C67)*Resumen!$D$1 -> 3305.86 | H68: =SUM(H37:H67)+SUM(I37:I67)/Resumen!$D$1 -> 3981.5 | I68: =SUM(I37:I67)+SUM(H37:H67)*Resumen!$D$1 -> 955.56 | M68: =SUM(M37:M67)+SUM(N37:N67)/Resumen!$D$1 -> 2186.75 | N68: =SUM(N37:N67)+SUM(M37:M67)*Resumen!$D$1 -> 524.82 | R68: =SUM(R37:R67)+SUM(S37:S67)/Resumen!$D$1 -> 2666.0833 | S68: =SUM(S37:S67)+SUM(R37:R67)*Resumen!$D$1 -> 639.86 | W68: =SUM(W37:W67)+SUM(X37:X67)/Resumen!$D$1 -> 3180.0417 | X68: =SUM(X37:X67)+SUM(W37:W67)*Resumen!$D$1 -> 763.21
A69: RESTANTE | C69: =C32-C68 -> 9690.75 | D69: =D32-D68 -> 2325.78 | H69: =C69-H68 -> 5709.25 | I69: =D69-I68 -> 1370.22 | M69: =H69-M68 -> 3522.5 | N69: =I69-N68 -> 845.4 | R69: =M69-R68 -> 856.41667 | S69: =N69-S68 -> 205.54 | W69: =R69-W68 -> -2323.625 | X69: =S69-X68 -> -557.67

Sheet Mayo
A1: INGRESOS MENSUALES
A2: Concepto | C2: Total AED | D2: Total EUR
A3: Salario Santi | C3: =Resumen!$C$4 -> 25000 | D3: =C3*Resumen!$D$1 -> 6000
A4: Salario Bea | C4: =D4/Resumen!$D$1 -> 5000 | D4: =Resumen!$C$5*Resumen!$D$1 -> 1200
A5: Ingresos extra | C5: =D5/Resumen!$D$1 -> 1800 | D5: =Resumen!$C$6*Resumen!$D$1 -> 432
A6: TOTAL INGRESOS | C6: =SUM(C3:C5) -> 31800 | D6: =SUM(D3:D5) -> 7632
A7: BALANCE (Ingreso - Gasto) | C7: =C6-C32 -> -46571.572 | D7: =D6-D32 -> -11177.177
A9: GASTOS MENSUALES
A11: RESUMEN POR CATEGORÍA
A12: Categoría | B12: Nº Gastos | C12: Total AED | D12: Total EUR
A13: Restaurantes | B13: =COUNTIF(B37:B86,A13)+COUNTIF(G37:G86,A13)+COUNTIF(L37:L86,A13)+COUNTIF(Q37:Q86,A13)+COUNTIF(V37:V86,A13) -> 17 | C13: =SUMIF(B37:B86,A13,C37:C86)+SUMIF(G37:G86,A13,H37:H86)+SUMIF(L37:L86,A13,M37:M86)+SUMIF(Q37:Q86,A13,R37:R86)+SUMIF(V37:V86,A13,W37:W86)+(SUMIF(B37:B86,A13,D37:D86)+SUMIF(G37:G86,A13,I37:I86)+SUMIF(L37:L86,A13,N37:N86)+SUMIF(Q37:Q86,A13,S37:S86)+SUMIF(V37:V86,A13,X37:X86))/Resumen!$D$1 -> 3310.2083 | D13: =C13*Resumen!$D$1 -> 794.45
A14: Ocio | B14: =COUNTIF(B37:B86,A14)+COUNTIF(G37:G86,A14)+COUNTIF(L37:L86,A14)+COUNTIF(Q37:Q86,A14)+COUNTIF(V37:V86,A14) -> 1 | C14: =SUMIF(B37:B86,A14,C37:C86)+SUMIF(G37:G86,A14,H37:H86)+SUMIF(L37:L86,A14,M37:M86)+SUMIF(Q37:Q86,A14,R37:R86)+SUMIF(V37:V86,A14,W37:W86)+(SUMIF(B37:B86,A14,D37:D86)+SUMIF(G37:G86,A14,I37:I86)+SUMIF(L37:L86,A14,N37:N86)+SUMIF(Q37:Q86,A14,S37:S86)+SUMIF(V37:V86,A14,X37:X86))/Resumen!$D$1 -> 400 | D14: =C14*Resumen!$D$1 -> 96
A15: Compras | B15: =COUNTIF(B37:B86,A15)+COUNTIF(G37:G86,A15)+COUNTIF(L37:L86,A15)+COUNTIF(Q37:Q86,A15)+COUNTIF(V37:V86,A15) -> 5 | C15: =SUMIF(B37:B86,A15,C37:C86)+SUMIF(G37:G86,A15,H37:H86)+SUMIF(L37:L86,A15,M37:M86)+SUMIF(Q37:Q86,A15,R37:R86)+SUMIF(V37:V86,A15,W37:W86)+(SUMIF(B37:B86,A15,D37:D86)+SUMIF(G37:G86,A15,I37:I86)+SUMIF(L37:L86,A15,N37:N86)+SUMIF(Q37:Q86,A15,S37:S86)+SUMIF(V37:V86,A15,X37:X86))/Resumen!$D$1 -> 882.44833 | D15: =C15*Resumen!$D$1 -> 211.7876
A16: Salud | B16: =COUNTIF(B37:B86,A16)+COUNTIF(G37:G86,A16)+COUNTIF(L37:L86,A16)+COUNTIF(Q37:Q86,A16)+COUNTIF(V37:V86,A16) -> 0 | C16: =SUMIF(B37:B86,A16,C37:C86)+SUMIF(G37:G86,A16,H37:H86)+SUMIF(L37:L86,A16,M37:M86)+SUMIF(Q37:Q86,A16,R37:R86)+SUMIF(V37:V86,A16,W37:W86)+(SUMIF(B37:B86,A16,D37:D86)+SUMIF(G37:G86,A16,I37:I86)+SUMIF(L37:L86,A16,N37:N86)+SUMIF(Q37:Q86,A16,S37:S86)+SUMIF(V37:V86,A16,X37:X86))/Resumen!$D$1 -> 0 | D16: =C16*Resumen!$D$1 -> 0
A17: Viajes | B17: =COUNTIF(B37:B86,A17)+COUNTIF(G37:G86,A17)+COUNTIF(L37:L86,A17)+COUNTIF(Q37:Q86,A17)+COUNTIF(V37:V86,A17) -> 0 | C17: =SUMIF(B37:B86,A17,C37:C86)+SUMIF(G37:G86,A17,H37:H86)+SUMIF(L37:L86,A17,M37:M86)+SUMIF(Q37:Q86,A17,R37:R86)+SUMIF(V37:V86,A17,W37:W86)+(SUMIF(B37:B86,A17,D37:D86)+SUMIF(G37:G86,A17,I37:I86)+SUMIF(L37:L86,A17,N37:N86)+SUMIF(Q37:Q86,A17,S37:S86)+SUMIF(V37:V86,A17,X37:X86))/Resumen!$D$1 -> 0 | D17: =C17*Resumen!$D$1 -> 0
A18: Santi | B18: =COUNTIF(B37:B86,A18)+COUNTIF(G37:G86,A18)+COUNTIF(L37:L86,A18)+COUNTIF(Q37:Q86,A18)+COUNTIF(V37:V86,A18) -> 2 | C18: =SUMIF(B37:B86,A18,C37:C86)+SUMIF(G37:G86,A18,H37:H86)+SUMIF(L37:L86,A18,M37:M86)+SUMIF(Q37:Q86,A18,R37:R86)+SUMIF(V37:V86,A18,W37:W86)+(SUMIF(B37:B86,A18,D37:D86)+SUMIF(G37:G86,A18,I37:I86)+SUMIF(L37:L86,A18,N37:N86)+SUMIF(Q37:Q86,A18,S37:S86)+SUMIF(V37:V86,A18,X37:X86))/Resumen!$D$1 -> 1096.7083 | D18: =C18*Resumen!$D$1 -> 263.21
A19: Bea | B19: =COUNTIF(B37:B86,A19)+COUNTIF(G37:G86,A19)+COUNTIF(L37:L86,A19)+COUNTIF(Q37:Q86,A19)+COUNTIF(V37:V86,A19) -> 4 | C19: =SUMIF(B37:B86,A19,C37:C86)+SUMIF(G37:G86,A19,H37:H86)+SUMIF(L37:L86,A19,M37:M86)+SUMIF(Q37:Q86,A19,R37:R86)+SUMIF(V37:V86,A19,W37:W86)+(SUMIF(B37:B86,A19,D37:D86)+SUMIF(G37:G86,A19,I37:I86)+SUMIF(L37:L86,A19,N37:N86)+SUMIF(Q37:Q86,A19,S37:S86)+SUMIF(V37:V86,A19,X37:X86))/Resumen!$D$1 -> 1537.0417 | D19: =C19*Resumen!$D$1 -> 368.89
A20: Personal | B20: =COUNTIF(B37:B86,A20)+COUNTIF(G37:G86,A20)+COUNTIF(L37:L86,A20)+COUNTIF(Q37:Q86,A20)+COUNTIF(V37:V86,A20) -> 0 | C20: =SUMIF(B37:B86,A20,C37:C86)+SUMIF(G37:G86,A20,H37:H86)+SUMIF(L37:L86,A20,M37:M86)+SUMIF(Q37:Q86,A20,R37:R86)+SUMIF(V37:V86,A20,W37:W86)+(SUMIF(B37:B86,A20,D37:D86)+SUMIF(G37:G86,A20,I37:I86)+SUMIF(L37:L86,A20,N37:N86)+SUMIF(Q37:Q86,A20,S37:S86)+SUMIF(V37:V86,A20,X37:X86))/Resumen!$D$1 -> 0 | D20: =C20*Resumen!$D$1 -> 0
A21: Transporte | B21: =COUNTIF(B37:B86,A21)+COUNTIF(G37:G86,A21)+COUNTIF(L37:L86,A21)+COUNTIF(Q37:Q86,A21)+COUNTIF(V37:V86,A21) -> 10 | C21: =SUMIF(B37:B86,A21,C37:C86)+SUMIF(G37:G86,A21,H37:H86)+SUMIF(L37:L86,A21,M37:M86)+SUMIF(Q37:Q86,A21,R37:R86)+SUMIF(V37:V86,A21,W37:W86)+(SUMIF(B37:B86,A21,D37:D86)+SUMIF(G37:G86,A21,I37:I86)+SUMIF(L37:L86,A21,N37:N86)+SUMIF(Q37:Q86,A21,S37:S86)+SUMIF(V37:V86,A21,X37:X86))/Resumen!$D$1 -> 2322.4333 | D21: =C21*Resumen!$D$1 -> 557.384
A22: Regalos | B22: =COUNTIF(B37:B86,A22)+COUNTIF(G37:G86,A22)+COUNTIF(L37:L86,A22)+COUNTIF(Q37:Q86,A22)+COUNTIF(V37:V86,A22) -> 1 | C22: =SUMIF(B37:B86,A22,C37:C86)+SUMIF(G37:G86,A22,H37:H86)+SUMIF(L37:L86,A22,M37:M86)+SUMIF(Q37:Q86,A22,R37:R86)+SUMIF(V37:V86,A22,W37:W86)+(SUMIF(B37:B86,A22,D37:D86)+SUMIF(G37:G86,A22,I37:I86)+SUMIF(L37:L86,A22,N37:N86)+SUMIF(Q37:Q86,A22,S37:S86)+SUMIF(V37:V86,A22,X37:X86))/Resumen!$D$1 -> 1250 | D22: =C22*Resumen!$D$1 -> 300
A23: Alquiler piso | B23: =COUNTIF(B37:B86,A23)+COUNTIF(G37:G86,A23)+COUNTIF(L37:L86,A23)+COUNTIF(Q37:Q86,A23)+COUNTIF(V37:V86,A23) -> 6 | C23: =SUMIF(B37:B86,A23,C37:C86)+SUMIF(G37:G86,A23,H37:H86)+SUMIF(L37:L86,A23,M37:M86)+SUMIF(Q37:Q86,A23,R37:R86)+SUMIF(V37:V86,A23,W37:W86)+(SUMIF(B37:B86,A23,D37:D86)+SUMIF(G37:G86,A23,I37:I86)+SUMIF(L37:L86,A23,N37:N86)+SUMIF(Q37:Q86,A23,S37:S86)+SUMIF(V37:V86,A23,X37:X86))/Resumen!$D$1 -> 34752.542 | D23: =C23*Resumen!$D$1 -> 8340.61
A24: Mudanza | B24: =COUNTIF(B37:B86,A24)+COUNTIF(G37:G86,A24)+COUNTIF(L37:L86,A24)+COUNTIF(Q37:Q86,A24)+COUNTIF(V37:V86,A24) -> 19 | C24: =SUMIF(B37:B86,A24,C37:C86)+SUMIF(G37:G86,A24,H37:H86)+SUMIF(L37:L86,A24,M37:M86)+SUMIF(Q37:Q86,A24,R37:R86)+SUMIF(V37:V86,A24,W37:W86)+(SUMIF(B37:B86,A24,D37:D86)+SUMIF(G37:G86,A24,I37:I86)+SUMIF(L37:L86,A24,N37:N86)+SUMIF(Q37:Q86,A24,S37:S86)+SUMIF(V37:V86,A24,X37:X86))/Resumen!$D$1 -> 26162.615 | D24: =C24*Resumen!$D$1 -> 6279.0276
A25: Tasas | B25: =COUNTIF(B37:B86,A25)+COUNTIF(G37:G86,A25)+COUNTIF(L37:L86,A25)+COUNTIF(Q37:Q86,A25)+COUNTIF(V37:V86,A25) -> 5 | C25: =SUMIF(B37:B86,A25,C37:C86)+SUMIF(G37:G86,A25,H37:H86)+SUMIF(L37:L86,A25,M37:M86)+SUMIF(Q37:Q86,A25,R37:R86)+SUMIF(V37:V86,A25,W37:W86)+(SUMIF(B37:B86,A25,D37:D86)+SUMIF(G37:G86,A25,I37:I86)+SUMIF(L37:L86,A25,N37:N86)+SUMIF(Q37:Q86,A25,S37:S86)+SUMIF(V37:V86,A25,X37:X86))/Resumen!$D$1 -> 2053.97 | D25: =C25*Resumen!$D$1 -> 492.9528
A26: Suministros piso | B26: =COUNTIF(B37:B86,A26)+COUNTIF(G37:G86,A26)+COUNTIF(L37:L86,A26)+COUNTIF(Q37:Q86,A26)+COUNTIF(V37:V86,A26) -> 2 | C26: =SUMIF(B37:B86,A26,C37:C86)+SUMIF(G37:G86,A26,H37:H86)+SUMIF(L37:L86,A26,M37:M86)+SUMIF(Q37:Q86,A26,R37:R86)+SUMIF(V37:V86,A26,W37:W86)+(SUMIF(B37:B86,A26,D37:D86)+SUMIF(G37:G86,A26,I37:I86)+SUMIF(L37:L86,A26,N37:N86)+SUMIF(Q37:Q86,A26,S37:S86)+SUMIF(V37:V86,A26,X37:X86))/Resumen!$D$1 -> 207.125 | D26: =C26*Resumen!$D$1 -> 49.71
A27: Otros | B27: =COUNTIF(B37:B86,A27)+COUNTIF(G37:G86,A27)+COUNTIF(L37:L86,A27)+COUNTIF(Q37:Q86,A27)+COUNTIF(V37:V86,A27) -> 1 | C27: =SUMIF(B37:B86,A27,C37:C86)+SUMIF(G37:G86,A27,H37:H86)+SUMIF(L37:L86,A27,M37:M86)+SUMIF(Q37:Q86,A27,R37:R86)+SUMIF(V37:V86,A27,W37:W86)+(SUMIF(B37:B86,A27,D37:D86)+SUMIF(G37:G86,A27,I37:I86)+SUMIF(L37:L86,A27,N37:N86)+SUMIF(Q37:Q86,A27,S37:S86)+SUMIF(V37:V86,A27,X37:X86))/Resumen!$D$1 -> 1000 | D27: =C27*Resumen!$D$1 -> 240
A28: Hogar | B28: =COUNTIF(B37:B86,A28)+COUNTIF(G37:G86,A28)+COUNTIF(L37:L86,A28)+COUNTIF(Q37:Q86,A28)+COUNTIF(V37:V86,A28) -> 0 | C28: =SUMIF(B37:B86,A28,C37:C86)+SUMIF(G37:G86,A28,H37:H86)+SUMIF(L37:L86,A28,M37:M86)+SUMIF(Q37:Q86,A28,R37:R86)+SUMIF(V37:V86,A28,W37:W86)+(SUMIF(B37:B86,A28,D37:D86)+SUMIF(G37:G86,A28,I37:I86)+SUMIF(L37:L86,A28,N37:N86)+SUMIF(Q37:Q86,A28,S37:S86)+SUMIF(V37:V86,A28,X37:X86))/Resumen!$D$1 -> 0 | D28: =C28*Resumen!$D$1 -> 0
A29: Delivery | B29: =COUNTIF(B37:B86,A29)+COUNTIF(G37:G86,A29)+COUNTIF(L37:L86,A29)+COUNTIF(Q37:Q86,A29)+COUNTIF(V37:V86,A29) -> 19 | C29: =SUMIF(B37:B86,A29,C37:C86)+SUMIF(G37:G86,A29,H37:H86)+SUMIF(L37:L86,A29,M37:M86)+SUMIF(Q37:Q86,A29,R37:R86)+SUMIF(V37:V86,A29,W37:W86)+(SUMIF(B37:B86,A29,D37:D86)+SUMIF(G37:G86,A29,I37:I86)+SUMIF(L37:L86,A29,N37:N86)+SUMIF(Q37:Q86,A29,S37:S86)+SUMIF(V37:V86,A29,X37:X86))/Resumen!$D$1 -> 3360.13 | D29: =C29*Resumen!$D$1 -> 806.4312
A30: Supermercado | B30: =COUNTIF(B37:B86,A30)+COUNTIF(G37:G86,A30)+COUNTIF(L37:L86,A30)+COUNTIF(Q37:Q86,A30)+COUNTIF(V37:V86,A30) -> 2 | C30: =SUMIF(B37:B86,A30,C37:C86)+SUMIF(G37:G86,A30,H37:H86)+SUMIF(L37:L86,A30,M37:M86)+SUMIF(Q37:Q86,A30,R37:R86)+SUMIF(V37:V86,A30,W37:W86)+(SUMIF(B37:B86,A30,D37:D86)+SUMIF(G37:G86,A30,I37:I86)+SUMIF(L37:L86,A30,N37:N86)+SUMIF(Q37:Q86,A30,S37:S86)+SUMIF(V37:V86,A30,X37:X86))/Resumen!$D$1 -> 36.35 | D30: =C30*Resumen!$D$1 -> 8.724
A31: Suscripciones | B31: =COUNTIF(B37:B86,A31)+COUNTIF(G37:G86,A31)+COUNTIF(L37:L86,A31)+COUNTIF(Q37:Q86,A31)+COUNTIF(V37:V86,A31) -> 0 | C31: =SUMIF(B37:B86,A31,C37:C86)+SUMIF(G37:G86,A31,H37:H86)+SUMIF(L37:L86,A31,M37:M86)+SUMIF(Q37:Q86,A31,R37:R86)+SUMIF(V37:V86,A31,W37:W86)+(SUMIF(B37:B86,A31,D37:D86)+SUMIF(G37:G86,A31,I37:I86)+SUMIF(L37:L86,A31,N37:N86)+SUMIF(Q37:Q86,A31,S37:S86)+SUMIF(V37:V86,A31,X37:X86))/Resumen!$D$1 -> 0 | D31: =C31*Resumen!$D$1 -> 0
A32: TOTAL MES | B32: =SUM(B13:B31) -> 94 | C32: =SUM(C13:C31) -> 78371.572 | D32: =SUM(D13:D31) -> 18809.177
A34: REGISTRO SEMANAL
A35: SEMANA 1 | F35: SEMANA 2 | K35: SEMANA 3 | P35: SEMANA 4 | U35: SEMANA 5
A36: Concepto | B36: Categ. | C36: AED | D36: EUR | E36: Fecha | F36: Concepto | G36: Categ. | H36: AED | I36: EUR | J36: Fecha | K36: Concepto | L36: Categ. | M36: AED | N36: EUR | O36: Fecha | P36: Concepto | Q36: Categ. | R36: AED | S36: EUR | T36: Fecha | U36: Concepto | V36: Categ. | W36: AED | X36: EUR
A37: sofa y mesa café | B37: Mudanza | D37: 821.61 | F37: Atmosphere | G37: Restaurantes | I37: 156.92 | K37: Vestido boda Philippa | L37: Bea | N37: 220.9 | O37: 46158
A38: utensilios cocina | B38: Mudanza | D38: 258.15 | F38: Ikea | G38: Mudanza | I38: 258.15 | K38: Comidas varias | L38: Restaurantes | N38: 152.92 | O38: 46158
A39: lavadora | B39: Mudanza | D39: 333.67 | F39: Careem | G39: Delivery | I39: 41.99 | K39: Careem varios | L39: Delivery | N39: 92.39 | O39: 46159
A40: cama y bed sheets | B40: Mudanza | D40: 84 | F40: Careem | G40: Delivery | I40: 5.36 | K40: Careem varios | L40: Delivery | N40: 36.47 | O40: 46160
A41: toallas | B41: Mudanza | D41: 57.72 | F41: Careem | G41: Delivery | I41: 52.02 | K41: du | L41: Suministros piso | N41: 14.33 | O41: 46161
A42: colchon | B42: Mudanza | D42: 370.78 | F42: Ikea | G42: Mudanza | I42: 426.48 | K42: Careem varios | L42: Delivery | N42: 92.58 | O42: 46163
A43: ikea sartenes | B43: Mudanza | D43: 71.8 | F43: Loocitane | G43: Bea | I43: 11.59 | K43: Aeropuert Dubai | L43: Compras | N43: 109.08 | O43: 46164
A44: cortinas | B44: Mudanza | D44: 563.28 | F44: Carrefour | G44: Mudanza | I44: 367.7 | K44: Estanco pamplona | L44: Compras | N44: 17.19 | O44: 46165
A45: RTA | B45: Tasas | C45: 870 | F45: Careem | G45: Delivery | I45: 20.48 | K45: Burger pamplona | L45: Restaurantes | N45: 46.56 | O45: 46165
A46: Markette rest | B46: Restaurantes | C46: 250 | F46: Careem | G46: Delivery | I46: 19.44 | K46: Viaje zaragoza | L46: Transporte | N46: 126.35 | O46: 46167
A47: 12 carts rest | B47: Restaurantes | C47: 35 | F47: Noon | G47: Compras | I47: 13.58 | K47: Heymondo | L47: Bea | N47: 36.59 | O47: 46160
A48: Smart dubai gov | B48: Tasas | C48: 6 | F48: Lime | G48: Transporte | I48: 5.44 | K48: Google Ai | L48: Santi | N48: 21.99 | O48: 46161
A49: Careem | B49: Delivery | C49: 24.59 | F49: Patinete rally star | G49: Santi | I49: 241.22 | K49: Regalo boda migas | L49: Regalos | N49: 300 | O49: 46162
A50: Lime | B50: Transporte | C50: 19.9 | F50: Careem | G50: Delivery | I50: 35.35 | K50: Womens secret | L50: Compras | N50: 34.98 | O50: 46163
A51: Piso 3 meses | B51: Alquiler piso | C51: 20000 | F51: Smart dubai gov | G51: Tasas | H51: 5 | K51: Cars Booking | L51: Transporte | N51: 253.52 | O51: 46167
A52: Lime | B52: Transporte | C52: 48.3 | F52: Efectivo Fianza move in | G52: Otros | H52: 1000 | K52: The lana high society | L52: Restaurantes | N52: 144.42 | O52: 46161
A53: Global sports | B53: Ocio | C53: 400 | F53: Retirada efectivo | G53: Alquiler piso | H53: 500 | K53: Nanan zishang | L53: Mudanza | N53: 432.86
A54: Lime | B54: Transporte | C54: 80.7 | F54: Whitewill real state | G54: Alquiler piso | H54: 5040 | K54: Orient center | L54: Mudanza | N54: 569.93
A55: KFC Dragon mart | B55: Restaurantes | C55: 41 | F55: lLime | G55: Transporte | H55: 7.7 | K55: Pullman couqley | L55: Restaurantes | N55: 113.51
A56: Dunkin | B56: Restaurantes | C56: 18 | F56: Retirada efectivo | G56: Alquiler piso | H56: 1200 | K56: Majid al futtaim | L56: Mudanza | N56: 705.88 | O56: 46167
A57: Be smart tech | B57: Tasas | C57: 247.97 | F57: Lime | G57: Transporte | H57: 7.7
A58: BSC Boulevard | B58: Restaurantes | C58: 53 | F58: GMG Consumer | G58: Supermercado | H58: 14.5
A59: retirada efectivo piso | B59: Alquiler piso | D59: 1840.21 | F59: May tai salad | G59: Restaurantes | H59: 65
A60: retirada efectivo piso.comis | B60: Alquiler piso | D60: 82.8 | F60: Half cup rest | G60: Restaurantes | H60: 65
A61: Careem | B61: Delivery | D61: 18.85 | F61: Noon | G61: Compras | H61: 153.99
A62: Careem | B62: Delivery | D62: 12.77 | F62: Careem | G62: Delivery | H62: 23.94
F63: Pan emirates | G63: Mudanza | H63: 931
F64: Pan emirates | G64: Mudanza | H64: 358
F65: nomad italian café | G65: Restaurantes | H65: 10
F66: carrefour festival city | G66: Mudanza | H66: 620.49
F67: Careem | G67: Delivery | H67: 34
F68: Fmart | G68: Restaurantes | H68: 9.5
F69: Estekana café | G69: Restaurantes | H69: 32
F70: Il forno | G70: Restaurantes | H70: 146
F71: Careem varios | G71: Delivery | H71: 159.1
F72: GMG Consumer | G72: Supermercado | H72: 21.85
F73: Lime | G73: Transporte | H73: 60.3
F74: My tai wok | G74: Restaurantes | H74: 26
F75: Royal gas | G75: Tasas | H75: 925
F76: Landmark group | G76: Mudanza | I76: 334.27
F77: Careem | G77: Delivery | I77: 59.47 | J77: 46154
F78: H&M | G78: Bea | I78: 99.81 | J78: 46154
F79: Zara Home | G79: Mudanza | I79: 164.47 | J79: 46154
F80: Noon Minutes | G80: Delivery | I80: 33.24 | J80: 46154
F81: Careem | G81: Delivery | I81: 69.58 | J81: 46155
F82: du | G82: Suministros piso | I82: 35.38 | J82: 46155
F83: Varios Delivery | G83: Delivery | I83: 158.45 | J83: 46155
F84: Dreamz Rent a car | G84: Transporte | I84: 118.17 | J84: 46157
A87: TOTAL | C87: =SUM(C37:C86)+SUM(D37:D86)/Resumen!$D$1 -> 40909.627 | D87: =SUM(D37:D86)+SUM(C37:C86)*Resumen!$D$1 -> 9818.3104 | H87: =SUM(H37:H86)+SUM(I37:I86)/Resumen!$D$1 -> 22785.07 | I87: =SUM(I37:I86)+SUM(H37:H86)*Resumen!$D$1 -> 5468.4168 | M87: =SUM(M37:M86)+SUM(N37:N86)/Resumen!$D$1 -> 14676.875 | N87: =SUM(N37:N86)+SUM(M37:M86)*Resumen!$D$1 -> 3522.45 | R87: =SUM(R37:R86)+SUM(S37:S86)/Resumen!$D$1 -> 0 | S87: =SUM(S37:S86)+SUM(R37:R86)*Resumen!$D$1 -> 0 | W87: =SUM(W37:W86)+SUM(X37:X86)/Resumen!$D$1 -> 0 | X87: =SUM(X37:X86)+SUM(W37:W86)*Resumen!$D$1 -> 0
A88: RESTANTE | C88: =Resumen!$B$32-C87 -> -37929.627 | D88: =Resumen!$C$32-D87 -> -9103.1104 | H88: =C88-H87 -> -60714.697 | I88: =D88-I87 -> -14571.527 | M88: =H88-M87 -> -75391.572 | N88: =I88-N87 -> -18093.977 | R88: =M88-R87 -> -75391.572 | S88: =N88-S87 -> -18093.977 | W88: =R88-W87 -> -75391.572 | X88: =S88-X87 -> -18093.977

Sheet Junio
A1: INGRESOS MENSUALES
A2: Concepto | C2: Total AED | D2: Total EUR | F2: 6697 | G2: =F2*Resumen!$D$1 -> 1607.28
A3: Salario Santi | C3: 24194.44 | D3: =C3*Resumen!$D$1 -> 5806.6656 | F3: =G3/Resumen!$D$1 -> 1875 | G3: 450
A4: Salario Bea | C4: =D4/Resumen!$D$1 -> 13450 | D4: 3228 | F4: =G4/Resumen!$D$1 -> 5383.875 | G4: 1292.13
A5: Ingresos extra | C5: =D5/Resumen!$D$1 -> 1875 | D5: 450 | F5: =G5/Resumen!$D$1 -> 682.70833 | G5: 163.85
A6: TOTAL INGRESOS | C6: =SUM(C3:C5) -> 39519.44 | D6: =SUM(D3:D5) -> 9484.6656 | F6: =SUM(F2:F5) -> 14638.583 | G6: =SUM(G2:G5) -> 3513.26 | H6: ahorrado este mes a 24 jun | J6: lo que tenemos en cuentas
A7: BALANCE (Ingreso - Gasto) | D7: =D6-E32 -> 79.6036
F8: 8000 | G8: =F8*Resumen!$D$1 -> 1920 | H8: alquiler mes
A9: GASTOS MENSUALES
G10: =G6-G8 -> 1593.26 | H10: ahorrado real con piso pagado
A11: RESUMEN POR CATEGORÍA
A12: Categoría | B12: Nº Gastos | C12: Total AED | D12: Total EUR
A13: Restaurantes | B13: =COUNTIF($B$37:$B$99,A13)+COUNTIF($G$37:$G$56,A13)+COUNTIF($L$37:$L$56,A13)+COUNTIF($Q$37:$Q$56,A13)+COUNTIF($V$37:$V$56,A13) -> 16 | C13: =SUMIF($B$37:$B$100,A13,$C$37:$C$100)+SUMIF($G$37:$G$100,A13,$H$37:$H$100)+SUMIF($L$37:$L$100,A13,$M$37:$M$100)+SUMIF($Q$37:$Q$100,A13,$R$37:$R$100)+SUMIF($V$37:$V$100,A13,$W$37:$W$100) -> 1983 | D13: =SUMIF($B$37:$B$100,A13,$D$37:$D$100)+SUMIF($G$37:$G$100,A13,$I$37:$I$100)+SUMIF($L$37:$L$100,A13,$N$37:$N$100)+SUMIF($Q$37:$Q$100,A13,$S$37:$S$100)+SUMIF($V$37:$V$100,A13,$X$37:$X$100) -> 452.76
A14: Ocio | B14: =COUNTIF($B$37:$B$99,A14)+COUNTIF($G$37:$G$56,A14)+COUNTIF($L$37:$L$56,A14)+COUNTIF($Q$37:$Q$56,A14)+COUNTIF($V$37:$V$56,A14) -> 3 | C14: =SUMIF($B$37:$B$100,A14,$C$37:$C$100)+SUMIF($G$37:$G$100,A14,$H$37:$H$100)+SUMIF($L$37:$L$100,A14,$M$37:$M$100)+SUMIF($Q$37:$Q$100,A14,$R$37:$R$100)+SUMIF($V$37:$V$100,A14,$W$37:$W$100) -> 822 | D14: =SUMIF($B$37:$B$100,A14,$D$37:$D$100)+SUMIF($G$37:$G$100,A14,$I$37:$I$100)+SUMIF($L$37:$L$100,A14,$N$37:$N$100)+SUMIF($Q$37:$Q$100,A14,$S$37:$S$100)+SUMIF($V$37:$V$100,A14,$X$37:$X$100) -> 13.94
A15: Compras | B15: =COUNTIF($B$37:$B$99,A15)+COUNTIF($G$37:$G$56,A15)+COUNTIF($L$37:$L$56,A15)+COUNTIF($Q$37:$Q$56,A15)+COUNTIF($V$37:$V$56,A15) -> 1 | C15: =SUMIF($B$37:$B$100,A15,$C$37:$C$100)+SUMIF($G$37:$G$100,A15,$H$37:$H$100)+SUMIF($L$37:$L$100,A15,$M$37:$M$100)+SUMIF($Q$37:$Q$100,A15,$R$37:$R$100)+SUMIF($V$37:$V$100,A15,$W$37:$W$100) -> 0 | D15: =SUMIF($B$37:$B$100,A15,$D$37:$D$100)+SUMIF($G$37:$G$100,A15,$I$37:$I$100)+SUMIF($L$37:$L$100,A15,$N$37:$N$100)+SUMIF($Q$37:$Q$100,A15,$S$37:$S$100)+SUMIF($V$37:$V$100,A15,$X$37:$X$100) -> 116.29
A16: Salud | B16: =COUNTIF($B$37:$B$99,A16)+COUNTIF($G$37:$G$56,A16)+COUNTIF($L$37:$L$56,A16)+COUNTIF($Q$37:$Q$56,A16)+COUNTIF($V$37:$V$56,A16) -> 7 | C16: =SUMIF($B$37:$B$100,A16,$C$37:$C$100)+SUMIF($G$37:$G$100,A16,$H$37:$H$100)+SUMIF($L$37:$L$100,A16,$M$37:$M$100)+SUMIF($Q$37:$Q$100,A16,$R$37:$R$100)+SUMIF($V$37:$V$100,A16,$W$37:$W$100) -> 0 | D16: =SUMIF($B$37:$B$100,A16,$D$37:$D$100)+SUMIF($G$37:$G$100,A16,$I$37:$I$100)+SUMIF($L$37:$L$100,A16,$N$37:$N$100)+SUMIF($Q$37:$Q$100,A16,$S$37:$S$100)+SUMIF($V$37:$V$100,A16,$X$37:$X$100) -> 513.67
A17: Viajes | B17: =COUNTIF($B$37:$B$99,A17)+COUNTIF($G$37:$G$56,A17)+COUNTIF($L$37:$L$56,A17)+COUNTIF($Q$37:$Q$56,A17)+COUNTIF($V$37:$V$56,A17) -> 0 | C17: =SUMIF($B$37:$B$100,A17,$C$37:$C$100)+SUMIF($G$37:$G$100,A17,$H$37:$H$100)+SUMIF($L$37:$L$100,A17,$M$37:$M$100)+SUMIF($Q$37:$Q$100,A17,$R$37:$R$100)+SUMIF($V$37:$V$100,A17,$W$37:$W$100) -> 0 | D17: =SUMIF($B$37:$B$100,A17,$D$37:$D$100)+SUMIF($G$37:$G$100,A17,$I$37:$I$100)+SUMIF($L$37:$L$100,A17,$N$37:$N$100)+SUMIF($Q$37:$Q$100,A17,$S$37:$S$100)+SUMIF($V$37:$V$100,A17,$X$37:$X$100) -> 0
A18: Santi | B18: =COUNTIF($B$37:$B$99,A18)+COUNTIF($G$37:$G$56,A18)+COUNTIF($L$37:$L$56,A18)+COUNTIF($Q$37:$Q$56,A18)+COUNTIF($V$37:$V$56,A18) -> 12 | C18: =SUMIF($B$37:$B$100,A18,$C$37:$C$100)+SUMIF($G$37:$G$100,A18,$H$37:$H$100)+SUMIF($L$37:$L$100,A18,$M$37:$M$100)+SUMIF($Q$37:$Q$100,A18,$R$37:$R$100)+SUMIF($V$37:$V$100,A18,$W$37:$W$100) -> 901.2 | D18: =SUMIF($B$37:$B$100,A18,$D$37:$D$100)+SUMIF($G$37:$G$100,A18,$I$37:$I$100)+SUMIF($L$37:$L$100,A18,$N$37:$N$100)+SUMIF($Q$37:$Q$100,A18,$S$37:$S$100)+SUMIF($V$37:$V$100,A18,$X$37:$X$100) -> 646.71
A19: Bea | B19: =COUNTIF($B$37:$B$99,A19)+COUNTIF($G$37:$G$56,A19)+COUNTIF($L$37:$L$56,A19)+COUNTIF($Q$37:$Q$56,A19)+COUNTIF($V$37:$V$56,A19) -> 14 | C19: =SUMIF($B$37:$B$100,A19,$C$37:$C$100)+SUMIF($G$37:$G$100,A19,$H$37:$H$100)+SUMIF($L$37:$L$100,A19,$M$37:$M$100)+SUMIF($Q$37:$Q$100,A19,$R$37:$R$100)+SUMIF($V$37:$V$100,A19,$W$37:$W$100) -> 5299.5 | D19: =SUMIF($B$37:$B$100,A19,$D$37:$D$100)+SUMIF($G$37:$G$100,A19,$I$37:$I$100)+SUMIF($L$37:$L$100,A19,$N$37:$N$100)+SUMIF($Q$37:$Q$100,A19,$S$37:$S$100)+SUMIF($V$37:$V$100,A19,$X$37:$X$100) -> 350.12
A20: Personal | B20: =COUNTIF($B$37:$B$99,A20)+COUNTIF($G$37:$G$56,A20)+COUNTIF($L$37:$L$56,A20)+COUNTIF($Q$37:$Q$56,A20)+COUNTIF($V$37:$V$56,A20) -> 0 | C20: =SUMIF($B$37:$B$100,A20,$C$37:$C$100)+SUMIF($G$37:$G$100,A20,$H$37:$H$100)+SUMIF($L$37:$L$100,A20,$M$37:$M$100)+SUMIF($Q$37:$Q$100,A20,$R$37:$R$100)+SUMIF($V$37:$V$100,A20,$W$37:$W$100) -> 0 | D20: =SUMIF($B$37:$B$100,A20,$D$37:$D$100)+SUMIF($G$37:$G$100,A20,$I$37:$I$100)+SUMIF($L$37:$L$100,A20,$N$37:$N$100)+SUMIF($Q$37:$Q$100,A20,$S$37:$S$100)+SUMIF($V$37:$V$100,A20,$X$37:$X$100) -> 0
A21: Transporte | B21: =COUNTIF($B$37:$B$99,A21)+COUNTIF($G$37:$G$56,A21)+COUNTIF($L$37:$L$56,A21)+COUNTIF($Q$37:$Q$56,A21)+COUNTIF($V$37:$V$56,A21) -> 24 | C21: =SUMIF($B$37:$B$100,A21,$C$37:$C$100)+SUMIF($G$37:$G$100,A21,$H$37:$H$100)+SUMIF($L$37:$L$100,A21,$M$37:$M$100)+SUMIF($Q$37:$Q$100,A21,$R$37:$R$100)+SUMIF($V$37:$V$100,A21,$W$37:$W$100) -> 1399.56 | D21: =SUMIF($B$37:$B$100,A21,$D$37:$D$100)+SUMIF($G$37:$G$100,A21,$I$37:$I$100)+SUMIF($L$37:$L$100,A21,$N$37:$N$100)+SUMIF($Q$37:$Q$100,A21,$S$37:$S$100)+SUMIF($V$37:$V$100,A21,$X$37:$X$100) -> 272.22
A22: Regalos | B22: =COUNTIF($B$37:$B$99,A22)+COUNTIF($G$37:$G$56,A22)+COUNTIF($L$37:$L$56,A22)+COUNTIF($Q$37:$Q$56,A22)+COUNTIF($V$37:$V$56,A22) -> 0 | C22: =SUMIF($B$37:$B$100,A22,$C$37:$C$100)+SUMIF($G$37:$G$100,A22,$H$37:$H$100)+SUMIF($L$37:$L$100,A22,$M$37:$M$100)+SUMIF($Q$37:$Q$100,A22,$R$37:$R$100)+SUMIF($V$37:$V$100,A22,$W$37:$W$100) -> 0 | D22: =SUMIF($B$37:$B$100,A22,$D$37:$D$100)+SUMIF($G$37:$G$100,A22,$I$37:$I$100)+SUMIF($L$37:$L$100,A22,$N$37:$N$100)+SUMIF($Q$37:$Q$100,A22,$S$37:$S$100)+SUMIF($V$37:$V$100,A22,$X$37:$X$100) -> 0
A23: Alquiler piso | B23: =COUNTIF($B$37:$B$99,A23)+COUNTIF($G$37:$G$56,A23)+COUNTIF($L$37:$L$56,A23)+COUNTIF($Q$37:$Q$56,A23)+COUNTIF($V$37:$V$56,A23) -> 1 | C23: =SUMIF($B$37:$B$100,A23,$C$37:$C$100)+SUMIF($G$37:$G$100,A23,$H$37:$H$100)+SUMIF($L$37:$L$100,A23,$M$37:$M$100)+SUMIF($Q$37:$Q$100,A23,$R$37:$R$100)+SUMIF($V$37:$V$100,A23,$W$37:$W$100) -> 8000 | D23: =SUMIF($B$37:$B$100,A23,$D$37:$D$100)+SUMIF($G$37:$G$100,A23,$I$37:$I$100)+SUMIF($L$37:$L$100,A23,$N$37:$N$100)+SUMIF($Q$37:$Q$100,A23,$S$37:$S$100)+SUMIF($V$37:$V$100,A23,$X$37:$X$100) -> 0
A24: Mudanza | B24: =COUNTIF($B$37:$B$99,A24)+COUNTIF($G$37:$G$56,A24)+COUNTIF($L$37:$L$56,A24)+COUNTIF($Q$37:$Q$56,A24)+COUNTIF($V$37:$V$56,A24) -> 0 | C24: =SUMIF($B$37:$B$100,A24,$C$37:$C$100)+SUMIF($G$37:$G$100,A24,$H$37:$H$100)+SUMIF($L$37:$L$100,A24,$M$37:$M$100)+SUMIF($Q$37:$Q$100,A24,$R$37:$R$100)+SUMIF($V$37:$V$100,A24,$W$37:$W$100) -> 0 | D24: =SUMIF($B$37:$B$100,A24,$D$37:$D$100)+SUMIF($G$37:$G$100,A24,$I$37:$I$100)+SUMIF($L$37:$L$100,A24,$N$37:$N$100)+SUMIF($Q$37:$Q$100,A24,$S$37:$S$100)+SUMIF($V$37:$V$100,A24,$X$37:$X$100) -> 0
... A31: Suscripciones | B31: =COUNTIF($B$37:$B$99,A31)+COUNTIF($G$37:$G$56,A31)+COUNTIF($L$37:$L$56,A31)+COUNTIF($Q$37:$Q$56,A31)+COUNTIF($V$37:$V$56,A31) -> 0 | C31: =SUMIF($B$37:$B$100,A31,$C$37:$C$100)+SUMIF($G$37:$G$100,A31,$H$37:$H$100)+SUMIF($L$37:$L$100,A31,$M$37:$M$100)+SUMIF($Q$37:$Q$100,A31,$R$37:$R$100)+SUMIF($V$37:$V$100,A31,$W$37:$W$100) -> 0 | D31: =SUMIF($B$37:$B$100,A31,$D$37:$D$100)+SUMIF($G$37:$G$100,A31,$I$37:$I$100)+SUMIF($L$37:$L$100,A31,$N$37:$N$100)+SUMIF($Q$37:$Q$100,A31,$S$37:$S$100)+SUMIF($V$37:$V$100,A31,$X$37:$X$100) -> 0
A32: TOTAL MES | B32: =SUM(B13:B31) -> 122 | C32: =SUM(C13:C31) -> 25618.3 | D32: =SUM(D13:D31) -> 3256.67 | E32: =D32+(C32*Resumen!D1) -> 9405.062
A34: REGISTRO SEMANAL
A35: SEMANA 1 | F35: SEMANA 2 | K35: SEMANA 3 | P35: SEMANA 4 | U35: SEMANA 5
A36: Concepto | B36: Categ. | C36: AED | D36: EUR | E36: Fecha | F36: Concepto | G36: Categ. | H36: AED | I36: EUR | J36: Fecha | K36: Concepto | L36: Categ. | M36: AED | N36: EUR | O36: Fecha | P36: Concepto | Q36: Categ. | R36: AED | S36: EUR | T36: Fecha | U36: Concepto | V36: Categ. | W36: AED | X36: EUR
A37: Compra mes | B37: Supermercado | C37: 1028 | E37: 46174 | F37: careem | G37: Delivery | H37: 96.48 | K37: irish vicker | L37: Restaurantes | M37: 192 | P37: careem ride | Q37: Transporte | R37: 141
A38: the groom uñas | B38: Bea | C38: 136.5 | F38: careem ride | G38: Transporte | H38: 79 | K38: the lounge | L38: Restaurantes | M38: 60 | P38: isd padel | Q38: Ocio | R38: 22
A39: noon | B39: Delivery | C39: 167.89 | F39: careem ride | G39: Transporte | H39: 85.27 | K39: arabia taxi | L39: Transporte | M39: 12.5 | P39: la fragola café | Q39: Restaurantes | R39: 20
A40: emira cent.cooling | B40: Suministros piso | C40: 203.7 | F40: careem quick | G40: Delivery | H40: 35.42 | K40: pullman down | L40: Restaurantes | M40: 518 | P40: first track govern | Q40: Tasas | R40: 374.55
A41: careem quick | B41: Delivery | C41: 76.25 | F41: careem | G41: Delivery | H41: 54.39 | K41: the lounge | L41: Restaurantes | M41: 65 | P41: amer | Q41: Tasas | R41: 126
A42: emirates | B42: Bea | C42: 4460 | F42: ons jabeur torneo | G42: Santi | H42: 225 | K42: careem | L42: Delivery | M42: 73.5 | P42: apple | Q42: Otros | R42: 189.76
A43: careem ride | B43: Transporte | C43: 105.62 | F43: dubai mall | G43: Santi | H43: 489 | K43: udrive rent | L43: Transporte | M43: 247.5 | P43: lime | Q43: Transporte | R43: 29.5
A44: Ergon agora rest | B44: Restaurantes | C44: 240 | F44: global sports | G44: Ocio | H44: 800 | K44: careem ride | L44: Transporte | M44: 48.15 | P44: careem | Q44: Delivery | R44: 28.61
A45: careem | B45: Delivery | C45: 95.94 | F45: careem | G45: Delivery | H45: 160.2 | K45: playtomic | L45: Bea | M45: 104 | P45: first track govern | Q45: Tasas | R45: 1343
A46: yaldi udrive | B46: Transporte | C46: 6.5 | F46: careem ride | G46: Transporte | H46: 173.31 | K46: careem quick | L46: Delivery | M46: 28.45 | P46: first track govern | Q46: Tasas | R46: 664
A47: careem ride | B47: Transporte | C47: 87.98 | E47: 46180 | F47: careem ride | G47: Transporte | H47: 13 | K47: city max hotel | L47: Restaurantes | M47: 253 | P47: arabia taxi | Q47: Transporte | R47: 44.5
A48: careem | B48: Delivery | D48: 73.01 | F48: careem | G48: Delivery | H48: 210.23 | K48: black white groc | L48: Supermercado | M48: 13 | P48: padel edit | Q48: Bea | R48: 110 | T48: 46197
A49: linkedin | B49: Bea | D49: 22 | F49: noon | G49: Delivery | H49: 75.59 | K49: noon | L49: Delivery | M49: 28.99 | P49: careem | Q49: Delivery | S49: 24.96
A50: careem | B50: Delivery | D50: 46.74 | F50: asics | G50: Bea | H50: 489 | K50: careem ride | L50: Transporte | M50: 13 | P50: careem | Q50: Delivery | S50: 26.89
A51: careem | B51: Delivery | D51: 33.55 | F51: playtomic | G51: Santi | H51: 187.2 | K51: careem | L51: Delivery | M51: 45.06 | P51: jo care | Q51: Transporte | S51: 23.96
A52: noon | B52: Delivery | D52: 9.01 | F52: careem | G52: Delivery | H52: 140.2 | K52: royal develop | L52: Suministros piso | M52: 44.5 | P52: careem | Q52: Delivery | S52: 14.93
A53: ons jabeur | B53: Ocio | D53: 2.87 | F53: careem ride | G53: Transporte | H53: 159.23 | K53: noqodi online | L53: Tasas | M53: 1016.8 | P53: better mind bus | Q53: Tasas | S53: 77.59
A54: seguro españa | B54: Salud | D54: 67.79 | F54: yahya seafood | G54: Restaurantes | H54: 105 | K54: noqodi online | L54: Tasas | M54: 206.3 | P54: care well care | Q54: Salud | S54: 28.88 | T54: 46197
A55: seguro españa | B55: Salud | D55: 54.67 | F55: careem ride | G55: Transporte | H55: 23.25 | K55: careem quick | L55: Delivery | M55: 27.2 | P55: alquiler | Q55: Alquiler piso | R55: 8000
A56: google one | B56: Santi | D56: 21.99 | F56: careem | G56: Delivery | H56: 160.2 | J56: 46187 | K56: talabat | L56: Delivery | M56: 65.15 | P56: careem | Q56: Delivery | R56: 64.4
A57: avis alquiler | B57: Transporte | D57: 57.78 | F57: careem | G57: Delivery | I57: 45.02 | K57: careem | L57: Delivery | M57: 255.18 | P57: jo care | Q57: Transporte | R57: 53.5
A58: intereses ibercaja | B58: Otros | D58: 29.99 | F58: careem | G58: Delivery | I58: 19.99 | K58: careem ride | L58: Transporte | M58: 21.75 | P58: cena basta | Q58: Restaurantes | R58: 530
A59: metro madrid | B59: Bea | D59: 9.8 | F59: the lounge dub | G59: Restaurantes | I59: 47.26 | K59: lime | L59: Transporte | M59: 18.5
A60: desayuno | B60: Bea | D60: 5.2 | K60: careem ride | L60: Transporte | M60: 36.5
A61: comida | B61: Restaurantes | D61: 97.2 | K61: black white groc | L61: Supermercado | M61: 18
A62: zara | B62: Bea | D62: 60.8 | K62: african estearn | L62: Supermercado | M62: 10 | O62: 46194
A63: natura | B63: Bea | D63: 60.7 | K63: cars taxi | L63: Transporte | N63: 5.89
A64: zara home | B64: Hogar | D64: 147.93 | K64: careem | L64: Delivery | N64: 22.09
A65: primor | B65: Compras | D65: 116.29 | K65: jo care | L65: Transporte | N65: 14.71
A66: mercadona | B66: Supermercado | D66: 149.83 | K66: tashas | L66: Otros | N66: 6.6
A67: bluebanan | B67: Santi | D67: 21 | K67: careem | L67: Delivery | N67: 25.68
A68: heymondo | B68: Salud | D68: 117.53 | K68: renfe | L68: Bea | N68: 62.4
A69: recarga movil | B69: Bea | D69: 5 | K69: Nola | L69: Bea | N69: 22.1
A70: careem | B70: Transporte | D70: 4 | K70: careem | L70: Delivery | N70: 30.73
A71: dominio web | B71: Bea | D71: 10.46 | K71: careem | L71: Delivery | N71: 34.12
A72: careem | B72: Delivery | C72: 86.1 | K72: careem | L72: Delivery | N72: 30.91
A73: eroski | B73: Supermercado | D73: 11.96 | K73: careem | L73: Transporte | N73: 17.32
A74: bizum | B74: Santi | D74: 46 | K74: careem | L74: Delivery | N74: 11.3
A75: dni | B75: Santi | D75: 12 | K75: isd cat | L75: Ocio | N75: 11.07
A76: ropa | B76: Santi | D76: 59.99
A77: scalpers | B77: Santi | D77: 52
A78: little dragon | B78: Restaurantes | D78: 52.2
A79: kaotico rest | B79: Restaurantes | D79: 33.6
A80: rest dolce | B80: Restaurantes | D80: 10
A81: claude suscr | B81: Santi | D81: 108.9
A82: cortefiel | B82: Santi | D82: 120.23
A83: women secret | B83: Bea | D83: 51.76
A84: zara | B84: Santi | D84: 204.6
A85: natura | B85: Bea | D85: 39.9
A86: peajes | B86: Transporte | D86: 11.4
A87: farmacia | B87: Salud | D87: 18.35
... A98: aeropuerto | B98: Transporte | D98: 12.8
A99: peajes
A101: TOTAL | C101: =SUM(C37:C100) -> 6694.48 | D101: =SUM(D37:D100) -> 2652.27 | H101: =SUM(H37:H100) -> 3760.97 | I101: =SUM(I37:I100) -> 112.27 | M101: =SUM(M37:M100) -> 3422.03 | N101: =SUM(N37:N100) -> 294.92 | R101: =SUM(R37:R100) -> 11740.82 | S101: =SUM(S37:S100) -> 197.21 | W101: =SUM(W37:W100) -> 0 | X101: =SUM(X37:X100) -> 0

Sheet Julio
A1: INGRESOS MENSUALES
A2: Concepto | C2: Total AED | D2: Total EUR
A3: Salario Santi | C3: =Resumen!$C$4 -> 25000 | D3: =C3*Resumen!$D$1 -> 6000
A4: Salario Bea | C4: =D4/Resumen!$D$1 -> 3583.3333 | D4: 860
A5: Ingresos extra | C5: =D5/Resumen!$D$1 -> 1875 | D5: 450
A6: TOTAL INGRESOS | C6: =SUM(C3:C5) -> 30458.333 | D6: =SUM(D3:D5) -> 7310
A7: BALANCE (Ingreso - Gasto) | C7: =C6-C32 -> 13346.232 | D7: =D6-D32 -> 3203.0956
A9: GASTOS MENSUALES
A11: RESUMEN POR CATEGORÍA
A12: Categoría | B12: Nº Gastos | C12: Total AED | D12: Total EUR
A13: Restaurantes | B13: =COUNTIF(B37:B91,A13)+COUNTIF(G37:G91,A13)+COUNTIF(L37:L91,A13)+COUNTIF(Q37:Q91,A13)+COUNTIF(V37:V91,A13) -> 10 | C13: =SUMIF(B37:B91,A13,C37:C91)+SUMIF(G37:G91,A13,H37:H91)+SUMIF(L37:L91,A13,M37:M91)+SUMIF(Q37:Q91,A13,R37:R91)+SUMIF(V37:V91,A13,W37:W91)+(SUMIF(B37:B91,A13,D37:D91)+SUMIF(G37:G91,A13,I37:I91)+SUMIF(L37:L91,A13,N37:N91)+SUMIF(Q37:Q91,A13,S37:S91)+SUMIF(V37:V91,A13,X37:X91))/Resumen!$D$1 -> 1238.125 | D13: =C13*Resumen!$D$1 -> 297.15
A14: Ocio | B14: =COUNTIF(B37:B91,A14)+COUNTIF(G37:G91,A14)+COUNTIF(L37:L91,A14)+COUNTIF(Q37:Q91,A14)+COUNTIF(V37:V91,A14) -> 1 | C14: =SUMIF(B37:B91,A14,C37:C91)+SUMIF(G37:G91,A14,H37:H91)+SUMIF(L37:L91,A14,M37:M91)+SUMIF(Q37:Q91,A14,R37:R91)+SUMIF(V37:V91,A14,W37:W91)+(SUMIF(B37:B91,A14,D37:D91)+SUMIF(G37:G91,A14,I37:I91)+SUMIF(L37:L91,A14,N37:N91)+SUMIF(Q37:Q91,A14,S37:S91)+SUMIF(V37:V91,A14,X37:X91))/Resumen!$D$1 -> 20.37 | D14: =C14*Resumen!$D$1 -> 4.8888
A15: Compras | B15: =COUNTIF(B37:B91,A15)+COUNTIF(G37:G91,A15)+COUNTIF(L37:L91,A15)+COUNTIF(Q37:Q91,A15)+COUNTIF(V37:V91,A15) -> 9 | C15: =SUMIF(B37:B91,A15,C37:C91)+SUMIF(G37:G91,A15,H37:H91)+SUMIF(L37:L91,A15,M37:M91)+SUMIF(Q37:Q91,A15,R37:R91)+SUMIF(V37:V91,A15,W37:W91)+(SUMIF(B37:B91,A15,D37:D91)+SUMIF(G37:G91,A15,I37:I91)+SUMIF(L37:L91,A15,N37:N91)+SUMIF(Q37:Q91,A15,S37:S91)+SUMIF(V37:V91,A15,X37:X91))/Resumen!$D$1 -> 1310.78 | D15: =C15*Resumen!$D$1 -> 314.5872
A16: Salud | B16: =COUNTIF(B37:B91,A16)+COUNTIF(G37:G91,A16)+COUNTIF(L37:L91,A16)+COUNTIF(Q37:Q91,A16)+COUNTIF(V37:V91,A16) -> 6 | C16: =SUMIF(B37:B91,A16,C37:C91)+SUMIF(G37:G91,A16,H37:H91)+SUMIF(L37:L91,A16,M37:M91)+SUMIF(Q37:Q91,A16,R37:R91)+SUMIF(V37:V91,A16,W37:W91)+(SUMIF(B37:B91,A16,D37:D91)+SUMIF(G37:G91,A16,I37:I91)+SUMIF(L37:L91,A16,N37:N91)+SUMIF(Q37:Q91,A16,S37:S91)+SUMIF(V37:V91,A16,X37:X91))/Resumen!$D$1 -> 4943.75 | D16: =C16*Resumen!$D$1 -> 1186.5
A17: Viajes | B17: =COUNTIF(B37:B91,A17)+COUNTIF(G37:G91,A17)+COUNTIF(L37:L91,A17)+COUNTIF(Q37:Q91,A17)+COUNTIF(V37:V91,A17) -> 0 | C17: =SUMIF(B37:B91,A17,C37:C91)+SUMIF(G37:G91,A17,H37:H91)+SUMIF(L37:L91,A17,M37:M91)+SUMIF(Q37:Q91,A17,R37:R91)+SUMIF(V37:V91,A17,W37:W91)+(SUMIF(B37:B91,A17,D37:D91)+SUMIF(G37:G91,A17,I37:I91)+SUMIF(L37:L91,A17,N37:N91)+SUMIF(Q37:Q91,A17,S37:S91)+SUMIF(V37:V91,A17,X37:X91))/Resumen!$D$1 -> 0 | D17: =C17*Resumen!$D$1 -> 0
A18: Santi | B18: =COUNTIF(B37:B91,A18)+COUNTIF(G37:G91,A18)+COUNTIF(L37:L91,A18)+COUNTIF(Q37:Q91,A18)+COUNTIF(V37:V91,A18) -> 2 | C18: =SUMIF(B37:B91,A18,C37:C91)+SUMIF(G37:G91,A18,H37:H91)+SUMIF(L37:L91,A18,M37:M91)+SUMIF(Q37:Q91,A18,R37:R91)+SUMIF(V37:V91,A18,W37:W91)+(SUMIF(B37:B91,A18,D37:D91)+SUMIF(G37:G91,A18,I37:I91)+SUMIF(L37:L91,A18,N37:N91)+SUMIF(Q37:Q91,A18,S37:S91)+SUMIF(V37:V91,A18,X37:X91))/Resumen!$D$1 -> 545.375 | D18: =C18*Resumen!$D$1 -> 130.89
A19: Bea | B19: =COUNTIF(B37:B91,A19)+COUNTIF(G37:G91,A19)+COUNTIF(L37:L91,A19)+COUNTIF(Q37:Q91,A19)+COUNTIF(V37:V91,A19) -> 14 | C19: =SUMIF(B37:B91,A19,C37:C91)+SUMIF(G37:G91,A19,H37:H91)+SUMIF(L37:L91,A19,M37:M91)+SUMIF(Q37:Q91,A19,R37:R91)+SUMIF(V37:V91,A19,W37:W91)+(SUMIF(B37:B91,A19,D37:D91)+SUMIF(G37:G91,A19,I37:I91)+SUMIF(L37:L91,A19,N37:N91)+SUMIF(Q37:Q91,A19,S37:S91)+SUMIF(V37:V91,A19,X37:X91))/Resumen!$D$1 -> 2205.7817 | D19: =C19*Resumen!$D$1 -> 529.3876
A20: Personal | B20: =COUNTIF(B37:B91,A20)+COUNTIF(G37:G91,A20)+COUNTIF(L37:L91,A20)+COUNTIF(Q37:Q91,A20)+COUNTIF(V37:V91,A20) -> 0 | C20: =SUMIF(B37:B91,A20,C37:C91)+SUMIF(G37:G91,A20,H37:H91)+SUMIF(L37:L91,A20,M37:M91)+SUMIF(Q37:Q91,A20,R37:R91)+SUMIF(V37:V91,A20,W37:W91)+(SUMIF(B37:B91,A20,D37:D91)+SUMIF(G37:G91,A20,I37:I91)+SUMIF(L37:L91,A20,N37:N91)+SUMIF(Q37:Q91,A20,S37:S91)+SUMIF(V37:V91,A20,X37:X91))/Resumen!$D$1 -> 0 | D20: =C20*Resumen!$D$1 -> 0
A21: Transporte | B21: =COUNTIF(B37:B91,A21)+COUNTIF(G37:G91,A21)+COUNTIF(L37:L91,A21)+COUNTIF(Q37:Q91,A21)+COUNTIF(V37:V91,A21) -> 28 | C21: =SUMIF(B37:B91,A21,C37:C91)+SUMIF(G37:G91,A21,H37:H91)+SUMIF(L37:L91,A21,M37:M91)+SUMIF(Q37:Q91,A21,R37:R91)+SUMIF(V37:V91,A21,W37:W91)+(SUMIF(B37:B91,A21,D37:D91)+SUMIF(G37:G91,A21,I37:I91)+SUMIF(L37:L91,A21,N37:N91)+SUMIF(Q37:Q91,A21,S37:S91)+SUMIF(V37:V91,A21,X37:X91))/Resumen!$D$1 -> 1184.3167 | D21: =C21*Resumen!$D$1 -> 284.236
A22: Regalos | B22: =COUNTIF(B37:B91,A22)+COUNTIF(G37:G91,A22)+COUNTIF(L37:L91,A22)+COUNTIF(Q37:Q91,A22)+COUNTIF(V37:V91,A22) -> 1 | C22: =SUMIF(B37:B91,A22,C37:C91)+SUMIF(G37:G91,A22,H37:H91)+SUMIF(L37:L91,A22,M37:M91)+SUMIF(Q37:Q91,A22,R37:R91)+SUMIF(V37:V91,A22,W37:W91)+(SUMIF(B37:B91,A22,D37:D91)+SUMIF(G37:G91,A22,I37:I91)+SUMIF(L37:L91,A22,N37:N91)+SUMIF(Q37:Q91,A22,S37:S91)+SUMIF(V37:V91,A22,X37:X91))/Resumen!$D$1 -> 833.33333 | D22: =C22*Resumen!$D$1 -> 200
A23: Alquiler piso | B23: =COUNTIF(B37:B91,A23)+COUNTIF(G37:G91,A23)+COUNTIF(L37:L91,A23)+COUNTIF(Q37:Q91,A23)+COUNTIF(V37:V91,A23) -> 0 | C23: =SUMIF(B37:B91,A23,C37:C91)+SUMIF(G37:G91,A23,H37:H91)+SUMIF(L37:L91,A23,M37:M91)+SUMIF(Q37:Q91,A23,R37:R91)+SUMIF(V37:V91,A23,W37:W91)+(SUMIF(B37:B91,A23,D37:D91)+SUMIF(G37:G91,A23,I37:I91)+SUMIF(L37:L91,A23,N37:N91)+SUMIF(Q37:Q91,A23,S37:S91)+SUMIF(V37:V91,A23,X37:X91))/Resumen!$D$1 -> 0 | D23: =C23*Resumen!$D$1 -> 0
A24: Mudanza | B24: =COUNTIF(B37:B91,A24)+COUNTIF(G37:G91,A24)+COUNTIF(L37:L91,A24)+COUNTIF(Q37:Q91,A24)+COUNTIF(V37:V91,A24) -> 0 | C24: =SUMIF(B37:B91,A24,C37:C91)+SUMIF(G37:G91,A24,H37:H91)+SUMIF(L37:L91,A24,M37:M91)+SUMIF(Q37:Q91,A24,R37:R91)+SUMIF(V37:V91,A24,W37:W91)+(SUMIF(B37:B91,A24,D37:D91)+SUMIF(G37:G91,A24,I37:I91)+SUMIF(L37:L91,A24,N37:N91)+SUMIF(Q37:Q91,A24,S37:S91)+SUMIF(V37:V91,A24,X37:X91))/Resumen!$D$1 -> 0 | D24: =C24*Resumen!$D$1 -> 0
A25: Tasas | B25: =COUNTIF(B37:B91,A25)+COUNTIF(G37:G91,A25)+COUNTIF(L37:L91,A25)+COUNTIF(Q37:Q91,A25)+COUNTIF(V37:V91,A25) -> 1 | C25: =SUMIF(B37:B91,A25,C37:C91)+SUMIF(G37:G91,A25,H37:H91)+SUMIF(L37:L91,A25,M37:M91)+SUMIF(Q37:Q91,A25,R37:R91)+SUMIF(V37:V91,A25,W37:W91)+(SUMIF(B37:B91,A25,D37:D91)+SUMIF(G37:G91,A25,I37:I91)+SUMIF(L37:L91,A25,N37:N91)+SUMIF(Q37:Q91,A25,S37:S91)+SUMIF(V37:V91,A25,X37:X91))/Resumen!$D$1 -> 6.3 | D25: =C25*Resumen!$D$1 -> 1.512
A26: Suministros piso | B26: =COUNTIF(B37:B91,A26)+COUNTIF(G37:G91,A26)+COUNTIF(L37:L91,A26)+COUNTIF(Q37:Q91,A26)+COUNTIF(V37:V91,A26) -> 2 | C26: =SUMIF(B37:B91,A26,C37:C91)+SUMIF(G37:G91,A26,H37:H91)+SUMIF(L37:L91,A26,M37:M91)+SUMIF(Q37:Q91,A26,R37:R91)+SUMIF(V37:V91,A26,W37:W91)+(SUMIF(B37:B91,A26,D37:D91)+SUMIF(G37:G91,A26,I37:I91)+SUMIF(L37:L91,A26,N37:N91)+SUMIF(Q37:Q91,A26,S37:S91)+SUMIF(V37:V91,A26,X37:X91))/Resumen!$D$1 -> 279 | D26: =C26*Resumen!$D$1 -> 66.96
A27: Otros | B27: =COUNTIF(B37:B91,A27)+COUNTIF(G37:G91,A27)+COUNTIF(L37:L91,A27)+COUNTIF(Q37:Q91,A27)+COUNTIF(V37:V91,A27) -> 1 | C27: =SUMIF(B37:B91,A27,C37:C91)+SUMIF(G37:G91,A27,H37:H91)+SUMIF(L37:L91,A27,M37:M91)+SUMIF(Q37:Q91,A27,R37:R91)+SUMIF(V37:V91,A27,W37:W91)+(SUMIF(B37:B91,A27,D37:D91)+SUMIF(G37:G91,A27,I37:I91)+SUMIF(L37:L91,A27,N37:N91)+SUMIF(Q37:Q91,A27,S37:S91)+SUMIF(V37:V91,A27,X37:X91))/Resumen!$D$1 -> 70 | D27: =C27*Resumen!$D$1 -> 16.8
A28: Hogar | B28: =COUNTIF(B37:B91,A28)+COUNTIF(G37:G91,A28)+COUNTIF(L37:L91,A28)+COUNTIF(Q37:Q91,A28)+COUNTIF(V37:V91,A28) -> 3 | C28: =SUMIF(B37:B91,A28,C37:C91)+SUMIF(G37:G91,A28,H37:H91)+SUMIF(L37:L91,A28,M37:M91)+SUMIF(Q37:Q91,A28,R37:R91)+SUMIF(V37:V91,A28,W37:W91)+(SUMIF(B37:B91,A28,D37:D91)+SUMIF(G37:G91,A28,I37:I91)+SUMIF(L37:L91,A28,N37:N91)+SUMIF(Q37:Q91,A28,S37:S91)+SUMIF(V37:V91,A28,X37:X91))/Resumen!$D$1 -> 1310.5 | D28: =C28*Resumen!$D$1 -> 314.52
A29: Delivery | B29: =COUNTIF(B37:B91,A29)+COUNTIF(G37:G91,A29)+COUNTIF(L37:L91,A29)+COUNTIF(Q37:Q91,A29)+COUNTIF(V37:V91,A29) -> 13 | C29: =SUMIF(B37:B91,A29,C37:C91)+SUMIF(G37:G91,A29,H37:H91)+SUMIF(L37:L91,A29,M37:M91)+SUMIF(Q37:Q91,A29,R37:R91)+SUMIF(V37:V91,A29,W37:W91)+(SUMIF(B37:B91,A29,D37:D91)+SUMIF(G37:G91,A29,I37:I91)+SUMIF(L37:L91,A29,N37:N91)+SUMIF(Q37:Q91,A29,S37:S91)+SUMIF(V37:V91,A29,X37:X91))/Resumen!$D$1 -> 1180.795 | D29: =C29*Resumen!$D$1 -> 283.3908
A30: Supermercado | B30: =COUNTIF(B37:B91,A30)+COUNTIF(G37:G91,A30)+COUNTIF(L37:L91,A30)+COUNTIF(Q37:Q91,A30)+COUNTIF(V37:V91,A30) -> 17 | C30: =SUMIF(B37:B91,A30,C37:C91)+SUMIF(G37:G91,A30,H37:H91)+SUMIF(L37:L91,A30,M37:M91)+SUMIF(Q37:Q91,A30,R37:R91)+SUMIF(V37:V91,A30,W37:W91)+(SUMIF(B37:B91,A30,D37:D91)+SUMIF(G37:G91,A30,I37:I91)+SUMIF(L37:L91,A30,N37:N91)+SUMIF(Q37:Q91,A30,S37:S91)+SUMIF(V37:V91,A30,X37:X91))/Resumen!$D$1 -> 1950.555 | D30: =C30*Resumen!$D$1 -> 468.1332
A31: Suscripciones | B31: =COUNTIF(B37:B91,A31)+COUNTIF(G37:G91,A31)+COUNTIF(L37:L91,A31)+COUNTIF(Q37:Q91,A31)+COUNTIF(V37:V91,A31) -> 2 | C31: =SUMIF(B37:B91,A31,C37:C91)+SUMIF(G37:G91,A31,H37:H91)+SUMIF(L37:L91,A31,M37:M91)+SUMIF(Q37:Q91,A31,R37:R91)+SUMIF(V37:V91,A31,W37:W91)+(SUMIF(B37:B91,A31,D37:D91)+SUMIF(G37:G91,A31,I37:I91)+SUMIF(L37:L91,A31,N37:N91)+SUMIF(Q37:Q91,A31,S37:S91)+SUMIF(V37:V91,A31,X37:X91))/Resumen!$D$1 -> 33.12 | D31: =C31*Resumen!$D$1 -> 7.9488
A32: TOTAL MES | B32: =SUM(B13:B31) -> 110 | C32: =SUM(C13:C31) -> 17112.102 | D32: =SUM(D13:D31) -> 4106.9044
A34: REGISTRO SEMANAL
A35: SEMANA 1 | F35: SEMANA 2 | K35: SEMANA 3 | P35: SEMANA 4 | U35: SEMANA 5
A36: Concepto | B36: Categ. | C36: AED | D36: EUR | E36: Fecha | F36: Concepto | G36: Categ. | H36: AED | I36: EUR | J36: Fecha | K36: Concepto | L36: Categ. | M36: AED | N36: EUR | O36: Fecha | P36: Concepto | Q36: Categ. | R36: AED | S36: EUR | T36: Fecha | U36: Concepto | V36: Categ. | W36: AED | X36: EUR
A37: fertilitas | B37: Salud | D37: 151.25 | F37: RALLY STAR GENERAL TRA | G37: Otros | H37: 70 | J37: 46209
A38: seguro españa | B38: Salud | D38: 67.79 | F38: CAREEM DELIVERIES QUIK | G38: Delivery | H38: 29.08 | J38: 46209
A39: seguro españa | B39: Salud | D39: 54.67 | F39: AFRICAN AND EASTERN | G39: Supermercado | H39: 151 | J39: 46209
A40: google one | B40: Santi | D40: 21.99 | F40: Smart Dubai Government | G40: Tasas | H40: 6.3 | J40: 46209
A41: claude suscr | B41: Santi | D41: 108.9 | F41: APPLE.COM/BILL | G41: Suscripciones | H41: 4.12 | J41: 46210
A42: linkedin | B42: Bea | C42: 22.99 | F42: CAREEM FOOD | G42: Delivery | H42: 97.65 | J42: 46210
A43: optivision gafas | B43: Salud | C43: 2249 | F43: noon.com | G43: Compras | H43: 72.89 | J43: 46211
A44: ADNOC BUSINESS BAY | B44: Transporte | C44: 167.75 | E44: 46200 | F44: noon.com | G44: Compras | H44: 37.98 | J44: 46211
A45: CAREEM QUIK | B45: Supermercado | C45: 89.94 | E45: 46200 | F45: CAREEM FOOD | G45: Delivery | H45: 75.6 | J45: 46212
A46: CAREEM DELIVERIES RH | B46: Delivery | C46: 112.26 | E46: 46200 | F46: CAREEM PLUS | G46: Suscripciones | H46: 29 | J46: 46213
A47: EATALY | B47: Restaurantes | C47: 223 | E47: 46200 | F47: CAREEM FOOD | G47: Delivery | H47: 75.05 | J47: 46214
A48: PAN EMIRATES DFC | B48: Hogar | C48: 532 | E48: 46200 | F48: talabat.com | G48: Delivery | H48: 88.3 | J48: 46214
A49: CAREEM SHOPS | B49: Compras | C49: 51.1 | E49: 46200 | F49: talabat.com | G49: Delivery | H49: 70.8 | J49: 46215
A50: DU Apple Pay | B50: Suministros piso | C50: 229 | E50: 46200 | F50: CAREEM FOOD | G50: Delivery | H50: 72.45 | J50: 46215
A51: CAREEM QUIK | B51: Supermercado | C51: 130.3 | E51: 46200 | F51: CAREEM QUIK | G51: Supermercado | H51: 37.15 | J51: 46215
A52: CAREEM QUIK | B52: Supermercado | C52: 14.15 | E52: 46200 | F52: CAREEM QUIK | G52: Supermercado | H52: 69.05 | J52: 46216
A53: DU Apple Pay | B53: Suministros piso | C53: 50 | E53: 46200 | F53: CAREEM SHOPS | G53: Compras | H53: 348.61 | J53: 46216
A54: Noon Minutes | B54: Supermercado | C54: 23.75 | E54: 46200 | F54: CAREEM QUIK | G54: Supermercado | H54: 63.97 | J54: 46216
A55: IKEA DFC ALFUTTAIM | B55: Hogar | C55: 660.6 | E55: 46201 | F55: CAREEM SHOPS | G55: Compras | H55: 113.85 | J55: 46216
... A58: H AND M ALSHAYA | B58: Compras | C58: 477 | E58: 46201 | F58: DUBAI TAXI | G58: Transporte | H58: 69.5 | J58: 46216
A59: LIME*3 VIAJES | B59: Transporte | C59: 9.5 | E59: 46202 | F59: jo care | G59: Transporte | I59: 15.8 | J59: revolut 1jul
A60: LIME*2 VIAJES | B60: Transporte | C60: 19.1 | E60: 46202 | F60: tayta inti | G60: Supermercado | I60: 8.4
A61: CAREEM SHOPS | B61: Compras | C61: 84 | E61: 46202 | F61: renfe | G61: Transporte | I61: 2.7
A62: Dott | B62: Transporte | C62: 9.5 | E62: 46203 | F62: stradivarius | G62: Bea | I62: 7.98
A63: CAREEM SHOPS | B63: Compras | C63: 26.85 | E63: 46203 | F63: bershka | G63: Bea | I63: 13.79
A64: PULLMAN DOWNTOWN | B64: Restaurantes | C64: 373 | E64: 46203 | F64: tabacos | G64: Bea | I64: 19.98
A65: Steam Purchase | B65: Ocio | C65: 20.37 | E65: 46203 | F65: little dragon | G65: Bea | I65: 21.85
A66: LIME*4 VIAJES | B66: Transporte | C66: 15.5 | E66: 46203 | F66: careem | G66: Delivery | I66: 37.35 | J66: 13 jul revol
A67: CAREEM QUIK | B67: Supermercado | C67: 33.36 | E67: 46204 | F67: mercadona | G67: Supermercado | I67: 174.24
A68: LIME*5 VIAJES | B68: Transporte | C68: 14.3 | E68: 46204 | F68: FARMACIA | G68: Salud | I68: 311.03
A69: LIME*3 VIAJES | B69: Transporte | C69: 22.7 | E69: 46205 | F69: florees carlota | G69: Bea | I69: 10
A70: CAREEM HALA | B70: Transporte | C70: 6 | E70: 46205 | F70: ecografia | G70: Salud | I70: 62
A71: CAREEM FOOD | B71: Delivery | C71: 224.95 | E71: 46205 | F71: taxis ecogr | G71: Transporte | I71: 17.6
A72: CAREEM QUIK | B72: Supermercado | C72: 108.67 | E72: 46205 | F72: taxis ecogr | G72: Transporte | I72: 17.99
A73: CAREEM HALA | B73: Transporte | C73: 53 | E73: 46205 | F73: regalo carlota | G73: Regalos | I73: 200
A74: Dott | B74: Transporte | C74: 21.5 | E74: 46205 | F74: desayuno viaje | G74: Restaurantes | I74: 9.9
A75: LIME*VIAJE | B75: Transporte | C75: 64.3 | E75: 46205 | F75: collar | G75: Bea | I75: 21.95
A76: CAREEM DELIVERIES RH | B76: Delivery | C76: 23.53 | E76: 46205 | F76: taxi boda | G76: Transporte | I76: 3.25
A77: CAREEM QUIK | B77: Supermercado | C77: 126.45 | E77: 46205 | F77: vermut zgza | G77: Restaurantes | I77: 11.4
A78: LIME*2 VIAJES | B78: Transporte | C78: 15.5 | E78: 46205 | F78: taxi aeropuerto | G78: Transporte | I78: 30.85
... A91: talabat.com | B91: Delivery | C91: 77.8 | E91: 46208 | F91: peluqueria | G91: Bea | I91: 73
F92: cortefiel | G92: Bea | I92: 55.22
F93: fan cuadros | G93: Hogar | I93: 36
F94: bolt | G94: Transporte | I94: 21.35
F95: aceite marta | G95: Otros | I95: 20.5
F96: vitaminas | G96: Salud | I96: 119.96
F97: cena amigas | G97: Restaurantes | I97: 45
F98: desayuno | G98: Restaurantes | I98: 17
F99: mdeiamarkt | G99: Otros | I99: 5.49
F100: comida aeropuerto | G100: Restaurantes | I100: 22.8
F101: chicles | G101: Bea | I101: 2.2
A105: TOTAL | C105: =SUM(C37:C91)+SUM(D37:D91)/Resumen!$D$1 -> 9191.3433 | D105: =SUM(D37:D91)+SUM(C37:C91)*Resumen!$D$1 -> 2205.9224 | H105: =SUM(H37:H101)+SUM(I37:I101)/Resumen!$D$1 -> 9360.425 | I105: =SUM(I37:I101)+SUM(H37:H91)*Resumen!$D$1 -> 2246.502 | M105: =SUM(M37:M91)+SUM(N37:N91)/Resumen!$D$1 -> 0 | N105: =SUM(N37:N91)+SUM(M37:M91)*Resumen!$D$1 -> 0 | R105: =SUM(R37:R91)+SUM(S37:S91)/Resumen!$D$1 -> 0 | S105: =SUM(S37:S91)+SUM(R37:R91)*Resumen!$D$1 -> 0 | W105: =SUM(W37:W91)+SUM(X37:X91)/Resumen!$D$1 -> 0 | X105: =SUM(X37:X91)+SUM(W37:W91)*Resumen!$D$1 -> 0
A106: RESTANTE | C106: =Resumen!$B$32-C105 -> -6211.3433 | D106: =Resumen!$C$32-D105 -> -1490.7224 | H106: =C106-H105 -> -15571.768 | I106: =D106-I105 -> -3737.2244 | M106: =H106-M105 -> -15571.768 | N106: =I106-N105 -> -3737.2244 | R106: =M106-R105 -> -15571.768 | S106: =N106-S105 -> -3737.2244 | W106: =R106-W105 -> -15571.768 | X106: =S106-X105 -> -3737.2244

Sheet Agosto
A1: INGRESOS MENSUALES
A2: Concepto | C2: Total AED | D2: Total EUR
A3: Salario Santi | C3: =Resumen!$C$4 -> 25000 | D3: =C3*Resumen!$D$1 -> 6000
A4: Salario Bea | C4: =D4/Resumen!$D$1 -> 5000 | D4: =Resumen!$C$5*Resumen!$D$1 -> 1200
A5: Ingresos extra | C5: =D5/Resumen!$D$1 -> 1800 | D5: =Resumen!$C$6*Resumen!$D$1 -> 432
A6: TOTAL INGRESOS | C6: =SUM(C3:C5) -> 31800 | D6: =SUM(D3:D5) -> 7632
A7: BALANCE (Ingreso - Gasto) | C7: =C6-C32 -> 31800 | D7: =D6-D32 -> 7632
A9: GASTOS MENSUALES
A11: RESUMEN POR CATEGORÍA
A12: Categoría | B12: Nº Gastos | C12: Total AED | D12: Total EUR
A13: Restaurantes | B13: =COUNTIF(B37:B56,A13)+COUNTIF(G37:G56,A13)+COUNTIF(L37:L56,A13)+COUNTIF(Q37:Q56,A13)+COUNTIF(V37:V56,A13) -> 0 | C13: =SUMIF(B37:B56,A13,C37:C56)+SUMIF(G37:G56,A13,H37:H56)+SUMIF(L37:L56,A13,M37:M56)+SUMIF(Q37:Q56,A13,R37:R56)+SUMIF(V37:V56,A13,W37:W56)+(SUMIF(B37:B56,A13,D37:D56)+SUMIF(G37:G56,A13,I37:I56)+SUMIF(L37:L56,A13,N37:N56)+SUMIF(Q37:Q56,A13,S37:S56)+SUMIF(V37:V56,A13,X37:X56))/Resumen!$D$1 -> 0 | D13: =C13*Resumen!$D$1 -> 0
A14: Ocio | B14: =COUNTIF(B37:B56,A14)+COUNTIF(G37:G56,A14)+COUNTIF(L37:L56,A14)+COUNTIF(Q37:Q56,A14)+COUNTIF(V37:V56,A14) -> 0 | C14: =SUMIF(B37:B56,A14,C37:C56)+SUMIF(G37:G56,A14,H37:H56)+SUMIF(L37:L56,A14,M37:M56)+SUMIF(Q37:Q56,A14,R37:R56)+SUMIF(V37:V56,A14,W37:W56)+(SUMIF(B37:B56,A14,D37:D56)+SUMIF(G37:G56,A14,I37:I56)+SUMIF(L37:L56,A14,N37:N56)+SUMIF(Q37:Q56,A14,S37:S56)+SUMIF(V37:V56,A14,X37:X56))/Resumen!$D$1 -> 0 | D14: =C14*Resumen!$D$1 -> 0
A15: Compras | B15: =COUNTIF(B37:B56,A15)+COUNTIF(G37:G56,A15)+COUNTIF(L37:L56,A15)+COUNTIF(Q37:Q56,A15)+COUNTIF(V37:V56,A15) -> 0 | C15: =SUMIF(B37:B56,A15,C37:C56)+SUMIF(G37:G56,A15,H37:H56)+SUMIF(L37:L56,A15,M37:M56)+SUMIF(Q37:Q56,A15,R37:R56)+SUMIF(V37:V56,A15,W37:W56)+(SUMIF(B37:B56,A15,D37:D56)+SUMIF(G37:G56,A15,I37:I56)+SUMIF(L37:L56,A15,N37:N56)+SUMIF(Q37:Q56,A15,S37:S56)+SUMIF(V37:V56,A15,X37:X56))/Resumen!$D$1 -> 0 | D15: =C15*Resumen!$D$1 -> 0
A16: Salud | B16: =COUNTIF(B37:B56,A16)+COUNTIF(G37:G56,A16)+COUNTIF(L37:L56,A16)+COUNTIF(Q37:Q56,A16)+COUNTIF(V37:V56,A16) -> 0 | C16: =SUMIF(B37:B56,A16,C37:C56)+SUMIF(G37:G56,A16,H37:H56)+SUMIF(L37:L56,A16,M37:M56)+SUMIF(Q37:Q56,A16,R37:R56)+SUMIF(V37:V56,A16,W37:W56)+(SUMIF(B37:B56,A16,D37:D56)+SUMIF(G37:G56,A16,I37:I56)+SUMIF(L37:L56,A16,N37:N56)+SUMIF(Q37:Q56,A16,S37:S56)+SUMIF(V37:V56,A16,X37:X56))/Resumen!$D$1 -> 0 | D16: =C16*Resumen!$D$1 -> 0
A17: Viajes | B17: =COUNTIF(B37:B56,A17)+COUNTIF(G37:G56,A17)+COUNTIF(L37:L56,A17)+COUNTIF(Q37:Q56,A17)+COUNTIF(V37:V56,A17) -> 0 | C17: =SUMIF(B37:B56,A17,C37:C56)+SUMIF(G37:G56,A17,H37:H56)+SUMIF(L37:L56,A17,M37:M56)+SUMIF(Q37:Q56,A17,R37:R56)+SUMIF(V37:V56,A17,W37:W56)+(SUMIF(B37:B56,A17,D37:D56)+SUMIF(G37:G56,A17,I37:I56)+SUMIF(L37:L56,A17,N37:N56)+SUMIF(Q37:Q56,A17,S37:S56)+SUMIF(V37:V56,A17,X37:X56))/Resumen!$D$1 -> 0 | D17: =C17*Resumen!$D$1 -> 0
A18: Santi | B18: =COUNTIF(B37:B56,A18)+COUNTIF(G37:G56,A18)+COUNTIF(L37:L56,A18)+COUNTIF(Q37:Q56,A18)+COUNTIF(V37:V56,A18) -> 0 | C18: =SUMIF(B37:B56,A18,C37:C56)+SUMIF(G37:G56,A18,H37:H56)+SUMIF(L37:L56,A18,M37:M56)+SUMIF(Q37:Q56,A18,R37:R56)+SUMIF(V37:V56,A18,W37:W56)+(SUMIF(B37:B56,A18,D37:D56)+SUMIF(G37:G56,A18,I37:I56)+SUMIF(L37:L56,A18,N37:N56)+SUMIF(Q37:Q56,A18,S37:S56)+SUMIF(V37:V56,A18,X37:X56))/Resumen!$D$1 -> 0 | D18: =C18*Resumen!$D$1 -> 0
A19: Bea | B19: =COUNTIF(B37:B56,A19)+COUNTIF(G37:G56,A19)+COUNTIF(L37:L56,A19)+COUNTIF(Q37:Q56,A19)+COUNTIF(V37:V56,A19) -> 0 | C19: =SUMIF(B37:B56,A19,C37:C56)+SUMIF(G37:G56,A19,H37:H56)+SUMIF(L37:L56,A19,M37:M56)+SUMIF(Q37:Q56,A19,R37:R56)+SUMIF(V37:V56,A19,W37:W56)+(SUMIF(B37:B56,A19,D37:D56)+SUMIF(G37:G56,A19,I37:I56)+SUMIF(L37:L56,A19,N37:N56)+SUMIF(Q37:Q56,A19,S37:S56)+SUMIF(V37:V56,A19,X37:X56))/Resumen!$D$1 -> 0 | D19: =C19*Resumen!$D$1 -> 0
A20: Personal | B20: =COUNTIF(B37:B56,A20)+COUNTIF(G37:G56,A20)+COUNTIF(L37:L56,A20)+COUNTIF(Q37:Q56,A20)+COUNTIF(V37:V56,A20) -> 0 | C20: =SUMIF(B37:B56,A20,C37:C56)+SUMIF(G37:G56,A20,H37:H56)+SUMIF(L37:L56,A20,M37:M56)+SUMIF(Q37:Q56,A20,R37:R56)+SUMIF(V37:V56,A20,W37:W56)+(SUMIF(B37:B56,A20,D37:D56)+SUMIF(G37:G56,A20,I37:I56)+SUMIF(L37:L56,A20,N37:N56)+SUMIF(Q37:Q56,A20,S37:S56)+SUMIF(V37:V56,A20,X37:X56))/Resumen!$D$1 -> 0 | D20: =C20*Resumen!$D$1 -> 0
A21: Transporte | B21: =COUNTIF(B37:B56,A21)+COUNTIF(G37:G56,A21)+COUNTIF(L37:L56,A21)+COUNTIF(Q37:Q56,A21)+COUNTIF(V37:V56,A21) -> 0 | C21: =SUMIF(B37:B56,A21,C37:C56)+SUMIF(G37:G56,A21,H37:H56)+SUMIF(L37:L56,A21,M37:M56)+SUMIF(Q37:Q56,A21,R37:R56)+SUMIF(V37:V56,A21,W37:W56)+(SUMIF(B37:B56,A21,D37:D56)+SUMIF(G37:G56,A21,I37:I56)+SUMIF(L37:L56,A21,N37:N56)+SUMIF(Q37:Q56,A21,S37:S56)+SUMIF(V37:V56,A21,X37:X56))/Resumen!$D$1 -> 0 | D21: =C21*Resumen!$D$1 -> 0
A22: Regalos | B22: =COUNTIF(B37:B56,A22)+COUNTIF(G37:G56,A22)+COUNTIF(L37:L56,A22)+COUNTIF(Q37:Q56,A22)+COUNTIF(V37:V56,A22) -> 0 | C22: =SUMIF(B37:B56,A22,C37:C56)+SUMIF(G37:G56,A22,H37:H56)+SUMIF(L37:L56,A22,M37:M56)+SUMIF(Q37:Q56,A22,R37:R56)+SUMIF(V37:V56,A22,W37:W56)+(SUMIF(B37:B56,A22,D37:D56)+SUMIF(G37:G56,A22,I37:I56)+SUMIF(L37:L56,A22,N37:N56)+SUMIF(Q37:Q56,A22,S37:S56)+SUMIF(V37:V56,A22,X37:X56))/Resumen!$D$1 -> 0 | D22: =C22*Resumen!$D$1 -> 0
A23: Alquiler piso | B23: =COUNTIF(B37:B56,A23)+COUNTIF(G37:G56,A23)+COUNTIF(L37:L56,A23)+COUNTIF(Q37:Q56,A23)+COUNTIF(V37:V56,A23) -> 0 | C23: =SUMIF(B37:B56,A23,C37:C56)+SUMIF(G37:G56,A23,H37:H56)+SUMIF(L37:L56,A23,M37:M56)+SUMIF(Q37:Q56,A23,R37:R56)+SUMIF(V37:V56,A23,W37:W56)+(SUMIF(B37:B56,A23,D37:D56)+SUMIF(G37:G56,A23,I37:I56)+SUMIF(L37:L56,A23,N37:N56)+SUMIF(Q37:Q56,A23,S37:S56)+SUMIF(V37:V56,A23,X37:X56))/Resumen!$D$1 -> 0 | D23: =C23*Resumen!$D$1 -> 0
A24: Mudanza | B24: =COUNTIF(B37:B56,A24)+COUNTIF(G37:G56,A24)+COUNTIF(L37:L56,A24)+COUNTIF(Q37:Q56,A24)+COUNTIF(V37:V56,A24) -> 0 | C24: =SUMIF(B37:B56,A24,C37:C56)+SUMIF(G37:G56,A24,H37:H56)+SUMIF(L37:L56,A24,M37:M56)+SUMIF(Q37:Q56,A24,R37:R56)+SUMIF(V37:V56,A24,W37:W56)+(SUMIF(B37:B56,A24,D37:D56)+SUMIF(G37:G56,A24,I37:I56)+SUMIF(L37:L56,A24,N37:N56)+SUMIF(Q37:Q56,A24,S37:S56)+SUMIF(V37:V56,A24,X37:X56))/Resumen!$D$1 -> 0 | D24: =C24*Resumen!$D$1 -> 0
A25: Tasas | B25: =COUNTIF(B37:B56,A25)+COUNTIF(G37:G56,A25)+COUNTIF(L37:L56,A25)+COUNTIF(Q37:Q56,A25)+COUNTIF(V37:V56,A25) -> 0 | C25: =SUMIF(B37:B56,A25,C37:C56)+SUMIF(G37:G56,A25,H37:H56)+SUMIF(L37:L56,A25,M37:M56)+SUMIF(Q37:Q56,A25,R37:R56)+SUMIF(V37:V56,A25,W37:W56)+(SUMIF(B37:B56,A25,D37:D56)+SUMIF(G37:G56,A25,I37:I56)+SUMIF(L37:L56,A25,N37:N56)+SUMIF(Q37:Q56,A25,S37:S56)+SUMIF(V37:V56,A25,X37:X56))/Resumen!$D$1 -> 0 | D25: =C25*Resumen!$D$1 -> 0
A26: Suministros piso | B26: =COUNTIF(B37:B56,A26)+COUNTIF(G37:G56,A26)+COUNTIF(L37:L56,A26)+COUNTIF(Q37:Q56,A26)+COUNTIF(V37:V56,A26) -> 0 | C26: =SUMIF(B37:B56,A26,C37:C56)+SUMIF(G37:G56,A26,H37:H56)+SUMIF(L37:L56,A26,M37:M56)+SUMIF(Q37:Q56,A26,R37:R56)+SUMIF(V37:V56,A26,W37:W56)+(SUMIF(B37:B56,A26,D37:D56)+SUMIF(G37:G56,A26,I37:I56)+SUMIF(L37:L56,A26,N37:N56)+SUMIF(Q37:Q56,A26,S37:S56)+SUMIF(V37:V56,A26,X37:X56))/Resumen!$D$1 -> 0 | D26: =C26*Resumen!$D$1 -> 0
A27: Otros | B27: =COUNTIF(B37:B56,A27)+COUNTIF(G37:G56,A27)+COUNTIF(L37:L56,A27)+COUNTIF(Q37:Q56,A27)+COUNTIF(V37:V56,A27) -> 0 | C27: =SUMIF(B37:B56,A27,C37:C56)+SUMIF(G37:G56,A27,H37:H56)+SUMIF(L37:L56,A27,M37:M56)+SUMIF(Q37:Q56,A27,R37:R56)+SUMIF(V37:V56,A27,W37:W56)+(SUMIF(B37:B56,A27,D37:D56)+SUMIF(G37:G56,A27,I37:I56)+SUMIF(L37:L56,A27,N37:N56)+SUMIF(Q37:Q56,A27,S37:S56)+SUMIF(V37:V56,A27,X37:X56))/Resumen!$D$1 -> 0 | D27: =C27*Resumen!$D$1 -> 0
A28: Hogar | B28: =COUNTIF(B37:B56,A28)+COUNTIF(G37:G56,A28)+COUNTIF(L37:L56,A28)+COUNTIF(Q37:Q56,A28)+COUNTIF(V37:V56,A28) -> 0 | C28: =SUMIF(B37:B56,A28,C37:C56)+SUMIF(G37:G56,A28,H37:H56)+SUMIF(L37:L56,A28,M37:M56)+SUMIF(Q37:Q56,A28,R37:R56)+SUMIF(V37:V56,A28,W37:W56)+(SUMIF(B37:B56,A28,D37:D56)+SUMIF(G37:G56,A28,I37:I56)+SUMIF(L37:L56,A28,N37:N56)+SUMIF(Q37:Q56,A28,S37:S56)+SUMIF(V37:V56,A28,X37:X56))/Resumen!$D$1 -> 0 | D28: =C28*Resumen!$D$1 -> 0
A29: Delivery | B29: =COUNTIF(B37:B56,A29)+COUNTIF(G37:G56,A29)+COUNTIF(L37:L56,A29)+COUNTIF(Q37:Q56,A29)+COUNTIF(V37:V56,A29) -> 0 | C29: =SUMIF(B37:B56,A29,C37:C56)+SUMIF(G37:G56,A29,H37:H56)+SUMIF(L37:L56,A29,M37:M56)+SUMIF(Q37:Q56,A29,R37:R56)+SUMIF(V37:V56,A29,W37:W56)+(SUMIF(B37:B56,A29,D37:D56)+SUMIF(G37:G56,A29,I37:I56)+SUMIF(L37:L56,A29,N37:N56)+SUMIF(Q37:Q56,A29,S37:S56)+SUMIF(V37:V56,A29,X37:X56))/Resumen!$D$1 -> 0 | D29: =C29*Resumen!$D$1 -> 0
A30: Supermercado | B30: =COUNTIF(B37:B56,A30)+COUNTIF(G37:G56,A30)+COUNTIF(L37:L56,A30)+COUNTIF(Q37:Q56,A30)+COUNTIF(V37:V56,A30) -> 0 | C30: =SUMIF(B37:B56,A30,C37:C56)+SUMIF(G37:G56,A30,H37:H56)+SUMIF(L37:L56,A30,M37:M56)+SUMIF(Q37:Q56,A30,R37:R56)+SUMIF(V37:V56,A30,W37:W56)+(SUMIF(B37:B56,A30,D37:D56)+SUMIF(G37:G56,A30,I37:I56)+SUMIF(L37:L56,A30,N37:N56)+SUMIF(Q37:Q56,A30,S37:S56)+SUMIF(V37:V56,A30,X37:X56))/Resumen!$D$1 -> 0 | D30: =C30*Resumen!$D$1 -> 0
A31: Suscripciones | B31: =COUNTIF(B37:B56,A31)+COUNTIF(G37:G56,A31)+COUNTIF(L37:L56,A31)+COUNTIF(Q37:Q56,A31)+COUNTIF(V37:V56,A31) -> 0 | C31: =SUMIF(B37:B56,A31,C37:C56)+SUMIF(G37:G56,A31,H37:H56)+SUMIF(L37:L56,A31,M37:M56)+SUMIF(Q37:Q56,A31,R37:R56)+SUMIF(V37:V56,A31,W37:W56)+(SUMIF(B37:B56,A31,D37:D56)+SUMIF(G37:G56,A31,I37:I56)+SUMIF(L37:L56,A31,N37:N56)+SUMIF(Q37:Q56,A31,S37:S56)+SUMIF(V37:V56,A31,X37:X56))/Resumen!$D$1 -> 0 | D31: =C31*Resumen!$D$1 -> 0
A32: TOTAL MES | B32: =SUM(B13:B31) -> 0 | C32: =SUM(C13:C31) -> 0 | D32: =SUM(D13:D31) -> 0
A34: REGISTRO SEMANAL
A35: SEMANA 1 | F35: SEMANA 2 | K35: SEMANA 3 | P35: SEMANA 4 | U35: SEMANA 5
A36: Concepto | B36: Categ. | C36: AED | D36: EUR | E36: Fecha | F36: Concepto | G36: Categ. | H36: AED | I36: EUR | J36: Fecha | K36: Concepto | L36: Categ. | M36: AED | N36: EUR | O36: Fecha | P36: Concepto | Q36: Categ. | R36: AED | S36: EUR | T36: Fecha | U36: Concepto | V36: Categ. | W36: AED | X36: EUR
A57: TOTAL | C57: =SUM(C37:C56)+SUM(D37:D56)/Resumen!$D$1 -> 0 | D57: =SUM(D37:D56)+SUM(C37:C56)*Resumen!$D$1 -> 0 | H57: =SUM(H37:H56)+SUM(I37:I56)/Resumen!$D$1 -> 0 | I57: =SUM(I37:I56)+SUM(H37:H56)*Resumen!$D$1 -> 0 | M57: =SUM(M37:M56)+SUM(N37:N56)/Resumen!$D$1 -> 0 | N57: =SUM(N37:N56)+SUM(M37:M56)*Resumen!$D$1 -> 0 | R57: =SUM(R37:R56)+SUM(S37:S56)/Resumen!$D$1 -> 0 | S57: =SUM(S37:S56)+SUM(R37:R56)*Resumen!$D$1 -> 0 | W57: =SUM(W37:W56)+SUM(X37:X56)/Resumen!$D$1 -> 0 | X57: =SUM(X37:X56)+SUM(W37:W56)*Resumen!$D$1 -> 0
A58: RESTANTE | C58: =Resumen!$B$32-C57 -> 2980 | D58: =Resumen!$C$32-D57 -> 715.2 | H58: =C58-H57 -> 2980 | I58: =D58-I57 -> 715.2 | M58: =H58-M57 -> 2980 | N58: =I58-N57 -> 715.2 | R58: =M58-R57 -> 2980 | S58: =N58-S57 -> 715.2 | W58: =R58-W57 -> 2980 | X58: =S58-X57 -> 715.2

Sheet Septiembre
A1: INGRESOS MENSUALES
A2: Concepto | C2: Total AED | D2: Total EUR
A3: Salario Santi | C3: =Resumen!$C$4 -> 25000 | D3: =C3*Resumen!$D$1 -> 6000
A4: Salario Bea | C4: =D4/Resumen!$D$1 -> 5000 | D4: =Resumen!$C$5*Resumen!$D$1 -> 1200
A5: Ingresos extra | C5: =D5/Resumen!$D$1 -> 1800 | D5: =Resumen!$C$6*Resumen!$D$1 -> 432
A6: TOTAL INGRESOS | C6: =SUM(C3:C5) -> 31800 | D6: =SUM(D3:D5) -> 7632
A7: BALANCE (Ingreso - Gasto) | C7: =C6-C32 -> 31800 | D7: =D6-D32 -> 7632
A9: GASTOS MENSUALES
A11: RESUMEN POR CATEGORÍA
A12: Categoría | B12: Nº Gastos | C12: Total AED | D12: Total EUR
A13: Restaurantes | B13: =COUNTIF(B37:B56,A13)+COUNTIF(G37:G56,A13)+COUNTIF(L37:L56,A13)+COUNTIF(Q37:Q56,A13)+COUNTIF(V37:V56,A13) -> 0 | C13: =SUMIF(B37:B56,A13,C37:C56)+SUMIF(G37:G56,A13,H37:H56)+SUMIF(L37:L56,A13,M37:M56)+SUMIF(Q37:Q56,A13,R37:R56)+SUMIF(V37:V56,A13,W37:W56)+(SUMIF(B37:B56,A13,D37:D56)+SUMIF(G37:G56,A13,I37:I56)+SUMIF(L37:L56,A13,N37:N56)+SUMIF(Q37:Q56,A13,S37:S56)+SUMIF(V37:V56,A13,X37:X56))/Resumen!$D$1 -> 0 | D13: =C13*Resumen!$D$1 -> 0
A14: Ocio | B14: =COUNTIF(B37:B56,A14)+COUNTIF(G37:G56,A14)+COUNTIF(L37:L56,A14)+COUNTIF(Q37:Q56,A14)+COUNTIF(V37:V56,A14) -> 0 | C14: =SUMIF(B37:B56,A14,C37:C56)+SUMIF(G37:G56,A14,H37:H56)+SUMIF(L37:L56,A14,M37:M56)+SUMIF(Q37:Q56,A14,R37:R56)+SUMIF(V37:V56,A14,W37:W56)+(SUMIF(B37:B56,A14,D37:D56)+SUMIF(G37:G56,A14,I37:I56)+SUMIF(L37:L56,A14,N37:N56)+SUMIF(Q37:Q56,A14,S37:S56)+SUMIF(V37:V56,A14,X37:X56))/Resumen!$D$1 -> 0 | D14: =C14*Resumen!$D$1 -> 0
A15: Compras | B15: =COUNTIF(B37:B56,A15)+COUNTIF(G37:G56,A15)+COUNTIF(L37:L56,A15)+COUNTIF(Q37:Q56,A15)+COUNTIF(V37:V56,A15) -> 0 | C15: =SUMIF(B37:B56,A15,C37:C56)+SUMIF(G37:G56,A15,H37:H56)+SUMIF(L37:L56,A15,M37:M56)+SUMIF(Q37:Q56,A15,R37:R56)+SUMIF(V37:V56,A15,W37:W56)+(SUMIF(B37:B56,A15,D37:D56)+SUMIF(G37:G56,A15,I37:I56)+SUMIF(L37:L56,A15,N37:N56)+SUMIF(Q37:Q56,A15,S37:S56)+SUMIF(V37:V56,A15,X37:X56))/Resumen!$D$1 -> 0 | D15: =C15*Resumen!$D$1 -> 0
A16: Salud | B16: =COUNTIF(B37:B56,A16)+COUNTIF(G37:G56,A16)+COUNTIF(L37:L56,A16)+COUNTIF(Q37:Q56,A16)+COUNTIF(V37:V56,A16) -> 0 | C16: =SUMIF(B37:B56,A16,C37:C56)+SUMIF(G37:G56,A16,H37:H56)+SUMIF(L37:L56,A16,M37:M56)+SUMIF(Q37:Q56,A16,R37:R56)+SUMIF(V37:V56,A16,W37:W56)+(SUMIF(B37:B56,A16,D37:D56)+SUMIF(G37:G56,A16,I37:I56)+SUMIF(L37:L56,A16,N37:N56)+SUMIF(Q37:Q56,A16,S37:S56)+SUMIF(V37:V56,A16,X37:X56))/Resumen!$D$1 -> 0 | D16: =C16*Resumen!$D$1 -> 0
A17: Viajes | B17: =COUNTIF(B37:B56,A17)+COUNTIF(G37:G56,A17)+COUNTIF(L37:L56,A17)+COUNTIF(Q37:Q56,A17)+COUNTIF(V37:V56,A17) -> 0 | C17: =SUMIF(B37:B56,A17,C37:C56)+SUMIF(G37:G56,A17,H37:H56)+SUMIF(L37:L56,A17,M37:M56)+SUMIF(Q37:Q56,A17,R37:R56)+SUMIF(V37:V56,A17,W37:W56)+(SUMIF(B37:B56,A17,D37:D56)+SUMIF(G37:G56,A17,I37:I56)+SUMIF(L37:L56,A17,N37:N56)+SUMIF(Q37:Q56,A17,S37:S56)+SUMIF(V37:V56,A17,X37:X56))/Resumen!$D$1 -> 0 | D17: =C17*Resumen!$D$1 -> 0
A18: Santi | B18: =COUNTIF(B37:B56,A18)+COUNTIF(G37:G56,A18)+COUNTIF(L37:L56,A18)+COUNTIF(Q37:Q56,A18)+COUNTIF(V37:V56,A18) -> 0 | C18: =SUMIF(B37:B56,A18,C37:C56)+SUMIF(G37:G56,A18,H37:H56)+SUMIF(L37:L56,A18,M37:M56)+SUMIF(Q37:Q56,A18,R37:R56)+SUMIF(V37:V56,A18,W37:W56)+(SUMIF(B37:B56,A18,D37:D56)+SUMIF(G37:G56,A18,I37:I56)+SUMIF(L37:L56,A18,N37:N56)+SUMIF(Q37:Q56,A18,S37:S56)+SUMIF(V37:V56,A18,X37:X56))/Resumen!$D$1 -> 0 | D18: =C18*Resumen!$D$1 -> 0
A19: Bea | B19: =COUNTIF(B37:B56,A19)+COUNTIF(G37:G56,A19)+COUNTIF(L37:L56,A19)+COUNTIF(Q37:Q56,A19)+COUNTIF(V37:V56,A19) -> 0 | C19: =SUMIF(B37:B56,A19,C37:C56)+SUMIF(G37:G56,A19,H37:H56)+SUMIF(L37:L56,A19,M37:M56)+SUMIF(Q37:Q56,A19,R37:R56)+SUMIF(V37:V56,A19,W37:W56)+(SUMIF(B37:B56,A19,D37:D56)+SUMIF(G37:G56,A19,I37:I56)+SUMIF(L37:L56,A19,N37:N56)+SUMIF(Q37:Q56,A19,S37:S56)+SUMIF(V37:V56,A19,X37:X56))/Resumen!$D$1 -> 0 | D19: =C19*Resumen!$D$1 -> 0
A20: Personal | B20: =COUNTIF(B37:B56,A20)+COUNTIF(G37:G56,A20)+COUNTIF(L37:L56,A20)+COUNTIF(Q37:Q56,A20)+COUNTIF(V37:V56,A20) -> 0 | C20: =SUMIF(B37:B56,A20,C37:C56)+SUMIF(G37:G56,A20,H37:H56)+SUMIF(L37:L56,A20,M37:M56)+SUMIF(Q37:Q56,A20,R37:R56)+SUMIF(V37:V56,A20,W37:W56)+(SUMIF(B37:B56,A20,D37:D56)+SUMIF(G37:G56,A20,I37:I56)+SUMIF(L37:L56,A20,N37:N56)+SUMIF(Q37:Q56,A20,S37:S56)+SUMIF(V37:V56,A20,X37:X56))/Resumen!$D$1 -> 0 | D20: =C20*Resumen!$D$1 -> 0
A21: Transporte | B21: =COUNTIF(B37:B56,A21)+COUNTIF(G37:G56,A21)+COUNTIF(L37:L56,A21)+COUNTIF(Q37:Q56,A21)+COUNTIF(V37:V56,A21) -> 0 | C21: =SUMIF(B37:B56,A21,C37:C56)+SUMIF(G37:G56,A21,H37:H56)+SUMIF(L37:L56,A21,M37:M56)+SUMIF(Q37:Q56,A21,R37:R56)+SUMIF(V37:V56,A21,W37:W56)+(SUMIF(B37:B56,A21,D37:D56)+SUMIF(G37:G56,A21,I37:I56)+SUMIF(L37:L56,A21,N37:N56)+SUMIF(Q37:Q56,A21,S37:S56)+SUMIF(V37:V56,A21,X37:X56))/Resumen!$D$1 -> 0 | D21: =C21*Resumen!$D$1 -> 0
A22: Regalos | B22: =COUNTIF(B37:B56,A22)+COUNTIF(G37:G56,A22)+COUNTIF(L37:L56,A22)+COUNTIF(Q37:Q56,A22)+COUNTIF(V37:V56,A22) -> 0 | C22: =SUMIF(B37:B56,A22,C37:C56)+SUMIF(G37:G56,A22,H37:H56)+SUMIF(L37:L56,A22,M37:M56)+SUMIF(Q37:Q56,A22,R37:R56)+SUMIF(V37:V56,A22,W37:W56)+(SUMIF(B37:B56,A22,D37:D56)+SUMIF(G37:G56,A22,I37:I56)+SUMIF(L37:L56,A22,N37:N56)+SUMIF(Q37:Q56,A22,S37:S56)+SUMIF(V37:V56,A22,X37:X56))/Resumen!$D$1 -> 0 | D22: =C22*Resumen!$D$1 -> 0
A23: Alquiler piso | B23: =COUNTIF(B37:B56,A23)+COUNTIF(G37:G56,A23)+COUNTIF(L37:L56,A23)+COUNTIF(Q37:Q56,A23)+COUNTIF(V37:V56,A23) -> 0 | C23: =SUMIF(B37:B56,A23,C37:C56)+SUMIF(G37:G56,A23,H37:H56)+SUMIF(L37:L56,A23,M37:M56)+SUMIF(Q37:Q56,A23,R37:R56)+SUMIF(V37:V56,A23,W37:W56)+(SUMIF(B37:B56,A23,D37:D56)+SUMIF(G37:G56,A23,I37:I56)+SUMIF(L37:L56,A23,N37:N56)+SUMIF(Q37:Q56,A23,S37:S56)+SUMIF(V37:V56,A23,X37:X56))/Resumen!$D$1 -> 0 | D23: =C23*Resumen!$D$1 -> 0
A24: Mudanza | B24: =COUNTIF(B37:B56,A24)+COUNTIF(G37:G56,A24)+COUNTIF(L37:L56,A24)+COUNTIF(Q37:Q56,A24)+COUNTIF(V37:V56,A24) -> 0 | C24: =SUMIF(B37:B56,A24,C37:C56)+SUMIF(G37:G56,A24,H37:H56)+SUMIF(L37:L56,A24,M37:M56)+SUMIF(Q37:Q56,A24,R37:R56)+SUMIF(V37:V56,A24,W37:W56)+(SUMIF(B37:B56,A24,D37:D56)+SUMIF(G37:G56,A24,I37:I56)+SUMIF(L37:L56,A24,N37:N56)+SUMIF(Q37:Q56,A24,S37:S56)+SUMIF(V37:V56,A24,X37:X56))/Resumen!$D$1 -> 0 | D24: =C24*Resumen!$D$1 -> 0
A25: Tasas | B25: =COUNTIF(B37:B56,A25)+COUNTIF(G37:G56,A25)+COUNTIF(L37:L56,A25)+COUNTIF(Q37:Q56,A25)+COUNTIF(V37:V56,A25) -> 0 | C25: =SUMIF(B37:B56,A25,C37:C56)+SUMIF(G37:G56,A25,H37:H56)+SUMIF(L37:L56,A25,M37:M56)+SUMIF(Q37:Q56,A25,R37:R56)+SUMIF(V37:V56,A25,W37:W56)+(SUMIF(B37:B56,A25,D37:D56)+SUMIF(G37:G56,A25,I37:I56)+SUMIF(L37:L56,A25,N37:N56)+SUMIF(Q37:Q56,A25,S37:S56)+SUMIF(V37:V56,A25,X37:X56))/Resumen!$D$1 -> 0 | D25: =C25*Resumen!$D$1 -> 0
A26: Suministros piso | B26: =COUNTIF(B37:B56,A26)+COUNTIF(G37:G56,A26)+COUNTIF(L37:L56,A26)+COUNTIF(Q37:Q56,A26)+COUNTIF(V37:V56,A26) -> 0 | C26: =SUMIF(B37:B56,A26,C37:C56)+SUMIF(G37:G56,A26,H37:H56)+SUMIF(L37:L56,A26,M37:M56)+SUMIF(Q37:Q56,A26,R37:R56)+SUMIF(V37:V56,A26,W37:W56)+(SUMIF(B37:B56,A26,D37:D56)+SUMIF(G37:G56,A26,I37:I56)+SUMIF(L37:L56,A26,N37:N56)+SUMIF(Q37:Q56,A26,S37:S56)+SUMIF(V37:V56,A26,X37:X56))/Resumen!$D$1 -> 0 | D26: =C26*Resumen!$D$1 -> 0
A27: Otros | B27: =COUNTIF(B37:B56,A27)+COUNTIF(G37:G56,A27)+COUNTIF(L37:L56,A27)+COUNTIF(Q37:Q56,A27)+COUNTIF(V37:V56,A27) -> 0 | C27: =SUMIF(B37:B56,A27,C37:C56)+SUMIF(G37:G56,A27,H37:H56)+SUMIF(L37:L56,A27,M37:M56)+SUMIF(Q37:Q56,A27,R37:R56)+SUMIF(V37:V56,A27,W37:W56)+(SUMIF(B37:B56,A27,D37:D56)+SUMIF(G37:G56,A27,I37:I56)+SUMIF(L37:L56,A27,N37:N56)+SUMIF(Q37:Q56,A27,S37:S56)+SUMIF(V37:V56,A27,X37:X56))/Resumen!$D$1 -> 0 | D27: =C27*Resumen!$D$1 -> 0
A28: Hogar | B28: =COUNTIF(B37:B56,A28)+COUNTIF(G37:G56,A28)+COUNTIF(L37:L56,A28)+COUNTIF(Q37:Q56,A28)+COUNTIF(V37:V56,A28) -> 0 | C28: =SUMIF(B37:B56,A28,C37:C56)+SUMIF(G37:G56,A28,H37:H56)+SUMIF(L37:L56,A28,M37:M56)+SUMIF(Q37:Q56,A28,R37:R56)+SUMIF(V37:V56,A28,W37:W56)+(SUMIF(B37:B56,A28,D37:D56)+SUMIF(G37:G56,A28,I37:I56)+SUMIF(L37:L56,A28,N37:N56)+SUMIF(Q37:Q56,A28,S37:S56)+SUMIF(V37:V56,A28,X37:X56))/Resumen!$D$1 -> 0 | D28: =C28*Resumen!$D$1 -> 0
A29: Delivery | B29: =COUNTIF(B37:B56,A29)+COUNTIF(G37:G56,A29)+COUNTIF(L37:L56,A29)+COUNTIF(Q37:Q56,A29)+COUNTIF(V37:V56,A29) -> 0 | C29: =SUMIF(B37:B56,A29,C37:C56)+SUMIF(G37:G56,A29,H37:H56)+SUMIF(L37:L56,A29,M37:M56)+SUMIF(Q37:Q56,A29,R37:R56)+SUMIF(V37:V56,A29,W37:W56)+(SUMIF(B37:B56,A29,D37:D56)+SUMIF(G37:G56,A29,I37:I56)+SUMIF(L37:L56,A29,N37:N56)+SUMIF(Q37:Q56,A29,S37:S56)+SUMIF(V37:V56,A29,X37:X56))/Resumen!$D$1 -> 0 | D29: =C29*Resumen!$D$1 -> 0
A30: Supermercado | B30: =COUNTIF(B37:B56,A30)+COUNTIF(G37:G56,A30)+COUNTIF(L37:L56,A30)+COUNTIF(Q37:Q56,A30)+COUNTIF(V37:V56,A30) -> 0 | C30: =SUMIF(B37:B56,A30,C37:C56)+SUMIF(G37:G56,A30,H37:H56)+SUMIF(L37:L56,A30,M37:M56)+SUMIF(Q37:Q56,A30,R37:R56)+SUMIF(V37:V56,A30,W37:W56)+(SUMIF(B37:B56,A30,D37:D56)+SUMIF(G37:G56,A30,I37:I56)+SUMIF(L37:L56,A30,N37:N56)+SUMIF(Q37:Q56,A30,S37:S56)+SUMIF(V37:V56,A30,X37:X56))/Resumen!$D$1 -> 0 | D30: =C30*Resumen!$D$1 -> 0
A31: Suscripciones | B31: =COUNTIF(B37:B56,A31)+COUNTIF(G37:G56,A31)+COUNTIF(L37:L56,A31)+COUNTIF(Q37:Q56,A31)+COUNTIF(V37:V56,A31) -> 0 | C31: =SUMIF(B37:B56,A31,C37:C56)+SUMIF(G37:G56,A31,H37:H56)+SUMIF(L37:L56,A31,M37:M56)+SUMIF(Q37:Q56,A31,R37:R56)+SUMIF(V37:V56,A31,W37:W56)+(SUMIF(B37:B56,A31,D37:D56)+SUMIF(G37:G56,A31,I37:I56)+SUMIF(L37:L56,A31,N37:N56)+SUMIF(Q37:Q56,A31,S37:S56)+SUMIF(V37:V56,A31,X37:X56))/Resumen!$D$1 -> 0 | D31: =C31*Resumen!$D$1 -> 0
A32: TOTAL MES | B32: =SUM(B13:B31) -> 0 | C32: =SUM(C13:C31) -> 0 | D32: =SUM(D13:D31) -> 0
A34: REGISTRO SEMANAL
A35: SEMANA 1 | F35: SEMANA 2 | K35: SEMANA 3 | P35: SEMANA 4 | U35: SEMANA 5
A36: Concepto | B36: Categ. | C36: AED | D36: EUR | E36: Fecha | F36: Concepto | G36: Categ. | H36: AED | I36: EUR | J36: Fecha | K36: Concepto | L36: Categ. | M36: AED | N36: EUR | O36: Fecha | P36: Concepto | Q36: Categ. | R36: AED | S36: EUR | T36: Fecha | U36: Concepto | V36: Categ. | W36: AED | X36: EUR
A57: TOTAL | C57: =SUM(C37:C56)+SUM(D37:D56)/Resumen!$D$1 -> 0 | D57: =SUM(D37:D56)+SUM(C37:C56)*Resumen!$D$1 -> 0 | H57: =SUM(H37:H56)+SUM(I37:I56)/Resumen!$D$1 -> 0 | I57: =SUM(I37:I56)+SUM(H37:H56)*Resumen!$D$1 -> 0 | M57: =SUM(M37:M56)+SUM(N37:N56)/Resumen!$D$1 -> 0 | N57: =SUM(N37:N56)+SUM(M37:M56)*Resumen!$D$1 -> 0 | R57: =SUM(R37:R56)+SUM(S37:S56)/Resumen!$D$1 -> 0 | S57: =SUM(S37:S56)+SUM(R37:R56)*Resumen!$D$1 -> 0 | W57: =SUM(W37:W56)+SUM(X37:X56)/Resumen!$D$1 -> 0 | X57: =SUM(X37:X56)+SUM(W37:W56)*Resumen!$D$1 -> 0
A58: RESTANTE | C58: =Resumen!$B$32-C57 -> 2980 | D58: =Resumen!$C$32-D57 -> 715.2 | H58: =C58-H57 -> 2980 | I58: =D58-I57 -> 715.2 | M58: =H58-M57 -> 2980 | N58: =I58-N57 -> 715.2 | R58: =M58-R57 -> 2980 | S58: =N58-S57 -> 715.2 | W58: =R58-W57 -> 2980 | X58: =S58-X57 -> 715.2

Sheet Octubre
A1: INGRESOS MENSUALES
A2: Concepto | C2: Total AED | D2: Total EUR
A3: Salario Santi | C3: =Resumen!$C$4 -> 25000 | D3: =C3*Resumen!$D$1 -> 6000
A4: Salario Bea | C4: =D4/Resumen!$D$1 -> 5000 | D4: =Resumen!$C$5*Resumen!$D$1 -> 1200
A5: Ingresos extra | C5: =D5/Resumen!$D$1 -> 1800 | D5: =Resumen!$C$6*Resumen!$D$1 -> 432
A6: TOTAL INGRESOS | C6: =SUM(C3:C5) -> 31800 | D6: =SUM(D3:D5) -> 7632
A7: BALANCE (Ingreso - Gasto) | C7: =C6-C32 -> 31800 | D7: =D6-D32 -> 7632
A9: GASTOS MENSUALES
A11: RESUMEN POR CATEGORÍA
A12: Categoría | B12: Nº Gastos | C12: Total AED | D12: Total EUR
A13: Restaurantes | B13: =COUNTIF(B37:B56,A13)+COUNTIF(G37:G56,A13)+COUNTIF(L37:L56,A13)+COUNTIF(Q37:Q56,A13)+COUNTIF(V37:V56,A13) -> 0 | C13: =SUMIF(B37:B56,A13,C37:C56)+SUMIF(G37:G56,A13,H37:H56)+SUMIF(L37:L56,A13,M37:M56)+SUMIF(Q37:Q56,A13,R37:R56)+SUMIF(V37:V56,A13,W37:W56)+(SUMIF(B37:B56,A13,D37:D56)+SUMIF(G37:G56,A13,I37:I56)+SUMIF(L37:L56,A13,N37:N56)+SUMIF(Q37:Q56,A13,S37:S56)+SUMIF(V37:V56,A13,X37:X56))/Resumen!$D$1 -> 0 | D13: =C13*Resumen!$D$1 -> 0
A14: Ocio | B14: =COUNTIF(B37:B56,A14)+COUNTIF(G37:G56,A14)+COUNTIF(L37:L56,A14)+COUNTIF(Q37:Q56,A14)+COUNTIF(V37:V56,A14) -> 0 | C14: =SUMIF(B37:B56,A14,C37:C56)+SUMIF(G37:G56,A14,H37:H56)+SUMIF(L37:L56,A14,M37:M56)+SUMIF(Q37:Q56,A14,R37:R56)+SUMIF(V37:V56,A14,W37:W56)+(SUMIF(B37:B56,A14,D37:D56)+SUMIF(G37:G56,A14,I37:I56)+SUMIF(L37:L56,A14,N37:N56)+SUMIF(Q37:Q56,A14,S37:S56)+SUMIF(V37:V56,A14,X37:X56))/Resumen!$D$1 -> 0 | D14: =C14*Resumen!$D$1 -> 0
A15: Compras | B15: =COUNTIF(B37:B56,A15)+COUNTIF(G37:G56,A15)+COUNTIF(L37:L56,A15)+COUNTIF(Q37:Q56,A15)+COUNTIF(V37:V56,A15) -> 0 | C15: =SUMIF(B37:B56,A15,C37:C56)+SUMIF(G37:G56,A15,H37:H56)+SUMIF(L37:L56,A15,M37:M56)+SUMIF(Q37:Q56,A15,R37:R56)+SUMIF(V37:V56,A15,W37:W56)+(SUMIF(B37:B56,A15,D37:D56)+SUMIF(G37:G56,A15,I37:I56)+SUMIF(L37:L56,A15,N37:N56)+SUMIF(Q37:Q56,A15,S37:S56)+SUMIF(V37:V56,A15,X37:X56))/Resumen!$D$1 -> 0 | D15: =C15*Resumen!$D$1 -> 0
A16: Salud | B16: =COUNTIF(B37:B56,A16)+COUNTIF(G37:G56,A16)+COUNTIF(L37:L56,A16)+COUNTIF(Q37:Q56,A16)+COUNTIF(V37:V56,A16) -> 0 | C16: =SUMIF(B37:B56,A16,C37:C56)+SUMIF(G37:G56,A16,H37:H56)+SUMIF(L37:L56,A16,M37:M56)+SUMIF(Q37:Q56,A16,R37:R56)+SUMIF(V37:V56,A16,W37:W56)+(SUMIF(B37:B56,A16,D37:D56)+SUMIF(G37:G56,A16,I37:I56)+SUMIF(L37:L56,A16,N37:N56)+SUMIF(Q37:Q56,A16,S37:S56)+SUMIF(V37:V56,A16,X37:X56))/Resumen!$D$1 -> 0 | D16: =C16*Resumen!$D$1 -> 0
A17: Viajes | B17: =COUNTIF(B37:B56,A17)+COUNTIF(G37:G56,A17)+COUNTIF(L37:L56,A17)+COUNTIF(Q37:Q56,A17)+COUNTIF(V37:V56,A17) -> 0 | C17: =SUMIF(B37:B56,A17,C37:C56)+SUMIF(G37:G56,A17,H37:H56)+SUMIF(L37:L56,A17,M37:M56)+SUMIF(Q37:Q56,A17,R37:R56)+SUMIF(V37:V56,A17,W37:W56)+(SUMIF(B37:B56,A17,D37:D56)+SUMIF(G37:G56,A17,I37:I56)+SUMIF(L37:L56,A17,N37:N56)+SUMIF(Q37:Q56,A17,S37:S56)+SUMIF(V37:V56,A17,X37:X56))/Resumen!$D$1 -> 0 | D17: =C17*Resumen!$D$1 -> 0
A18: Santi | B18: =COUNTIF(B37:B56,A18)+COUNTIF(G37:G56,A18)+COUNTIF(L37:L56,A18)+COUNTIF(Q37:Q56,A18)+COUNTIF(V37:V56,A18) -> 0 | C18: =SUMIF(B37:B56,A18,C37:C56)+SUMIF(G37:G56,A18,H37:H56)+SUMIF(L37:L56,A18,M37:M56)+SUMIF(Q37:Q56,A18,R37:R56)+SUMIF(V37:V56,A18,W37:W56)+(SUMIF(B37:B56,A18,D37:D56)+SUMIF(G37:G56,A18,I37:I56)+SUMIF(L37:L56,A18,N37:N56)+SUMIF(Q37:Q56,A18,S37:S56)+SUMIF(V37:V56,A18,X37:X56))/Resumen!$D$1 -> 0 | D18: =C18*Resumen!$D$1 -> 0
A19: Bea | B19: =COUNTIF(B37:B56,A19)+COUNTIF(G37:G56,A19)+COUNTIF(L37:L56,A19)+COUNTIF(Q37:Q56,A19)+COUNTIF(V37:V56,A19) -> 0 | C19: =SUMIF(B37:B56,A19,C37:C56)+SUMIF(G37:G56,A19,H37:H56)+SUMIF(L37:L56,A19,M37:M56)+SUMIF(Q37:Q56,A19,R37:R56)+SUMIF(V37:V56,A19,W37:W56)+(SUMIF(B37:B56,A19,D37:D56)+SUMIF(G37:G56,A19,I37:I56)+SUMIF(L37:L56,A19,N37:N56)+SUMIF(Q37:Q56,A19,S37:S56)+SUMIF(V37:V56,A19,X37:X56))/Resumen!$D$1 -> 0 | D19: =C19*Resumen!$D$1 -> 0
A20: Personal | B20: =COUNTIF(B37:B56,A20)+COUNTIF(G37:G56,A20)+COUNTIF(L37:L56,A20)+COUNTIF(Q37:Q56,A20)+COUNTIF(V37:V56,A20) -> 0 | C20: =SUMIF(B37:B56,A20,C37:C56)+SUMIF(G37:G56,A20,H37:H56)+SUMIF(L37:L56,A20,M37:M56)+SUMIF(Q37:Q56,A20,R37:R56)+SUMIF(V37:V56,A20,W37:W56)+(SUMIF(B37:B56,A20,D37:D56)+SUMIF(G37:G56,A20,I37:I56)+SUMIF(L37:L56,A20,N37:N56)+SUMIF(Q37:Q56,A20,S37:S56)+SUMIF(V37:V56,A20,X37:X56))/Resumen!$D$1 -> 0 | D20: =C20*Resumen!$D$1 -> 0
A21: Transporte | B21: =COUNTIF(B37:B56,A21)+COUNTIF(G37:G56,A21)+COUNTIF(L37:L56,A21)+COUNTIF(Q37:Q56,A21)+COUNTIF(V37:V56,A21) -> 0 | C21: =SUMIF(B37:B56,A21,C37:C56)+SUMIF(G37:G56,A21,H37:H56)+SUMIF(L37:L56,A21,M37:M56)+SUMIF(Q37:Q56,A21,R37:R56)+SUMIF(V37:V56,A21,W37:W56)+(SUMIF(B37:B56,A21,D37:D56)+SUMIF(G37:G56,A21,I37:I56)+SUMIF(L37:L56,A21,N37:N56)+SUMIF(Q37:Q56,A21,S37:S56)+SUMIF(V37:V56,A21,X37:X56))/Resumen!$D$1 -> 0 | D21: =C21*Resumen!$D$1 -> 0
A22: Regalos | B22: =COUNTIF(B37:B56,A22)+COUNTIF(G37:G56,A22)+COUNTIF(L37:L56,A22)+COUNTIF(Q37:Q56,A22)+COUNTIF(V37:V56,A22) -> 0 | C22: =SUMIF(B37:B56,A22,C37:C56)+SUMIF(G37:G56,A22,H37:H56)+SUMIF(L37:L56,A22,M37:M56)+SUMIF(Q37:Q56,A22,R37:R56)+SUMIF(V37:V56,A22,W37:W56)+(SUMIF(B37:B56,A22,D37:D56)+SUMIF(G37:G56,A22,I37:I56)+SUMIF(L37:L56,A22,N37:N56)+SUMIF(Q37:Q56,A22,S37:S56)+SUMIF(V37:V56,A22,X37:X56))/Resumen!$D$1 -> 0 | D22: =C22*Resumen!$D$1 -> 0
A23: Alquiler piso | B23: =COUNTIF(B37:B56,A23)+COUNTIF(G37:G56,A23)+COUNTIF(L37:L56,A23)+COUNTIF(Q37:Q56,A23)+COUNTIF(V37:V56,A23) -> 0 | C23: =SUMIF(B37:B56,A23,C37:C56)+SUMIF(G37:G56,A23,H37:H56)+SUMIF(L37:L56,A23,M37:M56)+SUMIF(Q37:Q56,A23,R37:R56)+SUMIF(V37:V56,A23,W37:W56)+(SUMIF(B37:B56,A23,D37:D56)+SUMIF(G37:G56,A23,I37:I56)+SUMIF(L37:L56,A23,N37:N56)+SUMIF(Q37:Q56,A23,S37:S56)+SUMIF(V37:V56,A23,X37:X56))/Resumen!$D$1 -> 0 | D23: =C23*Resumen!$D$1 -> 0
A24: Mudanza | B24: =COUNTIF(B37:B56,A24)+COUNTIF(G37:G56,A24)+COUNTIF(L37:L56,A24)+COUNTIF(Q37:Q56,A24)+COUNTIF(V37:V56,A24) -> 0 | C24: =SUMIF(B37:B56,A24,C37:C56)+SUMIF(G37:G56,A24,H37:H56)+SUMIF(L37:L56,A24,M37:M56)+SUMIF(Q37:Q56,A24,R37:R56)+SUMIF(V37:V56,A24,W37:W56)+(SUMIF(B37:B56,A24,D37:D56)+SUMIF(G37:G56,A24,I37:I56)+SUMIF(L37:L56,A24,N37:N56)+SUMIF(Q37:Q56,A24,S37:S56)+SUMIF(V37:V56,A24,X37:X56))/Resumen!$D$1 -> 0 | D24: =C24*Resumen!$D$1 -> 0
A25: Tasas | B25: =COUNTIF(B37:B56,A25)+COUNTIF(G37:G56,A25)+COUNTIF(L37:L56,A25)+COUNTIF(Q37:Q56,A25)+COUNTIF(V37:V56,A25) -> 0 | C25: =SUMIF(B37:B56,A25,C37:C56)+SUMIF(G37:G56,A25,H37:H56)+SUMIF(L37:L56,A25,M37:M56)+SUMIF(Q37:Q56,A25,R37:R56)+SUMIF(V37:V56,A25,W37:W56)+(SUMIF(B37:B56,A25,D37:D56)+SUMIF(G37:G56,A25,I37:I56)+SUMIF(L37:L56,A25,N37:N56)+SUMIF(Q37:Q56,A25,S37:S56)+SUMIF(V37:V56,A25,X37:X56))/Resumen!$D$1 -> 0 | D25: =C25*Resumen!$D$1 -> 0
A26: Suministros piso | B26: =COUNTIF(B37:B56,A26)+COUNTIF(G37:G56,A26)+COUNTIF(L37:L56,A26)+COUNTIF(Q37:Q56,A26)+COUNTIF(V37:V56,A26) -> 0 | C26: =SUMIF(B37:B56,A26,C37:C56)+SUMIF(G37:G56,A26,H37:H56)+SUMIF(L37:L56,A26,M37:M56)+SUMIF(Q37:Q56,A26,R37:R56)+SUMIF(V37:V56,A26,W37:W56)+(SUMIF(B37:B56,A26,D37:D56)+SUMIF(G37:G56,A26,I37:I56)+SUMIF(L37:L56,A26,N37:N56)+SUMIF(Q37:Q56,A26,S37:S56)+SUMIF(V37:V56,A26,X37:X56))/Resumen!$D$1 -> 0 | D26: =C26*Resumen!$D$1 -> 0
A27: Otros | B27: =COUNTIF(B37:B56,A27)+COUNTIF(G37:G56,A27)+COUNTIF(L37:L56,A27)+COUNTIF(Q37:Q56,A27)+COUNTIF(V37:V56,A27) -> 0 | C27: =SUMIF(B37:B56,A27,C37:C56)+SUMIF(G37:G56,A27,H37:H56)+SUMIF(L37:L56,A27,M37:M56)+SUMIF(Q37:Q56,A27,R37:R56)+SUMIF(V37:V56,A27,W37:W56)+(SUMIF(B37:B56,A27,D37:D56)+SUMIF(G37:G56,A27,I37:I56)+SUMIF(L37:L56,A27,N37:N56)+SUMIF(Q37:Q56,A27,S37:S56)+SUMIF(V37:V56,A27,X37:X56))/Resumen!$D$1 -> 0 | D27: =C27*Resumen!$D$1 -> 0
A28: Hogar | B28: =COUNTIF(B37:B56,A28)+COUNTIF(G37:G56,A28)+COUNTIF(L37:L56,A28)+COUNTIF(Q37:Q56,A28)+COUNTIF(V37:V56,A28) -> 0 | C28: =SUMIF(B37:B56,A28,C37:C56)+SUMIF(G37:G56,A28,H37:H56)+SUMIF(L37:L56,A28,M37:M56)+SUMIF(Q37:Q56,A28,R37:R56)+SUMIF(V37:V56,A28,W37:W56)+(SUMIF(B37:B56,A28,D37:D56)+SUMIF(G37:G56,A28,I37:I56)+SUMIF(L37:L56,A28,N37:N56)+SUMIF(Q37:Q56,A28,S37:S56)+SUMIF(V37:V56,A28,X37:X56))/Resumen!$D$1 -> 0 | D28: =C28*Resumen!$D$1 -> 0
A29: Delivery | B29: =COUNTIF(B37:B56,A29)+COUNTIF(G37:G56,A29)+COUNTIF(L37:L56,A29)+COUNTIF(Q37:Q56,A29)+COUNTIF(V37:V56,A29) -> 0 | C29: =SUMIF(B37:B56,A29,C37:C56)+SUMIF(G37:G56,A29,H37:H56)+SUMIF(L37:L56,A29,M37:M56)+SUMIF(Q37:Q56,A29,R37:R56)+SUMIF(V37:V56,A29,W37:W56)+(SUMIF(B37:B56,A29,D37:D56)+SUMIF(G37:G56,A29,I37:I56)+SUMIF(L37:L56,A29,N37:N56)+SUMIF(Q37:Q56,A29,S37:S56)+SUMIF(V37:V56,A29,X37:X56))/Resumen!$D$1 -> 0 | D29: =C29*Resumen!$D$1 -> 0
A30: Supermercado | B30: =COUNTIF(B37:B56,A30)+COUNTIF(G37:G56,A30)+COUNTIF(L37:L56,A30)+COUNTIF(Q37:Q56,A30)+COUNTIF(V37:V56,A30) -> 0 | C30: =SUMIF(B37:B56,A30,C37:C56)+SUMIF(G37:G56,A30,H37:H56)+SUMIF(L37:L56,A30,M37:M56)+SUMIF(Q37:Q56,A30,R37:R56)+SUMIF(V37:V56,A30,W37:W56)+(SUMIF(B37:B56,A30,D37:D56)+SUMIF(G37:G56,A30,I37:I56)+SUMIF(L37:L56,A30,N37:N56)+SUMIF(Q37:Q56,A30,S37:S56)+SUMIF(V37:V56,A30,X37:X56))/Resumen!$D$1 -> 0 | D30: =C30*Resumen!$D$1 -> 0
A31: Suscripciones | B31: =COUNTIF(B37:B56,A31)+COUNTIF(G37:G56,A31)+COUNTIF(L37:L56,A31)+COUNTIF(Q37:Q56,A31)+COUNTIF(V37:V56,A31) -> 0 | C31: =SUMIF(B37:B56,A31,C37:C56)+SUMIF(G37:G56,A31,H37:H56)+SUMIF(L37:L56,A31,M37:M56)+SUMIF(Q37:Q56,A31,R37:R56)+SUMIF(V37:V56,A31,W37:W56)+(SUMIF(B37:B56,A31,D37:D56)+SUMIF(G37:G56,A31,I37:I56)+SUMIF(L37:L56,A31,N37:N56)+SUMIF(Q37:Q56,A31,S37:S56)+SUMIF(V37:V56,A31,X37:X56))/Resumen!$D$1 -> 0 | D31: =C31*Resumen!$D$1 -> 0
A32: TOTAL MES | B32: =SUM(B13:B31) -> 0 | C32: =SUM(C13:C31) -> 0 | D32: =SUM(D13:D31) -> 0
A34: REGISTRO SEMANAL
A35: SEMANA 1 | F35: SEMANA 2 | K35: SEMANA 3 | P35: SEMANA 4 | U35: SEMANA 5
A36: Concepto | B36: Categ. | C36: AED | D36: EUR | E36: Fecha | F36: Concepto | G36: Categ. | H36: AED | I36: EUR | J36: Fecha | K36: Concepto | L36: Categ. | M36: AED | N36: EUR | O36: Fecha | P36: Concepto | Q36: Categ. | R36: AED | S36: EUR | T36: Fecha | U36: Concepto | V36: Categ. | W36: AED | X36: EUR
A57: TOTAL | C57: =SUM(C37:C56)+SUM(D37:D56)/Resumen!$D$1 -> 0 | D57: =SUM(D37:D56)+SUM(C37:C56)*Resumen!$D$1 -> 0 | H57: =SUM(H37:H56)+SUM(I37:I56)/Resumen!$D$1 -> 0 | I57: =SUM(I37:I56)+SUM(H37:H56)*Resumen!$D$1 -> 0 | M57: =SUM(M37:M56)+SUM(N37:N56)/Resumen!$D$1 -> 0 | N57: =SUM(N37:N56)+SUM(M37:M56)*Resumen!$D$1 -> 0 | R57: =SUM(R37:R56)+SUM(S37:S56)/Resumen!$D$1 -> 0 | S57: =SUM(S37:S56)+SUM(R37:R56)*Resumen!$D$1 -> 0 | W57: =SUM(W37:W56)+SUM(X37:X56)/Resumen!$D$1 -> 0 | X57: =SUM(X37:X56)+SUM(W37:W56)*Resumen!$D$1 -> 0
A58: RESTANTE | C58: =Resumen!$B$32-C57 -> 2980 | D58: =Resumen!$C$32-D57 -> 715.2 | H58: =C58-H57 -> 2980 | I58: =D58-I57 -> 715.2 | M58: =H58-M57 -> 2980 | N58: =I58-N57 -> 715.2 | R58: =M58-R57 -> 2980 | S58: =N58-S57 -> 715.2 | W58: =R58-W57 -> 2980 | X58: =S58-X57 -> 715.2

Sheet Noviembre
A1: INGRESOS MENSUALES
A2: Concepto | C2: Total AED | D2: Total EUR
A3: Salario Santi | C3: =Resumen!$C$4 -> 25000 | D3: =C3*Resumen!$D$1 -> 6000
A4: Salario Bea | C4: =D4/Resumen!$D$1 -> 5000 | D4: =Resumen!$C$5*Resumen!$D$1 -> 1200
A5: Ingresos extra | C5: =D5/Resumen!$D$1 -> 1800 | D5: =Resumen!$C$6*Resumen!$D$1 -> 432
A6: TOTAL INGRESOS | C6: =SUM(C3:C5) -> 31800 | D6: =SUM(D3:D5) -> 7632
A7: BALANCE (Ingreso - Gasto) | C7: =C6-C32 -> 31800 | D7: =D6-D32 -> 7632
A9: GASTOS MENSUALES
A11: RESUMEN POR CATEGORÍA
A12: Categoría | B12: Nº Gastos | C12: Total AED | D12: Total EUR
A13: Restaurantes | B13: =COUNTIF(B37:B56,A13)+COUNTIF(G37:G56,A13)+COUNTIF(L37:L56,A13)+COUNTIF(Q37:Q56,A13)+COUNTIF(V37:V56,A13) -> 0 | C13: =SUMIF(B37:B56,A13,C37:C56)+SUMIF(G37:G56,A13,H37:H56)+SUMIF(L37:L56,A13,M37:M56)+SUMIF(Q37:Q56,A13,R37:R56)+SUMIF(V37:V56,A13,W37:W56)+(SUMIF(B37:B56,A13,D37:D56)+SUMIF(G37:G56,A13,I37:I56)+SUMIF(L37:L56,A13,N37:N56)+SUMIF(Q37:Q56,A13,S37:S56)+SUMIF(V37:V56,A13,X37:X56))/Resumen!$D$1 -> 0 | D13: =C13*Resumen!$D$1 -> 0
A14: Ocio | B14: =COUNTIF(B37:B56,A14)+COUNTIF(G37:G56,A14)+COUNTIF(L37:L56,A14)+COUNTIF(Q37:Q56,A14)+COUNTIF(V37:V56,A14) -> 0 | C14: =SUMIF(B37:B56,A14,C37:C56)+SUMIF(G37:G56,A14,H37:H56)+SUMIF(L37:L56,A14,M37:M56)+SUMIF(Q37:Q56,A14,R37:R56)+SUMIF(V37:V56,A14,W37:W56)+(SUMIF(B37:B56,A14,D37:D56)+SUMIF(G37:G56,A14,I37:I56)+SUMIF(L37:L56,A14,N37:N56)+SUMIF(Q37:Q56,A14,S37:S56)+SUMIF(V37:V56,A14,X37:X56))/Resumen!$D$1 -> 0 | D14: =C14*Resumen!$D$1 -> 0
A15: Compras | B15: =COUNTIF(B37:B56,A15)+COUNTIF(G37:G56,A15)+COUNTIF(L37:L56,A15)+COUNTIF(Q37:Q56,A15)+COUNTIF(V37:V56,A15) -> 0 | C15: =SUMIF(B37:B56,A15,C37:C56)+SUMIF(G37:G56,A15,H37:H56)+SUMIF(L37:L56,A15,M37:M56)+SUMIF(Q37:Q56,A15,R37:R56)+SUMIF(V37:V56,A15,W37:W56)+(SUMIF(B37:B56,A15,D37:D56)+SUMIF(G37:G56,A15,I37:I56)+SUMIF(L37:L56,A15,N37:N56)+SUMIF(Q37:Q56,A15,S37:S56)+SUMIF(V37:V56,A15,X37:X56))/Resumen!$D$1 -> 0 | D15: =C15*Resumen!$D$1 -> 0
A16: Salud | B16: =COUNTIF(B37:B56,A16)+COUNTIF(G37:G56,A16)+COUNTIF(L37:L56,A16)+COUNTIF(Q37:Q56,A16)+COUNTIF(V37:V56,A16) -> 0 | C16: =SUMIF(B37:B56,A16,C37:C56)+SUMIF(G37:G56,A16,H37:H56)+SUMIF(L37:L56,A16,M37:M56)+SUMIF(Q37:Q56,A16,R37:R56)+SUMIF(V37:V56,A16,W37:W56)+(SUMIF(B37:B56,A16,D37:D56)+SUMIF(G37:G56,A16,I37:I56)+SUMIF(L37:L56,A16,N37:N56)+SUMIF(Q37:Q56,A16,S37:S56)+SUMIF(V37:V56,A16,X37:X56))/Resumen!$D$1 -> 0 | D16: =C16*Resumen!$D$1 -> 0
A17: Viajes | B17: =COUNTIF(B37:B56,A17)+COUNTIF(G37:G56,A17)+COUNTIF(L37:L56,A17)+COUNTIF(Q37:Q56,A17)+COUNTIF(V37:V56,A17) -> 0 | C17: =SUMIF(B37:B56,A17,C37:C56)+SUMIF(G37:G56,A17,H37:H56)+SUMIF(L37:L56,A17,M37:M56)+SUMIF(Q37:Q56,A17,R37:R56)+SUMIF(V37:V56,A17,W37:W56)+(SUMIF(B37:B56,A17,D37:D56)+SUMIF(G37:G56,A17,I37:I56)+SUMIF(L37:L56,A17,N37:N56)+SUMIF(Q37:Q56,A17,S37:S56)+SUMIF(V37:V56,A17,X37:X56))/Resumen!$D$1 -> 0 | D17: =C17*Resumen!$D$1 -> 0
A18: Santi | B18: =COUNTIF(B37:B56,A18)+COUNTIF(G37:G56,A18)+COUNTIF(L37:L56,A18)+COUNTIF(Q37:Q56,A18)+COUNTIF(V37:V56,A18) -> 0 | C18: =SUMIF(B37:B56,A18,C37:C56)+SUMIF(G37:G56,A18,H37:H56)+SUMIF(L37:L56,A18,M37:M56)+SUMIF(Q37:Q56,A18,R37:R56)+SUMIF(V37:V56,A18,W37:W56)+(SUMIF(B37:B56,A18,D37:D56)+SUMIF(G37:G56,A18,I37:I56)+SUMIF(L37:L56,A18,N37:N56)+SUMIF(Q37:Q56,A18,S37:S56)+SUMIF(V37:V56,A18,X37:X56))/Resumen!$D$1 -> 0 | D18: =C18*Resumen!$D$1 -> 0
A19: Bea | B19: =COUNTIF(B37:B56,A19)+COUNTIF(G37:G56,A19)+COUNTIF(L37:L56,A19)+COUNTIF(Q37:Q56,A19)+COUNTIF(V37:V56,A19) -> 0 | C19: =SUMIF(B37:B56,A19,C37:C56)+SUMIF(G37:G56,A19,H37:H56)+SUMIF(L37:L56,A19,M37:M56)+SUMIF(Q37:Q56,A19,R37:R56)+SUMIF(V37:V56,A19,W37:W56)+(SUMIF(B37:B56,A19,D37:D56)+SUMIF(G37:G56,A19,I37:I56)+SUMIF(L37:L56,A19,N37:N56)+SUMIF(Q37:Q56,A19,S37:S56)+SUMIF(V37:V56,A19,X37:X56))/Resumen!$D$1 -> 0 | D19: =C19*Resumen!$D$1 -> 0
A20: Personal | B20: =COUNTIF(B37:B56,A20)+COUNTIF(G37:G56,A20)+COUNTIF(L37:L56,A20)+COUNTIF(Q37:Q56,A20)+COUNTIF(V37:V56,A20) -> 0 | C20: =SUMIF(B37:B56,A20,C37:C56)+SUMIF(G37:G56,A20,H37:H56)+SUMIF(L37:L56,A20,M37:M56)+SUMIF(Q37:Q56,A20,R37:R56)+SUMIF(V37:V56,A20,W37:W56)+(SUMIF(B37:B56,A20,D37:D56)+SUMIF(G37:G56,A20,I37:I56)+SUMIF(L37:L56,A20,N37:N56)+SUMIF(Q37:Q56,A20,S37:S56)+SUMIF(V37:V56,A20,X37:X56))/Resumen!$D$1 -> 0 | D20: =C20*Resumen!$D$1 -> 0
A21: Transporte | B21: =COUNTIF(B37:B56,A21)+COUNTIF(G37:G56,A21)+COUNTIF(L37:L56,A21)+COUNTIF(Q37:Q56,A21)+COUNTIF(V37:V56,A21) -> 0 | C21: =SUMIF(B37:B56,A21,C37:C56)+SUMIF(G37:G56,A21,H37:H56)+SUMIF(L37:L56,A21,M37:M56)+SUMIF(Q37:Q56,A21,R37:R56)+SUMIF(V37:V56,A21,W37:W56)+(SUMIF(B37:B56,A21,D37:D56)+SUMIF(G37:G56,A21,I37:I56)+SUMIF(L37:L56,A21,N37:N56)+SUMIF(Q37:Q56,A21,S37:S56)+SUMIF(V37:V56,A21,X37:X56))/Resumen!$D$1 -> 0 | D21: =C21*Resumen!$D$1 -> 0
A22: Regalos | B22: =COUNTIF(B37:B56,A22)+COUNTIF(G37:G56,A22)+COUNTIF(L37:L56,A22)+COUNTIF(Q37:Q56,A22)+COUNTIF(V37:V56,A22) -> 0 | C22: =SUMIF(B37:B56,A22,C37:C56)+SUMIF(G37:G56,A22,H37:H56)+SUMIF(L37:L56,A22,M37:M56)+SUMIF(Q37:Q56,A22,R37:R56)+SUMIF(V37:V56,A22,W37:W56)+(SUMIF(B37:B56,A22,D37:D56)+SUMIF(G37:G56,A22,I37:I56)+SUMIF(L37:L56,A22,N37:N56)+SUMIF(Q37:Q56,A22,S37:S56)+SUMIF(V37:V56,A22,X37:X56))/Resumen!$D$1 -> 0 | D22: =C22*Resumen!$D$1 -> 0
A23: Alquiler piso | B23: =COUNTIF(B37:B56,A23)+COUNTIF(G37:G56,A23)+COUNTIF(L37:L56,A23)+COUNTIF(Q37:Q56,A23)+COUNTIF(V37:V56,A23) -> 0 | C23: =SUMIF(B37:B56,A23,C37:C56)+SUMIF(G37:G56,A23,H37:H56)+SUMIF(L37:L56,A23,M37:M56)+SUMIF(Q37:Q56,A23,R37:R56)+SUMIF(V37:V56,A23,W37:W56)+(SUMIF(B37:B56,A23,D37:D56)+SUMIF(G37:G56,A23,I37:I56)+SUMIF(L37:L56,A23,N37:N56)+SUMIF(Q37:Q56,A23,S37:S56)+SUMIF(V37:V56,A23,X37:X56))/Resumen!$D$1 -> 0 | D23: =C23*Resumen!$D$1 -> 0
A24: Mudanza | B24: =COUNTIF(B37:B56,A24)+COUNTIF(G37:G56,A24)+COUNTIF(L37:L56,A24)+COUNTIF(Q37:Q56,A24)+COUNTIF(V37:V56,A24) -> 0 | C24: =SUMIF(B37:B56,A24,C37:C56)+SUMIF(G37:G56,A24,H37:H56)+SUMIF(L37:L56,A24,M37:M56)+SUMIF(Q37:Q56,A24,R37:R56)+SUMIF(V37:V56,A24,W37:W56)+(SUMIF(B37:B56,A24,D37:D56)+SUMIF(G37:G56,A24,I37:I56)+SUMIF(L37:L56,A24,N37:N56)+SUMIF(Q37:Q56,A24,S37:S56)+SUMIF(V37:V56,A24,X37:X56))/Resumen!$D$1 -> 0 | D24: =C24*Resumen!$D$1 -> 0
A25: Tasas | B25: =COUNTIF(B37:B56,A25)+COUNTIF(G37:G56,A25)+COUNTIF(L37:L56,A25)+COUNTIF(Q37:Q56,A25)+COUNTIF(V37:V56,A25) -> 0 | C25: =SUMIF(B37:B56,A25,C37:C56)+SUMIF(G37:G56,A25,H37:H56)+SUMIF(L37:L56,A25,M37:M56)+SUMIF(Q37:Q56,A25,R37:R56)+SUMIF(V37:V56,A25,W37:W56)+(SUMIF(B37:B56,A25,D37:D56)+SUMIF(G37:G56,A25,I37:I56)+SUMIF(L37:L56,A25,N37:N56)+SUMIF(Q37:Q56,A25,S37:S56)+SUMIF(V37:V56,A25,X37:X56))/Resumen!$D$1 -> 0 | D25: =C25*Resumen!$D$1 -> 0
A26: Suministros piso | B26: =COUNTIF(B37:B56,A26)+COUNTIF(G37:G56,A26)+COUNTIF(L37:L56,A26)+COUNTIF(Q37:Q56,A26)+COUNTIF(V37:V56,A26) -> 0 | C26: =SUMIF(B37:B56,A26,C37:C56)+SUMIF(G37:G56,A26,H37:H56)+SUMIF(L37:L56,A26,M37:M56)+SUMIF(Q37:Q56,A26,R37:R56)+SUMIF(V37:V56,A26,W37:W56)+(SUMIF(B37:B56,A26,D37:D56)+SUMIF(G37:G56,A26,I37:I56)+SUMIF(L37:L56,A26,N37:N56)+SUMIF(Q37:Q56,A26,S37:S56)+SUMIF(V37:V56,A26,X37:X56))/Resumen!$D$1 -> 0 | D26: =C26*Resumen!$D$1 -> 0
A27: Otros | B27: =COUNTIF(B37:B56,A27)+COUNTIF(G37:G56,A27)+COUNTIF(L37:L56,A27)+COUNTIF(Q37:Q56,A27)+COUNTIF(V37:V56,A27) -> 0 | C27: =SUMIF(B37:B56,A27,C37:C56)+SUMIF(G37:G56,A27,H37:H56)+SUMIF(L37:L56,A27,M37:M56)+SUMIF(Q37:Q56,A27,R37:R56)+SUMIF(V37:V56,A27,W37:W56)+(SUMIF(B37:B56,A27,D37:D56)+SUMIF(G37:G56,A27,I37:I56)+SUMIF(L37:L56,A27,N37:N56)+SUMIF(Q37:Q56,A27,S37:S56)+SUMIF(V37:V56,A27,X37:X56))/Resumen!$D$1 -> 0 | D27: =C27*Resumen!$D$1 -> 0
A28: Hogar | B28: =COUNTIF(B37:B56,A28)+COUNTIF(G37:G56,A28)+COUNTIF(L37:L56,A28)+COUNTIF(Q37:Q56,A28)+COUNTIF(V37:V56,A28) -> 0 | C28: =SUMIF(B37:B56,A28,C37:C56)+SUMIF(G37:G56,A28,H37:H56)+SUMIF(L37:L56,A28,M37:M56)+SUMIF(Q37:Q56,A28,R37:R56)+SUMIF(V37:V56,A28,W37:W56)+(SUMIF(B37:B56,A28,D37:D56)+SUMIF(G37:G56,A28,I37:I56)+SUMIF(L37:L56,A28,N37:N56)+SUMIF(Q37:Q56,A28,S37:S56)+SUMIF(V37:V56,A28,X37:X56))/Resumen!$D$1 -> 0 | D28: =C28*Resumen!$D$1 -> 0
A29: Delivery | B29: =COUNTIF(B37:B56,A29)+COUNTIF(G37:G56,A29)+COUNTIF(L37:L56,A29)+COUNTIF(Q37:Q56,A29)+COUNTIF(V37:V56,A29) -> 0 | C29: =SUMIF(B37:B56,A29,C37:C56)+SUMIF(G37:G56,A29,H37:H56)+SUMIF(L37:L56,A29,M37:M56)+SUMIF(Q37:Q56,A29,R37:R56)+SUMIF(V37:V56,A29,W37:W56)+(SUMIF(B37:B56,A29,D37:D56)+SUMIF(G37:G56,A29,I37:I56)+SUMIF(L37:L56,A29,N37:N56)+SUMIF(Q37:Q56,A29,S37:S56)+SUMIF(V37:V56,A29,X37:X56))/Resumen!$D$1 -> 0 | D29: =C29*Resumen!$D$1 -> 0
A30: Supermercado | B30: =COUNTIF(B37:B56,A30)+COUNTIF(G37:G56,A30)+COUNTIF(L37:L56,A30)+COUNTIF(Q37:Q56,A30)+COUNTIF(V37:V56,A30) -> 0 | C30: =SUMIF(B37:B56,A30,C37:C56)+SUMIF(G37:G56,A30,H37:H56)+SUMIF(L37:L56,A30,M37:M56)+SUMIF(Q37:Q56,A30,R37:R56)+SUMIF(V37:V56,A30,W37:W56)+(SUMIF(B37:B56,A30,D37:D56)+SUMIF(G37:G56,A30,I37:I56)+SUMIF(L37:L56,A30,N37:N56)+SUMIF(Q37:Q56,A30,S37:S56)+SUMIF(V37:V56,A30,X37:X56))/Resumen!$D$1 -> 0 | D30: =C30*Resumen!$D$1 -> 0
A31: Suscripciones | B31: =COUNTIF(B37:B56,A31)+COUNTIF(G37:G56,A31)+COUNTIF(L37:L56,A31)+COUNTIF(Q37:Q56,A31)+COUNTIF(V37:V56,A31) -> 0 | C31: =SUMIF(B37:B56,A31,C37:C56)+SUMIF(G37:G56,A31,H37:H56)+SUMIF(L37:L56,A31,M37:M56)+SUMIF(Q37:Q56,A31,R37:R56)+SUMIF(V37:V56,A31,W37:W56)+(SUMIF(B37:B56,A31,D37:D56)+SUMIF(G37:G56,A31,I37:I56)+SUMIF(L37:L56,A31,N37:N56)+SUMIF(Q37:Q56,A31,S37:S56)+SUMIF(V37:V56,A31,X37:X56))/Resumen!$D$1 -> 0 | D31: =C31*Resumen!$D$1 -> 0
A32: TOTAL MES | B32: =SUM(B13:B31) -> 0 | C32: =SUM(C13:C31) -> 0 | D32: =SUM(D13:D31) -> 0
A34: REGISTRO SEMANAL
A35: SEMANA 1 | F35: SEMANA 2 | K35: SEMANA 3 | P35: SEMANA 4 | U35: SEMANA 5
A36: Concepto | B36: Categ. | C36: AED | D36: EUR | E36: Fecha | F36: Concepto | G36: Categ. | H36: AED | I36: EUR | J36: Fecha | K36: Concepto | L36: Categ. | M36: AED | N36: EUR | O36: Fecha | P36: Concepto | Q36: Categ. | R36: AED | S36: EUR | T36: Fecha | U36: Concepto | V36: Categ. | W36: AED | X36: EUR
A57: TOTAL | C57: =SUM(C37:C56)+SUM(D37:D56)/Resumen!$D$1 -> 0 | D57: =SUM(D37:D56)+SUM(C37:C56)*Resumen!$D$1 -> 0 | H57: =SUM(H37:H56)+SUM(I37:I56)/Resumen!$D$1 -> 0 | I57: =SUM(I37:I56)+SUM(H37:H56)*Resumen!$D$1 -> 0 | M57: =SUM(M37:M56)+SUM(N37:N56)/Resumen!$D$1 -> 0 | N57: =SUM(N37:N56)+SUM(M37:M56)*Resumen!$D$1 -> 0 | R57: =SUM(R37:R56)+SUM(S37:S56)/Resumen!$D$1 -> 0 | S57: =SUM(S37:S56)+SUM(R37:R56)*Resumen!$D$1 -> 0 | W57: =SUM(W37:W56)+SUM(X37:X56)/Resumen!$D$1 -> 0 | X57: =SUM(X37:X56)+SUM(W37:W56)*Resumen!$D$1 -> 0
A58: RESTANTE | C58: =Resumen!$B$32-C57 -> 2980 | D58: =Resumen!$C$32-D57 -> 715.2 | H58: =C58-H57 -> 2980 | I58: =D58-I57 -> 715.2 | M58: =H58-M57 -> 2980 | N58: =I58-N57 -> 715.2 | R58: =M58-R57 -> 2980 | S58: =N58-S57 -> 715.2 | W58: =R58-W57 -> 2980 | X58: =S58-X57 -> 715.2

Sheet Diciembre
A1: INGRESOS MENSUALES
A2: Concepto | C2: Total AED | D2: Total EUR
A3: Salario Santi | C3: =Resumen!$C$4 -> 25000 | D3: =C3*Resumen!$D$1 -> 6000
A4: Salario Bea | C4: =D4/Resumen!$D$1 -> 5000 | D4: =Resumen!$C$5*Resumen!$D$1 -> 1200
A5: Ingresos extra | C5: =D5/Resumen!$D$1 -> 1800 | D5: =Resumen!$C$6*Resumen!$D$1 -> 432
A6: TOTAL INGRESOS | C6: =SUM(C3:C5) -> 31800 | D6: =SUM(D3:D5) -> 7632
A7: BALANCE (Ingreso - Gasto) | C7: =C6-C32 -> 31800 | D7: =D6-D32 -> 7632
A9: GASTOS MENSUALES
A11: RESUMEN POR CATEGORÍA
A12: Categoría | B12: Nº Gastos | C12: Total AED | D12: Total EUR
A13: Restaurantes | B13: =COUNTIF(B37:B56,A13)+COUNTIF(G37:G56,A13)+COUNTIF(L37:L56,A13)+COUNTIF(Q37:Q56,A13)+COUNTIF(V37:V56,A13) -> 0 | C13: =SUMIF(B37:B56,A13,C37:C56)+SUMIF(G37:G56,A13,H37:H56)+SUMIF(L37:L56,A13,M37:M56)+SUMIF(Q37:Q56,A13,R37:R56)+SUMIF(V37:V56,A13,W37:W56)+(SUMIF(B37:B56,A13,D37:D56)+SUMIF(G37:G56,A13,I37:I56)+SUMIF(L37:L56,A13,N37:N56)+SUMIF(Q37:Q56,A13,S37:S56)+SUMIF(V37:V56,A13,X37:X56))/Resumen!$D$1 -> 0 | D13: =C13*Resumen!$D$1 -> 0
A14: Ocio | B14: =COUNTIF(B37:B56,A14)+COUNTIF(G37:G56,A14)+COUNTIF(L37:L56,A14)+COUNTIF(Q37:Q56,A14)+COUNTIF(V37:V56,A14) -> 0 | C14: =SUMIF(B37:B56,A14,C37:C56)+SUMIF(G37:G56,A14,H37:H56)+SUMIF(L37:L56,A14,M37:M56)+SUMIF(Q37:Q56,A14,R37:R56)+SUMIF(V37:V56,A14,W37:W56)+(SUMIF(B37:B56,A14,D37:D56)+SUMIF(G37:G56,A14,I37:I56)+SUMIF(L37:L56,A14,N37:N56)+SUMIF(Q37:Q56,A14,S37:S56)+SUMIF(V37:V56,A14,X37:X56))/Resumen!$D$1 -> 0 | D14: =C14*Resumen!$D$1 -> 0
A15: Compras | B15: =COUNTIF(B37:B56,A15)+COUNTIF(G37:G56,A15)+COUNTIF(L37:L56,A15)+COUNTIF(Q37:Q56,A15)+COUNTIF(V37:V56,A15) -> 0 | C15: =SUMIF(B37:B56,A15,C37:C56)+SUMIF(G37:G56,A15,H37:H56)+SUMIF(L37:L56,A15,M37:M56)+SUMIF(Q37:Q56,A15,R37:R56)+SUMIF(V37:V56,A15,W37:W56)+(SUMIF(B37:B56,A15,D37:D56)+SUMIF(G37:G56,A15,I37:I56)+SUMIF(L37:L56,A15,N37:N56)+SUMIF(Q37:Q56,A15,S37:S56)+SUMIF(V37:V56,A15,X37:X56))/Resumen!$D$1 -> 0 | D15: =C15*Resumen!$D$1 -> 0
A16: Salud | B16: =COUNTIF(B37:B56,A16)+COUNTIF(G37:G56,A16)+COUNTIF(L37:L56,A16)+COUNTIF(Q37:Q56,A16)+COUNTIF(V37:V56,A16) -> 0 | C16: =SUMIF(B37:B56,A16,C37:C56)+SUMIF(G37:G56,A16,H37:H56)+SUMIF(L37:L56,A16,M37:M56)+SUMIF(Q37:Q56,A16,R37:R56)+SUMIF(V37:V56,A16,W37:W56)+(SUMIF(B37:B56,A16,D37:D56)+SUMIF(G37:G56,A16,I37:I56)+SUMIF(L37:L56,A16,N37:N56)+SUMIF(Q37:Q56,A16,S37:S56)+SUMIF(V37:V56,A16,X37:X56))/Resumen!$D$1 -> 0 | D16: =C16*Resumen!$D$1 -> 0
A17: Viajes | B17: =COUNTIF(B37:B56,A17)+COUNTIF(G37:G56,A17)+COUNTIF(L37:L56,A17)+COUNTIF(Q37:Q56,A17)+COUNTIF(V37:V56,A17) -> 0 | C17: =SUMIF(B37:B56,A17,C37:C56)+SUMIF(G37:G56,A17,H37:H56)+SUMIF(L37:L56,A17,M37:M56)+SUMIF(Q37:Q56,A17,R37:R56)+SUMIF(V37:V56,A17,W37:W56)+(SUMIF(B37:B56,A17,D37:D56)+SUMIF(G37:G56,A17,I37:I56)+SUMIF(L37:L56,A17,N37:N56)+SUMIF(Q37:Q56,A17,S37:S56)+SUMIF(V37:V56,A17,X37:X56))/Resumen!$D$1 -> 0 | D17: =C17*Resumen!$D$1 -> 0
A18: Santi | B18: =COUNTIF(B37:B56,A18)+COUNTIF(G37:G56,A18)+COUNTIF(L37:L56,A18)+COUNTIF(Q37:Q56,A18)+COUNTIF(V37:V56,A18) -> 0 | C18: =SUMIF(B37:B56,A18,C37:C56)+SUMIF(G37:G56,A18,H37:H56)+SUMIF(L37:L56,A18,M37:M56)+SUMIF(Q37:Q56,A18,R37:R56)+SUMIF(V37:V56,A18,W37:W56)+(SUMIF(B37:B56,A18,D37:D56)+SUMIF(G37:G56,A18,I37:I56)+SUMIF(L37:L56,A18,N37:N56)+SUMIF(Q37:Q56,A18,S37:S56)+SUMIF(V37:V56,A18,X37:X56))/Resumen!$D$1 -> 0 | D18: =C18*Resumen!$D$1 -> 0
A19: Bea | B19: =COUNTIF(B37:B56,A19)+COUNTIF(G37:G56,A19)+COUNTIF(L37:L56,A19)+COUNTIF(Q37:Q56,A19)+COUNTIF(V37:V56,A19) -> 0 | C19: =SUMIF(B37:B56,A19,C37:C56)+SUMIF(G37:G56,A19,H37:H56)+SUMIF(L37:L56,A19,M37:M56)+SUMIF(Q37:Q56,A19,R37:R56)+SUMIF(V37:V56,A19,W37:W56)+(SUMIF(B37:B56,A19,D37:D56)+SUMIF(G37:G56,A19,I37:I56)+SUMIF(L37:L56,A19,N37:N56)+SUMIF(Q37:Q56,A19,S37:S56)+SUMIF(V37:V56,A19,X37:X56))/Resumen!$D$1 -> 0 | D19: =C19*Resumen!$D$1 -> 0
A20: Personal | B20: =COUNTIF(B37:B56,A20)+COUNTIF(G37:G56,A20)+COUNTIF(L37:L56,A20)+COUNTIF(Q37:Q56,A20)+COUNTIF(V37:V56,A20) -> 0 | C20: =SUMIF(B37:B56,A20,C37:C56)+SUMIF(G37:G56,A20,H37:H56)+SUMIF(L37:L56,A20,M37:M56)+SUMIF(Q37:Q56,A20,R37:R56)+SUMIF(V37:V56,A20,W37:W56)+(SUMIF(B37:B56,A20,D37:D56)+SUMIF(G37:G56,A20,I37:I56)+SUMIF(L37:L56,A20,N37:N56)+SUMIF(Q37:Q56,A20,S37:S56)+SUMIF(V37:V56,A20,X37:X56))/Resumen!$D$1 -> 0 | D20: =C20*Resumen!$D$1 -> 0
A21: Transporte | B21: =COUNTIF(B37:B56,A21)+COUNTIF(G37:G56,A21)+COUNTIF(L37:L56,A21)+COUNTIF(Q37:Q56,A21)+COUNTIF(V37:V56,A21) -> 0 | C21: =SUMIF(B37:B56,A21,C37:C56)+SUMIF(G37:G56,A21,H37:H56)+SUMIF(L37:L56,A21,M37:M56)+SUMIF(Q37:Q56,A21,R37:R56)+SUMIF(V37:V56,A21,W37:W56)+(SUMIF(B37:B56,A21,D37:D56)+SUMIF(G37:G56,A21,I37:I56)+SUMIF(L37:L56,A21,N37:N56)+SUMIF(Q37:Q56,A21,S37:S56)+SUMIF(V37:V56,A21,X37:X56))/Resumen!$D$1 -> 0 | D21: =C21*Resumen!$D$1 -> 0
A22: Regalos | B22: =COUNTIF(B37:B56,A22)+COUNTIF(G37:G56,A22)+COUNTIF(L37:L56,A22)+COUNTIF(Q37:Q56,A22)+COUNTIF(V37:V56,A22) -> 0 | C22: =SUMIF(B37:B56,A22,C37:C56)+SUMIF(G37:G56,A22,H37:H56)+SUMIF(L37:L56,A22,M37:M56)+SUMIF(Q37:Q56,A22,R37:R56)+SUMIF(V37:V56,A22,W37:W56)+(SUMIF(B37:B56,A22,D37:D56)+SUMIF(G37:G56,A22,I37:I56)+SUMIF(L37:L56,A22,N37:N56)+SUMIF(Q37:Q56,A22,S37:S56)+SUMIF(V37:V56,A22,X37:X56))/Resumen!$D$1 -> 0 | D22: =C22*Resumen!$D$1 -> 0
A23: Alquiler piso | B23: =COUNTIF(B37:B56,A23)+COUNTIF(G37:G56,A23)+COUNTIF(L37:L56,A23)+COUNTIF(Q37:Q56,A23)+COUNTIF(V37:V56,A23) -> 0 | C23: =SUMIF(B37:B56,A23,C37:C56)+SUMIF(G37:G56,A23,H37:H56)+SUMIF(L37:L56,A23,M37:M56)+SUMIF(Q37:Q56,A23,R37:R56)+SUMIF(V37:V56,A23,W37:W56)+(SUMIF(B37:B56,A23,D37:D56)+SUMIF(G37:G56,A23,I37:I56)+SUMIF(L37:L56,A23,N37:N56)+SUMIF(Q37:Q56,A23,S37:S56)+SUMIF(V37:V56,A23,X37:X56))/Resumen!$D$1 -> 0 | D23: =C23*Resumen!$D$1 -> 0
A24: Mudanza | B24: =COUNTIF(B37:B56,A24)+COUNTIF(G37:G56,A24)+COUNTIF(L37:L56,A24)+COUNTIF(Q37:Q56,A24)+COUNTIF(V37:V56,A24) -> 0 | C24: =SUMIF(B37:B56,A24,C37:C56)+SUMIF(G37:G56,A24,H37:H56)+SUMIF(L37:L56,A24,M37:M56)+SUMIF(Q37:Q56,A24,R37:R56)+SUMIF(V37:V56,A24,W37:W56)+(SUMIF(B37:B56,A24,D37:D56)+SUMIF(G37:G56,A24,I37:I56)+SUMIF(L37:L56,A24,N37:N56)+SUMIF(Q37:Q56,A24,S37:S56)+SUMIF(V37:V56,A24,X37:X56))/Resumen!$D$1 -> 0 | D24: =C24*Resumen!$D$1 -> 0
A25: Tasas | B25: =COUNTIF(B37:B56,A25)+COUNTIF(G37:G56,A25)+COUNTIF(L37:L56,A25)+COUNTIF(Q37:Q56,A25)+COUNTIF(V37:V56,A25) -> 0 | C25: =SUMIF(B37:B56,A25,C37:C56)+SUMIF(G37:G56,A25,H37:H56)+SUMIF(L37:L56,A25,M37:M56)+SUMIF(Q37:Q56,A25,R37:R56)+SUMIF(V37:V56,A25,W37:W56)+(SUMIF(B37:B56,A25,D37:D56)+SUMIF(G37:G56,A25,I37:I56)+SUMIF(L37:L56,A25,N37:N56)+SUMIF(Q37:Q56,A25,S37:S56)+SUMIF(V37:V56,A25,X37:X56))/Resumen!$D$1 -> 0 | D25: =C25*Resumen!$D$1 -> 0
A26: Suministros piso | B26: =COUNTIF(B37:B56,A26)+COUNTIF(G37:G56,A26)+COUNTIF(L37:L56,A26)+COUNTIF(Q37:Q56,A26)+COUNTIF(V37:V56,A26) -> 0 | C26: =SUMIF(B37:B56,A26,C37:C56)+SUMIF(G37:G56,A26,H37:H56)+SUMIF(L37:L56,A26,M37:M56)+SUMIF(Q37:Q56,A26,R37:R56)+SUMIF(V37:V56,A26,W37:W56)+(SUMIF(B37:B56,A26,D37:D56)+SUMIF(G37:G56,A26,I37:I56)+SUMIF(L37:L56,A26,N37:N56)+SUMIF(Q37:Q56,A26,S37:S56)+SUMIF(V37:V56,A26,X37:X56))/Resumen!$D$1 -> 0 | D26: =C26*Resumen!$D$1 -> 0
A27: Otros | B27: =COUNTIF(B37:B56,A27)+COUNTIF(G37:G56,A27)+COUNTIF(L37:L56,A27)+COUNTIF(Q37:Q56,A27)+COUNTIF(V37:V56,A27) -> 0 | C27: =SUMIF(B37:B56,A27,C37:C56)+SUMIF(G37:G56,A27,H37:H56)+SUMIF(L37:L56,A27,M37:M56)+SUMIF(Q37:Q56,A27,R37:R56)+SUMIF(V37:V56,A27,W37:W56)+(SUMIF(B37:B56,A27,D37:D56)+SUMIF(G37:G56,A27,I37:I56)+SUMIF(L37:L56,A27,N37:N56)+SUMIF(Q37:Q56,A27,S37:S56)+SUMIF(V37:V56,A27,X37:X56))/Resumen!$D$1 -> 0 | D27: =C27*Resumen!$D$1 -> 0
A28: Hogar | B28: =COUNTIF(B37:B56,A28)+COUNTIF(G37:G56,A28)+COUNTIF(L37:L56,A28)+COUNTIF(Q37:Q56,A28)+COUNTIF(V37:V56,A28) -> 0 | C28: =SUMIF(B37:B56,A28,C37:C56)+SUMIF(G37:G56,A28,H37:H56)+SUMIF(L37:L56,A28,M37:M56)+SUMIF(Q37:Q56,A28,R37:R56)+SUMIF(V37:V56,A28,W37:W56)+(SUMIF(B37:B56,A28,D37:D56)+SUMIF(G37:G56,A28,I37:I56)+SUMIF(L37:L56,A28,N37:N56)+SUMIF(Q37:Q56,A28,S37:S56)+SUMIF(V37:V56,A28,X37:X56))/Resumen!$D$1 -> 0 | D28: =C28*Resumen!$D$1 -> 0
A29: Delivery | B29: =COUNTIF(B37:B56,A29)+COUNTIF(G37:G56,A29)+COUNTIF(L37:L56,A29)+COUNTIF(Q37:Q56,A29)+COUNTIF(V37:V56,A29) -> 0 | C29: =SUMIF(B37:B56,A29,C37:C56)+SUMIF(G37:G56,A29,H37:H56)+SUMIF(L37:L56,A29,M37:M56)+SUMIF(Q37:Q56,A29,R37:R56)+SUMIF(V37:V56,A29,W37:W56)+(SUMIF(B37:B56,A29,D37:D56)+SUMIF(G37:G56,A29,I37:I56)+SUMIF(L37:L56,A29,N37:N56)+SUMIF(Q37:Q56,A29,S37:S56)+SUMIF(V37:V56,A29,X37:X56))/Resumen!$D$1 -> 0 | D29: =C29*Resumen!$D$1 -> 0
A30: Supermercado | B30: =COUNTIF(B37:B56,A30)+COUNTIF(G37:G56,A30)+COUNTIF(L37:L56,A30)+COUNTIF(Q37:Q56,A30)+COUNTIF(V37:V56,A30) -> 0 | C30: =SUMIF(B37:B56,A30,C37:C56)+SUMIF(G37:G56,A30,H37:H56)+SUMIF(L37:L56,A30,M37:M56)+SUMIF(Q37:Q56,A30,R37:R56)+SUMIF(V37:V56,A30,W37:W56)+(SUMIF(B37:B56,A30,D37:D56)+SUMIF(G37:G56,A30,I37:I56)+SUMIF(L37:L56,A30,N37:N56)+SUMIF(Q37:Q56,A30,S37:S56)+SUMIF(V37:V56,A30,X37:X56))/Resumen!$D$1 -> 0 | D30: =C30*Resumen!$D$1 -> 0
A31: Suscripciones | B31: =COUNTIF(B37:B56,A31)+COUNTIF(G37:G56,A31)+COUNTIF(L37:L56,A31)+COUNTIF(Q37:Q56,A31)+COUNTIF(V37:V56,A31) -> 0 | C31: =SUMIF(B37:B56,A31,C37:C56)+SUMIF(G37:G56,A31,H37:H56)+SUMIF(L37:L56,A31,M37:M56)+SUMIF(Q37:Q56,A31,R37:R56)+SUMIF(V37:V56,A31,W37:W56)+(SUMIF(B37:B56,A31,D37:D56)+SUMIF(G37:G56,A31,I37:I56)+SUMIF(L37:L56,A31,N37:N56)+SUMIF(Q37:Q56,A31,S37:S56)+SUMIF(V37:V56,A31,X37:X56))/Resumen!$D$1 -> 0 | D31: =C31*Resumen!$D$1 -> 0
A32: TOTAL MES | B32: =SUM(B13:B31) -> 0 | C32: =SUM(C13:C31) -> 0 | D32: =SUM(D13:D31) -> 0
A34: REGISTRO SEMANAL
A35: SEMANA 1 | F35: SEMANA 2 | K35: SEMANA 3 | P35: SEMANA 4 | U35: SEMANA 5
A36: Concepto | B36: Categ. | C36: AED | D36: EUR | E36: Fecha | F36: Concepto | G36: Categ. | H36: AED | I36: EUR | J36: Fecha | K36: Concepto | L36: Categ. | M36: AED | N36: EUR | O36: Fecha | P36: Concepto | Q36: Categ. | R36: AED | S36: EUR | T36: Fecha | U36: Concepto | V36: Categ. | W36: AED | X36: EUR
A57: TOTAL | C57: =SUM(C37:C56)+SUM(D37:D56)/Resumen!$D$1 -> 0 | D57: =SUM(D37:D56)+SUM(C37:C56)*Resumen!$D$1 -> 0 | H57: =SUM(H37:H56)+SUM(I37:I56)/Resumen!$D$1 -> 0 | I57: =SUM(I37:I56)+SUM(H37:H56)*Resumen!$D$1 -> 0 | M57: =SUM(M37:M56)+SUM(N37:N56)/Resumen!$D$1 -> 0 | N57: =SUM(N37:N56)+SUM(M37:M56)*Resumen!$D$1 -> 0 | R57: =SUM(R37:R56)+SUM(S37:S56)/Resumen!$D$1 -> 0 | S57: =SUM(S37:S56)+SUM(R37:R56)*Resumen!$D$1 -> 0 | W57: =SUM(W37:W56)+SUM(X37:X56)/Resumen!$D$1 -> 0 | X57: =SUM(X37:X56)+SUM(W37:W56)*Resumen!$D$1 -> 0
A58: RESTANTE | C58: =Resumen!$B$32-C57 -> 2980 | D58: =Resumen!$C$32-D57 -> 715.2 | H58: =C58-H57 -> 2980 | I58: =D58-I57 -> 715.2 | M58: =H58-M57 -> 2980 | N58: =I58-N57 -> 715.2 | R58: =M58-R57 -> 2980 | S58: =N58-S57 -> 715.2 | W58: =R58-W57 -> 2980 | X58: =S58-X57 -> 715.2

Sheet _Categorías
A1: Restaurantes
A2: Ocio
A3: Compras
A4: Salud
A5: Viajes
A6: Santi
A7: Bea
A8: Personal
A9: Transporte
A10: Regalos
A11: Hogar
A12: Delivery
... A19: Otros
